Workbook
Name Slicer_Age: #N/A
Name Slicer_Category: #N/A
Name Slicer_Customer_ID: #N/A
Name Slicer_Gender: #N/A
Name Slicer_New_Loyalty: #N/A
Name Slicer_Region: #N/A
Name Slicer_Sales_ID: #N/A
Name Slicer_Store_Type: #N/A
Name Timeline_Order_Date__Delimited1: #N/A

Sheet Customer_Dim
A1: Customer_ID | B1: Name | C1: Age | D1: Gender | E1: City | F1: State | G1: Country | H1: Loyalty_Level
A2: CUST1000 | B2: sheena bonilla | C2: 55 | D2: Male | E2: Donaldton | F2: North Carolina | G2: USA
A3: CUST1001 | B3: Eugene Nelson | C3: 26 | D3: Female | E3: Phillipsmouth | F3: North Dakota | G3: USA | H3: Platinum
A4: CUST1002 | B4: dr. Benjamin Price | C4: 29 | D4: Female | E4: Kylebury | F4: Alabama | G4: USA | H4: Platinum
A5: CUST1003 | B5: jeremy harris | C5: 59 | D5: Female | E5: Thomastown | F5: Ohio | G5: USA | H5: Bronze
A6: CUST1004 | B6: Caroline Collins | C6: 64 | D6: Female | E6: Nicholasshire | F6: California | G6: USA | H6: Silver
A7: CUST1005 | B7: Christine Vaughn | C7: 24 | D7: Male | E7: East Amandamouth | F7: Oregon | G7: USA | H7: Bronze
A8: CUST1006 | B8: Amber Jackson | C8: 29 | D8: Female | E8: Deborahborough | F8: South Dakota | G8: USA | H8: Platinum
A9: CUST1007 | B9: Daniel Boyd | C9: 29 | D9: Female | E9: West Pamelafurt | F9: West Virginia | G9: USA | H9: Bronze
A10: CUST1008 | B10: Melissa Howard | C10: 53 | D10: Female | E10: Maynardton | F10: New Hampshire | G10: USA | H10: Gold
A11: CUST1009 | B11: Ms. Maria Leach | C11: 64 | D11: Male | E11: Melissashire | F11: Pennsylvania | G11: USA | H11: Platinum
A12: CUST1010 | B12: Dominic Page | C12: 53 | D12: Male | E12: Port Michaelburgh | F12: Pennsylvania | G12: USA | H12: Bronze
A13: CUST1011 | B13: Brian Lopez | C13: 28 | D13: Female | E13: East Krista | F13: New York | G13: USA | H13: Gold
A14: CUST1012 | B14: Kenneth Lambert | C14: 55 | D14: Female | E14: North Kathryn | F14: Kansas | G14: USA | H14: Platinum
... A19: CUST1017 | B19: Adam Cruz | C19: 60 | D19: Female | E19: Brandonville | F19: Georgia | G19: USA | H19: Platinum
A20: CUST1018 | B20: Rhonda Moss | C20: 43 | D20: Male | E20: South William | F20: Kansas | G20: USA
A21: CUST1019 | B21: Michael Torres | C21: 46 | D21: Female | E21: Gonzalezfort | F21: New Jersey | G21: USA | H21: Platinum
A22: CUST1020 | B22: Bridget Allen | C22: 59 | D22: Male | E22: Lake Shaneburgh | F22: Delaware | G22: USA | H22: Silver
A23: CUST1021 | B23: Jeff Martinez | C23: 36 | D23: Female | E23: Smithburgh | F23: Oklahoma | G23: USA | H23: Gold
A24: CUST1022 | B24: paul fox | C24: 33 | D24: Female | E24: Michaelton | F24: Hawaii | G24: USA | H24: Silver
A25: CUST1023 | B25: Jonathan Steele | C25: 52 | D25: Female | E25: Molinabury | F25: Oregon | G25: USA | H25: Silver
A26: CUST1024 | B26: Heather Collins | C26: 40 | D26: Male | E26: Rogerschester | F26: Idaho | G26: USA | H26: Platinum
A27: CUST1025 | B27: Diana Taylor | C27: 59 | D27: Female | E27: Vasqueztown | F27: California | G27: USA | H27: Bronze
A28: CUST1026 | B28: Amber Carlson | C28: 18 | D28: Female | E28: East Michellemouth | F28: Missouri | G28: USA | H28: Gold
A29: CUST1027 | B29: Leslie Johnson | C29: 31 | D29: Male | E29: Mollyshire | F29: Utah | G29: USA
A30: CUST1028 | B30: Joshua Ryan | C30: 27 | D30: Female | E30: New David | F30: New Jersey | G30: USA | H30: Platinum
A31: CUST1029 | B31: David Arnold | C31: 54 | D31: Female | E31: East Jennifer | F31: California | G31: USA | H31: Silver
A32: CUST1030 | B32: Jessica Acevedo | C32: 64 | D32: Female | E32: Amybury | F32: Pennsylvania | G32: USA | H32: Bronze
A33: CUST1031 | B33: Sarah Vance | C33: 41 | D33: Male | E33: Johnsonville | F33: Oregon | G33: USA | H33: Silver
A34: CUST1032 | B34: Mike Jennings | C34: 48 | D34: Female | E34: Fostermouth | F34: Arizona | G34: USA | H34: Gold
A35: CUST1033 | B35: Robert Jones DDS | C35: 25 | D35: Male | E35: Tristanton | F35: Oklahoma | G35: USA | H35: Platinum
A36: CUST1034 | B36: Christopher Olson | C36: 27 | D36: Female | E36: West Richard | F36: Maryland | G36: USA | H36: Platinum
A37: CUST1035 | B37: Rachel Myers | C37: 52 | D37: Male | E37: Robertberg | F37: North Dakota | G37: USA | H37: Silver
A38: CUST1036 | B38: Thomas Phillips | C38: 20 | D38: Female | E38: Luisfurt | F38: Georgia | G38: USA | H38: Gold
A39: CUST1037 | B39: Christopher Carter | C39: 27 | D39: Female | E39: Brendastad | F39: South Dakota | G39: USA
A40: CUST1038 | B40: Deanna Simpson | C40: 35 | D40: Female | E40: Brownport | F40: North Dakota | G40: USA | H40: Bronze
A41: CUST1039 | B41: Tonya Reynolds | C41: 55 | D41: Female | E41: Darleneton | F41: Michigan | G41: USA | H41: Gold
A42: CUST1040 | B42: Eric Vega | C42: 50 | D42: Male | E42: Williamsonland | F42: Kansas | G42: USA | H42: Gold
A43: CUST1041 | B43: James Gibbs | C43: 21 | D43: Male | E43: Mooneyshire | F43: Alaska | G43: USA | H43: Platinum
A44: CUST1042 | B44: William Martin | C44: 19 | D44: Male | E44: Ryanburgh | F44: Connecticut | G44: USA | H44: Platinum
A45: CUST1043 | B45: Joseph Snow | C45: 45 | D45: Male | E45: South Michaelfort | F45: Vermont | G45: USA | H45: Gold
A46: CUST1044 | B46: Denise Williams | C46: 34 | D46: Male | E46: Christianstad | F46: Hawaii | G46: USA | H46: Bronze
A47: CUST1045 | B47: Jordan Jackson DDS | C47: 54 | D47: Male | E47: North Johnview | F47: Arizona | G47: USA | H47: Gold
A48: CUST1046 | B48: Michelle Garcia DDS | C48: 55 | D48: Female | E48: Perezbury | F48: Ohio | G48: USA | H48: Platinum
A49: CUST1047 | B49: Gina Knight | C49: 54 | D49: Female | E49: Lake Roberthaven | F49: Nevada | G49: USA | H49: Silver
A50: CUST1048 | B50: April Mullins | C50: 54 | D50: Male | E50: Dawsonbury | F50: North Carolina | G50: USA | H50: Platinum
A51: CUST1049 | B51: Timothy Weaver | C51: 45 | D51: Female | E51: New Amy | F51: Ohio | G51: USA | H51: Gold
... A501: C-1499 | B501: Philip Pennington | C501: 27 | D501: Female | E501: East Valerieview | F501: Oregon | G501: USA | H501: Platinum

Sheet Cleaned Customer Dim
A1: Customer_ID | B1: Name | C1: Proper Name | D1: Age | E1: Gender | F1: City | G1: State | H1: Country | I1: Loyalty_Level | J1: New Loyalty
A2: CUST1000 | B2: Sheena Bonilla | C2: =PROPER($B$2:$B$501) -> Sheena Bonilla | D2: 55 | E2: Male | F2: Donaldton | G2: North Carolina | H2: USA | J2: =IF(I2="","Platinum",I2) -> Platinum | M2: Sum of Age | N2: Column Labels | T2: Age | U2: 55
A3: CUST1001 | B3: Eugene Nelson | C3: =PROPER($B$2:$B$501) -> Eugene Nelson | D3: 26 | E3: Female | F3: Phillipsmouth | G3: North Dakota | H3: USA | I3: Platinum | J3: =IF(I3="","Platinum",I3) -> Platinum | M3: Row Labels | N3: Female | O3: Male
A4: CUST1002 | B4: dr. Benjamin Price | C4: =PROPER($B$2:$B$501) -> Dr. Benjamin Price | D4: 29 | E4: Female | F4: Kylebury | G4: Alabama | H4: USA | I4: Platinum | J4: =IF(I4="","Platinum",I4) -> Platinum | M4: Bronze | N4: 2490 | O4: 2647 | T4: Count of Gender | U4: Column Labels
A5: CUST1003 | B5: jeremy harris | C5: =PROPER($B$2:$B$501) -> Jeremy Harris | D5: 59 | E5: Female | F5: Thomastown | G5: Ohio | H5: USA | I5: Bronze | J5: =IF(I5="","Platinum",I5) -> Bronze | M5: Gold | N5: 2849 | O5: 2107 | T5: Row Labels | U5: Bronze | V5: Gold | W5: Platinum | X5: Silver | Y5: Grand Total
A6: CUST1004 | B6: Caroline Collins | C6: =PROPER($B$2:$B$501) -> Caroline Collins | D6: 64 | E6: Female | F6: Nicholasshire | G6: California | H6: USA | I6: Silver | J6: =IF(I6="","Platinum",I6) -> Silver | M6: Platinum | N6: 3542 | O6: 2879 | T6: USA | U6: 1 | V6: 2 | W6: 5 | X6: 1 | Y6: 9
A7: CUST1005 | B7: Christine Vaughn | C7: =PROPER($B$2:$B$501) -> Christine Vaughn | D7: 24 | E7: Male | F7: East Amandamouth | G7: Oregon | H7: USA | I7: Bronze | J7: =IF(I7="","Platinum",I7) -> Bronze | M7: Silver | N7: 2060 | O7: 2207 | T7: Grand Total | U7: 1 | V7: 2 | W7: 5 | X7: 1 | Y7: 9
A8: CUST1006 | B8: Amber Jackson | C8: =PROPER($B$2:$B$501) -> Amber Jackson | D8: 29 | E8: Female | F8: Deborahborough | G8: South Dakota | H8: USA | I8: Platinum | J8: =IF(I8="","Platinum",I8) -> Platinum | M8: Grand Total | N8: 10941 | O8: 9840
A9: CUST1007 | B9: Daniel Boyd | C9: =PROPER($B$2:$B$501) -> Daniel Boyd | D9: 29 | E9: Female | F9: West Pamelafurt | G9: West Virginia | H9: USA | I9: Bronze | J9: =IF(I9="","Platinum",I9) -> Bronze
A10: CUST1008 | B10: Melissa Howard | C10: =PROPER($B$2:$B$501) -> Melissa Howard | D10: 53 | E10: Female | F10: Maynardton | G10: New Hampshire | H10: USA | I10: Gold | J10: =IF(I10="","Platinum",I10) -> Gold
A11: CUST1009 | B11: Ms. Maria Leach | C11: =PROPER($B$2:$B$501) -> Ms. Maria Leach | D11: 64 | E11: Male | F11: Melissashire | G11: Pennsylvania | H11: USA | I11: Platinum | J11: =IF(I11="","Platinum",I11) -> Platinum | M11: Count of Country | N11: Column Labels
A12: CUST1010 | B12: Dominic Page | C12: =PROPER($B$2:$B$501) -> Dominic Page | D12: 53 | E12: Male | F12: Port Michaelburgh | G12: Pennsylvania | H12: USA | I12: Bronze | J12: =IF(I12="","Platinum",I12) -> Bronze | M12: Row Labels | N12: Bronze | O12: Gold | P12: Platinum | Q12: Silver | R12: Grand Total
A13: CUST1011 | B13: Brian Lopez | C13: =PROPER($B$2:$B$501) -> Brian Lopez | D13: 28 | E13: Female | F13: East Krista | G13: New York | H13: USA | I13: Gold | J13: =IF(I13="","Platinum",I13) -> Gold | M13: Female | N13: 60 | O13: 68 | P13: 83 | Q13: 51 | R13: 262
A14: CUST1012 | B14: Kenneth Lambert | C14: =PROPER($B$2:$B$501) -> Kenneth Lambert | D14: 55 | E14: Female | F14: North Kathryn | G14: Kansas | H14: USA | I14: Platinum | J14: =IF(I14="","Platinum",I14) -> Platinum | M14: Male | N14: 65 | O14: 54 | P14: 66 | Q14: 53 | R14: 238
A15: CUST1013 | B15: Nathan Hernandez | C15: =PROPER($B$2:$B$501) -> Nathan Hernandez | D15: 32 | E15: Female | F15: New Becky | G15: Montana | H15: USA | I15: Silver | J15: =IF(I15="","Platinum",I15) -> Silver | M15: Grand Total | N15: 125 | O15: 122 | P15: 149 | Q15: 104 | R15: 500
A16: CUST1014 | B16: Ashley Cohen | C16: =PROPER($B$2:$B$501) -> Ashley Cohen | D16: 53 | E16: Female | F16: Lake Kristamouth | G16: Nebraska | H16: USA | I16: Silver | J16: =IF(I16="","Platinum",I16) -> Silver
A17: CUST1015 | B17: Laura Alvarez | C17: =PROPER($B$2:$B$501) -> Laura Alvarez | D17: 49 | E17: Female | F17: Lawsonhaven | G17: Washington | H17: USA | I17: Platinum | J17: =IF(I17="","Platinum",I17) -> Platinum | M17: Count of State | N17: Column Labels
A18: CUST1016 | B18: John Scott | C18: =PROPER($B$2:$B$501) -> John Scott | D18: 24 | E18: Female | F18: South Christopher | G18: Pennsylvania | H18: USA | I18: Bronze | J18: =IF(I18="","Platinum",I18) -> Bronze | N18: United States of America | O18: USA | Q18: Grand Total
A19: CUST1017 | B19: Adam Cruz | C19: =PROPER($B$2:$B$501) -> Adam Cruz | D19: 60 | E19: Female | F19: Brandonville | G19: Georgia | H19: USA | I19: Platinum | J19: =IF(I19="","Platinum",I19) -> Platinum | M19: Row Labels | N19: Male | O19: Female | P19: Male
A20: CUST1018 | B20: Rhonda Moss | C20: =PROPER($B$2:$B$501) -> Rhonda Moss | D20: 43 | E20: Male | F20: South William | G20: Kansas | H20: USA | J20: =IF(I20="","Platinum",I20) -> Platinum | M20: Bronze | N20: 1 | O20: 60 | P20: 64 | Q20: 125
A21: CUST1019 | B21: Michael Torres | C21: =PROPER($B$2:$B$501) -> Michael Torres | D21: 46 | E21: Female | F21: Gonzalezfort | G21: New Jersey | H21: USA | I21: Platinum | J21: =IF(I21="","Platinum",I21) -> Platinum | M21: Gold | O21: 68 | P21: 54 | Q21: 122
A22: CUST1020 | B22: Bridget Allen | C22: =PROPER($B$2:$B$501) -> Bridget Allen | D22: 59 | E22: Male | F22: Lake Shaneburgh | G22: Delaware | H22: USA | I22: Silver | J22: =IF(I22="","Platinum",I22) -> Silver | M22: Platinum | N22: 1 | O22: 83 | P22: 65 | Q22: 149
A23: CUST1021 | B23: Jeff Martinez | C23: =PROPER($B$2:$B$501) -> Jeff Martinez | D23: 36 | E23: Female | F23: Smithburgh | G23: Oklahoma | H23: USA | I23: Gold | J23: =IF(I23="","Platinum",I23) -> Gold | M23: Silver | N23: 1 | O23: 51 | P23: 52 | Q23: 104
A24: CUST1022 | B24: Paul Fox | C24: =PROPER($B$2:$B$501) -> Paul Fox | D24: 33 | E24: Female | F24: Michaelton | G24: Hawaii | H24: USA | I24: Silver | J24: =IF(I24="","Platinum",I24) -> Silver | M24: Grand Total | N24: 3 | O24: 262 | P24: 235 | Q24: 500
A25: CUST1023 | B25: Jonathan Steele | C25: =PROPER($B$2:$B$501) -> Jonathan Steele | D25: 52 | E25: Female | F25: Molinabury | G25: Oregon | H25: USA | I25: Silver | J25: =IF(I25="","Platinum",I25) -> Silver
A26: CUST1024 | B26: Heather Collins | C26: =PROPER($B$2:$B$501) -> Heather Collins | D26: 40 | E26: Male | F26: Rogerschester | G26: Idaho | H26: USA | I26: Platinum | J26: =IF(I26="","Platinum",I26) -> Platinum
A27: CUST1025 | B27: Diana Taylor | C27: =PROPER($B$2:$B$501) -> Diana Taylor | D27: 59 | E27: Female | F27: Vasqueztown | G27: California | H27: USA | I27: Bronze | J27: =IF(I27="","Platinum",I27) -> Bronze
A28: CUST1026 | B28: Amber Carlson | C28: =PROPER($B$2:$B$501) -> Amber Carlson | D28: 18 | E28: Female | F28: East Michellemouth | G28: Missouri | H28: USA | I28: Gold | J28: =IF(I28="","Platinum",I28) -> Gold
A29: CUST1027 | B29: Leslie Johnson | C29: =PROPER($B$2:$B$501) -> Leslie Johnson | D29: 31 | E29: Male | F29: Mollyshire | G29: Utah | H29: USA | J29: =IF(I29="","Platinum",I29) -> Platinum
A30: CUST1028 | B30: Joshua Ryan | C30: =PROPER($B$2:$B$501) -> Joshua Ryan | D30: 27 | E30: Female | F30: New David | G30: New Jersey | H30: USA | I30: Platinum | J30: =IF(I30="","Platinum",I30) -> Platinum
A31: CUST1029 | B31: David Arnold | C31: =PROPER($B$2:$B$501) -> David Arnold | D31: 54 | E31: Female | F31: East Jennifer | G31: California | H31: USA | I31: Silver | J31: =IF(I31="","Platinum",I31) -> Silver
A32: CUST1030 | B32: Jessica Acevedo | C32: =PROPER($B$2:$B$501) -> Jessica Acevedo | D32: 64 | E32: Female | F32: Amybury | G32: Pennsylvania | H32: USA | I32: Bronze | J32: =IF(I32="","Platinum",I32) -> Bronze
A33: CUST1031 | B33: Sarah Vance | C33: =PROPER($B$2:$B$501) -> Sarah Vance | D33: 41 | E33: Male | F33: Johnsonville | G33: Oregon | H33: USA | I33: Silver | J33: =IF(I33="","Platinum",I33) -> Silver
A34: CUST1032 | B34: Mike Jennings | C34: =PROPER($B$2:$B$501) -> Mike Jennings | D34: 48 | E34: Female | F34: Fostermouth | G34: Arizona | H34: USA | I34: Gold | J34: =IF(I34="","Platinum",I34) -> Gold
A35: CUST1033 | B35: Robert Jones DDS | C35: =PROPER($B$2:$B$501) -> Robert Jones Dds | D35: 25 | E35: Male | F35: Tristanton | G35: Oklahoma | H35: USA | I35: Platinum | J35: =IF(I35="","Platinum",I35) -> Platinum
A36: CUST1034 | B36: Christopher Olson | C36: =PROPER($B$2:$B$501) -> Christopher Olson | D36: 27 | E36: Female | F36: West Richard | G36: Maryland | H36: USA | I36: Platinum | J36: =IF(I36="","Platinum",I36) -> Platinum
A37: CUST1035 | B37: Rachel Myers | C37: =PROPER($B$2:$B$501) -> Rachel Myers | D37: 52 | E37: Male | F37: Robertberg | G37: North Dakota | H37: USA | I37: Silver | J37: =IF(I37="","Platinum",I37) -> Silver
A38: CUST1036 | B38: Thomas Phillips | C38: =PROPER($B$2:$B$501) -> Thomas Phillips | D38: 20 | E38: Female | F38: Luisfurt | G38: Georgia | H38: USA | I38: Gold | J38: =IF(I38="","Platinum",I38) -> Gold
A39: CUST1037 | B39: Christopher Carter | C39: =PROPER($B$2:$B$501) -> Christopher Carter | D39: 27 | E39: Female | F39: Brendastad | G39: South Dakota | H39: USA | J39: =IF(I39="","Platinum",I39) -> Platinum
A40: CUST1038 | B40: Deanna Simpson | C40: =PROPER($B$2:$B$501) -> Deanna Simpson | D40: 35 | E40: Female | F40: Brownport | G40: North Dakota | H40: USA | I40: Bronze | J40: =IF(I40="","Platinum",I40) -> Bronze
A41: CUST1039 | B41: Tonya Reynolds | C41: =PROPER($B$2:$B$501) -> Tonya Reynolds | D41: 55 | E41: Female | F41: Darleneton | G41: Michigan | H41: USA | I41: Gold | J41: =IF(I41="","Platinum",I41) -> Gold
A42: CUST1040 | B42: Eric Vega | C42: =PROPER($B$2:$B$501) -> Eric Vega | D42: 50 | E42: Male | F42: Williamsonland | G42: Kansas | H42: USA | I42: Gold | J42: =IF(I42="","Platinum",I42) -> Gold
A43: CUST1041 | B43: James Gibbs | C43: =PROPER($B$2:$B$501) -> James Gibbs | D43: 21 | E43: Male | F43: Mooneyshire | G43: Alaska | H43: USA | I43: Platinum | J43: =IF(I43="","Platinum",I43) -> Platinum
A44: CUST1042 | B44: William Martin | C44: =PROPER($B$2:$B$501) -> William Martin | D44: 19 | E44: Male | F44: Ryanburgh | G44: Connecticut | H44: USA | I44: Platinum | J44: =IF(I44="","Platinum",I44) -> Platinum
A45: CUST1043 | B45: Joseph Snow | C45: =PROPER($B$2:$B$501) -> Joseph Snow | D45: 45 | E45: Male | F45: South Michaelfort | G45: Vermont | H45: USA | I45: Gold | J45: =IF(I45="","Platinum",I45) -> Gold
A46: CUST1044 | B46: Denise Williams | C46: =PROPER($B$2:$B$501) -> Denise Williams | D46: 34 | E46: Male | F46: Christianstad | G46: Hawaii | H46: USA | I46: Bronze | J46: =IF(I46="","Platinum",I46) -> Bronze
A47: CUST1045 | B47: Jordan Jackson DDS | C47: =PROPER($B$2:$B$501) -> Jordan Jackson Dds | D47: 54 | E47: Male | F47: North Johnview | G47: Arizona | H47: USA | I47: Gold | J47: =IF(I47="","Platinum",I47) -> Gold
A48: CUST1046 | B48: Michelle Garcia DDS | C48: =PROPER($B$2:$B$501) -> Michelle Garcia Dds | D48: 55 | E48: Female | F48: Perezbury | G48: Ohio | H48: USA | I48: Platinum | J48: =IF(I48="","Platinum",I48) -> Platinum
A49: CUST1047 | B49: Gina Knight | C49: =PROPER($B$2:$B$501) -> Gina Knight | D49: 54 | E49: Female | F49: Lake Roberthaven | G49: Nevada | H49: USA | I49: Silver | J49: =IF(I49="","Platinum",I49) -> Silver
A50: CUST1048 | B50: April Mullins | C50: =PROPER($B$2:$B$501) -> April Mullins | D50: 54 | E50: Male | F50: Dawsonbury | G50: North Carolina | H50: USA | I50: Platinum | J50: =IF(I50="","Platinum",I50) -> Platinum
A51: CUST1049 | B51: Timothy Weaver | C51: =PROPER($B$2:$B$501) -> Timothy Weaver | D51: 45 | E51: Female | F51: New Amy | G51: Ohio | H51: USA | I51: Gold | J51: =IF(I51="","Platinum",I51) -> Gold
... A501: CUST1499 | B501: Philip Pennington | C501: =PROPER($B$2:$B$501) -> Philip Pennington | D501: 27 | E501: Female | F501: East Valerieview | G501: Oregon | H501: USA | I501: Platinum | J501: =IF(I501="","Platinum",I501) -> Platinum
I502: =COUNTA($I$2:$I$501) -> 496
I503: =COUNTIF($I$2:$I$501,"Platinum") -> 145
I504: =COUNTIF(I2:I501,"Gold") -> 122
I505: =COUNTIF(I2:I501,"Silver") -> 104
I506: =COUNTIF(I2:I501,"Bronze") -> 125

Sheet Product_Dim
A1: Product_ID | B1: Product_Name | C1: Category | D1: Sub_Category | E1: Brand | F1: Cost | G1: Stock
A2: PROD0 | B2: Brother Laser Printer | C2: Electronics | D2: Computer | E2: Hunt Inc | F2: 112.42 | G2: 416
A3: PROD1 | B3: Men's Graphic T-Shirt | C3: Clothing | D3: Tops | E3: Terry-Moore | F3: 342.56 | G3: 181
A4: PROD2 | B4: Women's Casual Hoodie | C4: Clothing | D4: Outerwear | E4: Sims Inc | G4: 352
A5: P-3 | B5: Men's Running Jacket | C5: Clothing | D5: Outerwear | E5: Pineda Ltd | F5: 364.67 | G5: 452
A6: PROD4 | B6: Women's Yoga Pants | C6: Clothing | D6: Bottoms | E6: Gonzales-Davis | F6: 306.46 | G6: 487
A7: PROD5 | B7: Men's Leather Belt | C7: Clothing | D7: Accessories | E7: Baldwin, Garza and Gonzalez | F7: 261 | G7: 59
A8: PROD6 | B8: Herbal Face Moisturizer | C8: Beauty | D8: Skincare | E8: Davidson PLC | F8: 312.8 | G8: 350
A9: PROD7 | B9: LED Table Lamp | C9: Home | D9: Lighting | E9: Harrell LLC | F9: 218.86 | G9: 170
A10: PROD8 | B10: Wireless Bluetooth Earbuds | C10: Electronics | D10: Audio | E10: Perez-Johnston | F10: 439.07 | G10: 142
A11: PROD9 | B11: Adjustable Dumbbell Set | C11: Sports | D11: Fitness | E11: Hill PLC | F11: 495.72 | G11: 323
A12: PROD10 | B12: Ceramic Kitchen Bowl Set | C12: Home | D12: Kitchen | E12: Hamilton Group | F12: 298.86 | G12: 308
A13: PROD11 | B13: HD Smart TV Stick | C13: Electronics | D13: Accessories | E13: Gibson, Hobbs and Weaver | F13: 449.4
A14: PROD12 | B14: Hair Strengthening Shampoo | C14: Beauty | D14: Haircare | E14: Rice LLC | F14: 115.82 | G14: 460
A15: PROD13 | B15: USB-C Fast Charger | C15: Electronics | D15: Accessories | E15: Dawson-Perkins | F15: 242.23 | G15: 453
A16: PROD14 | B16: Decorative Wall Mirror | C16: Home | D16: Decor | E16: Luna, Anderson and Bowman | F16: 48.01 | G16: 439
A17: PROD15 | B17: 4K Home Projector | C17: Electronics | D17: Appliances | E17: Thomas LLC | F17: 465.34 | G17: 301
A18: P-16 | B18: Beard Grooming Kit | C18: Beauty | D18: Grooming | E18: Erickson-Green | F18: 337.42 | G18: 256
A19: PROD17 | B19: Soccer Training Cone Set | C19: Sports | D19: Accessories | E19: Ford, Murphy and Wilson | F19: 144.53 | G19: 367
A20: PROD18 | B20: Women's Denim Jeans | C20: Clothing | D20: Bottoms | E20: Guerra-Hendrix | G20: 343
A21: PROD19 | B21: Knee Support Brace | C21: Sports | D21: Equipment | E21: May-Reese | F21: 21.34 | G21: 65
A22: PROD20 | B22: Outdoor Sports Water Bottle | C22: Sports | D22: Accessories | E22: Soto-Ellis | F22: 131.51
A23: PROD21 | B23: Multi-Purpose Storage Box | C23: Home | D23: Storage | E23: Gardner-Montes | F23: 123.46 | G23: 76
A24: PROD22 | B24: Carbon Fiber Tennis Racket | C24: Sports | D24: Equipment | E24: Flores, Pineda and Rodriguez | F24: 484.62 | G24: 432
A25: PROD23 | B25: Men's Formal Shirt | C25: Clothing | D25: Tops | E25: Moon, Mora and Santos | G25: 360
A26: PROD24 | B26: Foldable Camping Chair | C26: Sports | D26: Outdoor | E26: Cook Ltd | F26: 166.06 | G26: 340
A27: PROD25 | B27: Women's Scarf Set | C27: Clothing | D27: Accessories | E27: Brown and Sons | F27: 174.02 | G27: 268
A28: PROD26 | B28: Wireless Bluetooth Speaker | C28: Electronics | D28: Audio | E28: Reed-Schmidt | F28: 322.41 | G28: 213
A29: PROD27 | B29: Decorative Floor Vase | C29: Home | D29: Decor | E29: Khan, Jones and Paul | G29: 378
A30: PROD28 | B30: Sports Stopwatch Timer | C30: Sports | D30: Accessories | E30: Burns-Hansen | F30: 38.76 | G30: 137
A31: PROD29 | B31: Fabric Sofa Throw Blanket | C31: Home | D31: Decor | E31: Hoffman Group | F31: 218.48 | G31: 276
A32: PROD30 | B32: Stainless Steel Cutlery Set | C32: Home | D32: Kitchen | E32: Stevens, Fernandez and Martin | F32: 19.52 | G32: 57
A33: PROD31 | B33: Basketball | C33: Sports | D33: Team Sports | E33: Nolan-Snow | F33: 204.39 | G33: 281
A34: PROD32 | B34: Vitamin C Face Serum | C34: Beauty | D34: Skincare | E34: Griffin Ltd | F34: 283.83 | G34: 244
A35: PROD33 | B35: Modern Wall Clock | C35: Home | D35: Decor | E35: Weiss-Watson | F35: 179.77 | G35: 305
A36: PROD34 | B36: Gaming Mechanical Keyboard | C36: Electronics | D36: Computer | E36: Lucero LLC | F36: 419.28 | G36: 86
A37: PROD35 | B37: Bedroom Table Lamp | C37: Home | D37: Lighting | E37: Jones LLC | F37: 382.22 | G37: 329
A38: PROD36 | B38: Women's Summer Dress | C38: Clothing | D38: Tops | E38: Smith-Mills | F38: 223.43 | G38: 154
A39: PROD37 | B39: Men's Casual Sneakers | C39: Clothing | D39: Footwear | E39: Hogan-Lee | F39: 353.47 | G39: 214
A40: PROD38 | B40: Sports Water Hydration Pack | C40: Sports | D40: Outdoor | E40: Sims-Smith | F40: 135.61 | G40: 394
A41: PROD39 | B41: Portable Power Bank | C41: Electronics | D41: Mobile | E41: Cummings and Sons | F41: 326.06 | G41: 301
... A48: PROD46 | B48: Men's Winter Jacket | C48: Clothing | D48: Outerwear | E48: Kelly, Smith and Perez | F48: 167.34 | G48: 296
A49: PROD47 | B49: Makeup Brush Set | C49: Beauty | D49: Makeup | E49: Cook Inc | G49: 431
A50: PROD48 | B50: Car Dashboard Phone Holder | C50: Electronics | D50: Accessories | E50: Byrd, Stewart and Valdez | F50: 177.98 | G50: 103
A51: PROD49 | B51: Men's Roll-On Perfume | C51: Beauty | D51: Fragrance | E51: Sullivan and Sons | F51: 43.29 | G51: 267
A52: PROD50 | B52: Boxing Hand Wraps | C52: Sports | D52: Fitness | E52: Smith-King | F52: 190.29 | G52: 260
A53: PROD51 | B53: HDMI Cable – 2m | C53: Electronics | D53: Accessories | E53: Bautista, Green and Hale | F53: 88.49 | G53: 246
A54: PROD52 | B54: Rugby Ball | C54: Sports | D54: Team Sports | E54: Harris Inc | F54: 212.26 | G54: 82
A55: PROD53 | B55: Men's Track Pants | C55: Clothing | D55: Bottoms | E55: Hamilton, Woods and Walker | F55: 386.56 | G55: 125
A56: PROD54 | B56: Sports Stopwatch Pro | C56: Sports | D56: Accessories | E56: Thompson-French | F56: 434.84 | G56: 185
A57: PROD55 | B57: Ceramic Plant Pot | C57: Home | D57: Decor | E57: Hatfield, Baird and Torres | F57: 81.75
A58: PROD56 | B58: Premium Blanket Throw | C58: Home | D58: Decor | E58: Hernandez, Kennedy and Porter | F58: 461.47 | G58: 190
A59: PROD57 | B59: Foam Roller | C59: Sports | D59: Fitness | E59: Atkinson, Camacho and Oliver | F59: 30.62 | G59: 138
A60: PROD58 | B60: Womens Cotton Scarf | C60: Clothing | D60: Accessories | E60: Shepherd-Gould | F60: 113.83 | G60: 485
A61: PROD59 | B61: Men's Hair Styling Gel | C61: Beauty | D61: Haircare | E61: Cline-Mccarthy | F61: 17.31 | G61: 399
A62: PROD60 | B62: Luxury Perfume Spray | C62: Beauty | D62: Fragrance | E62: Gibson, Green and Lopez | F62: 482.75 | G62: 444
A63: PROD61 | B63: Tennis Ball 3-Pack | C63: Sports | D63: Equipment | E63: Lopez LLC | F63: 103.45 | G63: 465
A64: PROD62 | B64: Laptop Cooling Pad | C64: Electronics | D64: Computer | E64: Murray, Gould and Ware | F64: 86.42 | G64: 222
A65: PROD63 | B65: Organic Sunscreen Lotion | C65: Beauty | D65: Skincare | E65: Anderson-Riley | F65: 266.86 | G65: 458
A66: PROD64 | B66: Matte Lipstick Set | C66: Beauty | D66: Makeup | E66: Zhang Inc | F66: 299.11 | G66: 118
A67: PROD65 | B67: Adjustable Dumbbells 20kg | C67: Sports | D67: Fitness | E67: Montgomery, Benton and Miller | F67: 240.63 | G67: 423
A68: PROD66 | B68: Women's Hair Dryer Brush | C68: Beauty | D68: Haircare | E68: Torres, Spencer and Potter | F68: 340.39 | G68: 177
A69: PROD67 | B69: Smart LED Light Strip | C69: Electronics | D69: Accessories | E69: Flores-Davis | F69: 349.17 | G69: 476
... A84: PROD82 | B84: Fitness Resistance Bands | C84: Sports | D84: Fitness | E84: Reese-Watson | F84: 152.92 | G84: 281
A85: PROD83 | B85: Hydrating Face Cleanser | C85: Beauty | D85: Skincare | E85: Butler Group | G85: 159
A86: PROD84 | B86: Wooden Bookshelf | C86: Home | D86: Furniture | E86: Collins-Stephenson | F86: 388.46 | G86: 208
A87: PROD85 | B87: Women's Beanie Hat | C87: Clothing | D87: Accessories | E87: Richardson-Carrillo | F87: 119.57 | G87: 210
A88: PROD86 | B88: Kitchen Cutting Board | C88: Home | D88: Kitchen | E88: Taylor, Dodson and Johnston | F88: 176.07 | G88: 82
A89: PROD87 | B89: LED Bedside Lamp | C89: Home | D89: Lighting | E89: Aguilar, Horton and Lewis | F89: 371.38 | G89: 220
A90: PROD88 | B90: Sports Wrist Sweatbands | C90: Sports | D90: Accessories | E90: Olsen-Daniels | F90: 131.24 | G90: 232
A91: PROD89 | B91: Face Foundation Kit | C91: Beauty | D91: Makeup | E91: Taylor-Elliott | F91: 183.04 | G91: 457
A92: PROD90 | B92: Gaming Mouse Pad XL | C92: Electronics | D92: Accessories | E92: Sharp, Taylor and Rodriguez | F92: 340.14 | G92: 361
A93: PROD91 | B93: Women's High Heels | C93: Clothing | D93: Footwear | E93: Smith-Charles | F93: 438.25 | G93: 496
A94: PROD92 | B94: Microwave Oven | C94: Home | D94: Appliances | E94: Green, Powell and Palmer | F94: 447.43 | G94: 191
A95: PROD93 | B95: USB-C Laptop Charger | C95: Electronics | D95: Computer | E95: Martin LLC | F95: 377.52 | G95: 485
A96: PROD94 | B96: Vitamin E Body Lotion | C96: Beauty | D96: Skincare | E96: Hoffman-Williams | F96: 358.47 | G96: 213
A97: PROD95 | B97: Sports Stopwatch Basic | C97: Sports | D97: Accessories | E97: Wilson Group | F97: 60.65 | G97: 75
... A101: PROD99 | B101: Stainless Steel Cookware Set | C101: Home | D101: Kitchen | E101: Campbell Ltd | F101: 201.41 | G101: 146

Sheet Cleaned Product Dim
A1: Product_ID | B1: Product_Name | C1: Category | D1: Brand | E1: Cost | F1: Stock | G1: New Cost | H1: New Stock
A2: PROD0 | B2: Brother Laser Printer | C2: Electronics | D2: Hunt Inc | E2: 112.42 | F2: 416 | G2: =IF(E2="",AVERAGEIF(($C$2:$C$101),C2,($E$2:$E$101)),E2) -> 112.42 | H2: =IF(F2="",AVERAGEIF(($C$2:$C$101),C2,($F$2:$F$101)),F2) -> 416 | K2: New Cost | M2: New Stock
A3: PROD1 | B3: Men's Graphic T-Shirt | C3: Clothing | D3: Terry-Moore | E3: 342.56 | F3: 181 | G3: =IF(E3="",AVERAGEIF(($C$2:$C$101),C3,($E$2:$E$101)),E3) -> 342.56 | H3: =IF(F3="",AVERAGEIF(($C$2:$C$101),C3,($F$2:$F$101)),F3) -> 181
A4: PROD2 | B4: Women's Casual Hoodie | C4: Clothing | D4: Sims Inc | F4: 352 | G4: =IF(E4="",AVERAGEIF(($C$2:$C$101),C4,($E$2:$E$101)),E4) -> 265.73267 | H4: =IF(F4="",AVERAGEIF(($C$2:$C$101),C4,($F$2:$F$101)),F4) -> 352 | K4: Mean | L4: 254.12936 | M4: Mean | N4: 273.11708
A5: PROD3 | B5: Men's Running Jacket | C5: Clothing | D5: Pineda Ltd | E5: 364.67 | F5: 452 | G5: =IF(E5="",AVERAGEIF(($C$2:$C$101),C5,($E$2:$E$101)),E5) -> 364.67 | H5: =IF(F5="",AVERAGEIF(($C$2:$C$101),C5,($F$2:$F$101)),F5) -> 452 | K5: Standard Error | L5: 13.085141 | M5: Standard Error | N5: 13.004017
A6: PROD4 | B6: Women's Yoga Pants | C6: Clothing | D6: Gonzales-Davis | E6: 306.46 | F6: 487 | G6: =IF(E6="",AVERAGEIF(($C$2:$C$101),C6,($E$2:$E$101)),E6) -> 306.46 | H6: =IF(F6="",AVERAGEIF(($C$2:$C$101),C6,($F$2:$F$101)),F6) -> 487 | K6: Median | L6: 248.19808 | M6: Median | N6: 275.35
A7: PROD5 | B7: Men's Leather Belt | C7: Clothing | D7: Baldwin, Garza and Gonzalez | E7: 261 | F7: 59 | G7: =IF(E7="",AVERAGEIF(($C$2:$C$101),C7,($E$2:$E$101)),E7) -> 261 | H7: =IF(F7="",AVERAGEIF(($C$2:$C$101),C7,($F$2:$F$101)),F7) -> 59 | K7: Mode | L7: 265.73267 | M7: Mode | N7: 82
A8: PROD6 | B8: Herbal Face Moisturizer | C8: Beauty | D8: Davidson PLC | E8: 312.8 | F8: 350 | G8: =IF(E8="",AVERAGEIF(($C$2:$C$101),C8,($E$2:$E$101)),E8) -> 312.8 | H8: =IF(F8="",AVERAGEIF(($C$2:$C$101),C8,($F$2:$F$101)),F8) -> 350 | K8: Standard Deviation | L8: 130.85141 | M8: Standard Deviation | N8: 130.04017
A9: PROD7 | B9: LED Table Lamp | C9: Home | D9: Harrell LLC | E9: 218.86 | F9: 170 | G9: =IF(E9="",AVERAGEIF(($C$2:$C$101),C9,($E$2:$E$101)),E9) -> 218.86 | H9: =IF(F9="",AVERAGEIF(($C$2:$C$101),C9,($F$2:$F$101)),F9) -> 170 | K9: Sample Variance | L9: 17122.09 | M9: Sample Variance | N9: 16910.445
A10: PROD8 | B10: Wireless Bluetooth Earbuds | C10: Electronics | D10: Perez-Johnston | E10: 439.07 | F10: 142 | G10: =IF(E10="",AVERAGEIF(($C$2:$C$101),C10,($E$2:$E$101)),E10) -> 439.07 | H10: =IF(F10="",AVERAGEIF(($C$2:$C$101),C10,($F$2:$F$101)),F10) -> 142 | K10: Kurtosis | L10: -0.95127662 | M10: Kurtosis | N10: -1.158146
A11: PROD9 | B11: Adjustable Dumbbell Set | C11: Sports | D11: Hill PLC | E11: 495.72 | F11: 323 | G11: =IF(E11="",AVERAGEIF(($C$2:$C$101),C11,($E$2:$E$101)),E11) -> 495.72 | H11: =IF(F11="",AVERAGEIF(($C$2:$C$101),C11,($F$2:$F$101)),F11) -> 323 | K11: Skewness | L11: 0.050263902 | M11: Skewness | N11: 0.00071961406
A12: PROD10 | B12: Ceramic Kitchen Bowl Set | C12: Home | D12: Hamilton Group | E12: 298.86 | F12: 308 | G12: =IF(E12="",AVERAGEIF(($C$2:$C$101),C12,($E$2:$E$101)),E12) -> 298.86 | H12: =IF(F12="",AVERAGEIF(($C$2:$C$101),C12,($F$2:$F$101)),F12) -> 308 | K12: Range | L12: 478.41 | M12: Range | N12: 439
A13: PROD11 | B13: HD Smart TV Stick | C13: Electronics | D13: Gibson, Hobbs and Weaver | E13: 449.4 | G13: =IF(E13="",AVERAGEIF(($C$2:$C$101),C13,($E$2:$E$101)),E13) -> 449.4 | H13: =IF(F13="",AVERAGEIF(($C$2:$C$101),C13,($F$2:$F$101)),F13) -> 274.7 | K13: Minimum | L13: 17.31 | M13: Minimum | N13: 57
A14: PROD12 | B14: Hair Strengthening Shampoo | C14: Beauty | D14: Rice LLC | E14: 115.82 | F14: 460 | G14: =IF(E14="",AVERAGEIF(($C$2:$C$101),C14,($E$2:$E$101)),E14) -> 115.82 | H14: =IF(F14="",AVERAGEIF(($C$2:$C$101),C14,($F$2:$F$101)),F14) -> 460 | K14: Maximum | L14: 495.72 | M14: Maximum | N14: 496
A15: PROD13 | B15: USB-C Fast Charger | C15: Electronics | D15: Dawson-Perkins | E15: 242.23 | F15: 453 | G15: =IF(E15="",AVERAGEIF(($C$2:$C$101),C15,($E$2:$E$101)),E15) -> 242.23 | H15: =IF(F15="",AVERAGEIF(($C$2:$C$101),C15,($F$2:$F$101)),F15) -> 453 | K15: Sum | L15: 25412.936 | M15: Sum | N15: 27311.708
A16: PROD14 | B16: Decorative Wall Mirror | C16: Home | D16: Luna, Anderson and Bowman | E16: 48.01 | F16: 439 | G16: =IF(E16="",AVERAGEIF(($C$2:$C$101),C16,($E$2:$E$101)),E16) -> 48.01 | H16: =IF(F16="",AVERAGEIF(($C$2:$C$101),C16,($F$2:$F$101)),F16) -> 439 | K16: Count | L16: 100 | M16: Count | N16: 100
A17: PROD15 | B17: 4K Home Projector | C17: Electronics | D17: Thomas LLC | E17: 465.34 | F17: 301 | G17: =IF(E17="",AVERAGEIF(($C$2:$C$101),C17,($E$2:$E$101)),E17) -> 465.34 | H17: =IF(F17="",AVERAGEIF(($C$2:$C$101),C17,($F$2:$F$101)),F17) -> 301
A18: PROD16 | B18: Beard Grooming Kit | C18: Beauty | D18: Erickson-Green | E18: 337.42 | F18: 256 | G18: =IF(E18="",AVERAGEIF(($C$2:$C$101),C18,($E$2:$E$101)),E18) -> 337.42 | H18: =IF(F18="",AVERAGEIF(($C$2:$C$101),C18,($F$2:$F$101)),F18) -> 256
A19: PROD17 | B19: Soccer Training Cone Set | C19: Sports | D19: Ford, Murphy and Wilson | E19: 144.53 | F19: 367 | G19: =IF(E19="",AVERAGEIF(($C$2:$C$101),C19,($E$2:$E$101)),E19) -> 144.53 | H19: =IF(F19="",AVERAGEIF(($C$2:$C$101),C19,($F$2:$F$101)),F19) -> 367 | K19: PROD1
A20: PROD18 | B20: Women's Denim Jeans | C20: Clothing | D20: Guerra-Hendrix | F20: 343 | G20: =IF(E20="",AVERAGEIF(($C$2:$C$101),C20,($E$2:$E$101)),E20) -> 265.73267 | H20: =IF(F20="",AVERAGEIF(($C$2:$C$101),C20,($F$2:$F$101)),F20) -> 343 | J20: vlookup | K20: =VLOOKUP(K19,$A$2:$H$101,4,FALSE) -> Terry-Moore
A21: PROD19 | B21: Knee Support Brace | C21: Sports | D21: May-Reese | E21: 21.34 | F21: 65 | G21: =IF(E21="",AVERAGEIF(($C$2:$C$101),C21,($E$2:$E$101)),E21) -> 21.34 | H21: =IF(F21="",AVERAGEIF(($C$2:$C$101),C21,($F$2:$F$101)),F21) -> 65
A22: PROD20 | B22: Outdoor Sports Water Bottle | C22: Sports | D22: Soto-Ellis | E22: 131.51 | G22: =IF(E22="",AVERAGEIF(($C$2:$C$101),C22,($E$2:$E$101)),E22) -> 131.51 | H22: =IF(F22="",AVERAGEIF(($C$2:$C$101),C22,($F$2:$F$101)),F22) -> 281.95833 | K22: Row Labels | L22: Sum of New Cost | M22: Sum of New Stock
A23: PROD21 | B23: Multi-Purpose Storage Box | C23: Home | D23: Gardner-Montes | E23: 123.46 | F23: 76 | G23: =IF(E23="",AVERAGEIF(($C$2:$C$101),C23,($E$2:$E$101)),E23) -> 123.46 | H23: =IF(F23="",AVERAGEIF(($C$2:$C$101),C23,($F$2:$F$101)),F23) -> 76 | K23: Beauty | L23: 3756.2423 | M23: 4816
A24: PROD22 | B24: Carbon Fiber Tennis Racket | C24: Sports | D24: Flores, Pineda and Rodriguez | E24: 484.62 | F24: 432 | G24: =IF(E24="",AVERAGEIF(($C$2:$C$101),C24,($E$2:$E$101)),E24) -> 484.62 | H24: =IF(F24="",AVERAGEIF(($C$2:$C$101),C24,($F$2:$F$101)),F24) -> 432 | K24: Clothing | L24: 4783.188 | M24: 4931
A25: PROD23 | B25: Men's Formal Shirt | C25: Clothing | D25: Moon, Mora and Santos | F25: 360 | G25: =IF(E25="",AVERAGEIF(($C$2:$C$101),C25,($E$2:$E$101)),E25) -> 265.73267 | H25: =IF(F25="",AVERAGEIF(($C$2:$C$101),C25,($F$2:$F$101)),F25) -> 360 | K25: Electronics | L25: 6647.66 | M25: 5768.7
A26: PROD24 | B26: Foldable Camping Chair | C26: Sports | D26: Cook Ltd | E26: 166.06 | F26: 340 | G26: =IF(E26="",AVERAGEIF(($C$2:$C$101),C26,($E$2:$E$101)),E26) -> 166.06 | H26: =IF(F26="",AVERAGEIF(($C$2:$C$101),C26,($F$2:$F$101)),F26) -> 340 | K26: Home | L26: 4930.926 | M26: 4747.05
A27: PROD25 | B27: Women's Scarf Set | C27: Clothing | D27: Brown and Sons | E27: 174.02 | F27: 268 | G27: =IF(E27="",AVERAGEIF(($C$2:$C$101),C27,($E$2:$E$101)),E27) -> 174.02 | H27: =IF(F27="",AVERAGEIF(($C$2:$C$101),C27,($F$2:$F$101)),F27) -> 268 | K27: Sports | L27: 5294.92 | M27: 7048.9583
A28: PROD26 | B28: Wireless Bluetooth Speaker | C28: Electronics | D28: Reed-Schmidt | E28: 322.41 | F28: 213 | G28: =IF(E28="",AVERAGEIF(($C$2:$C$101),C28,($E$2:$E$101)),E28) -> 322.41 | H28: =IF(F28="",AVERAGEIF(($C$2:$C$101),C28,($F$2:$F$101)),F28) -> 213 | K28: Grand Total | L28: 25412.936 | M28: 27311.708
A29: PROD27 | B29: Decorative Floor Vase | C29: Home | D29: Khan, Jones and Paul | F29: 378 | G29: =IF(E29="",AVERAGEIF(($C$2:$C$101),C29,($E$2:$E$101)),E29) -> 234.806 | H29: =IF(F29="",AVERAGEIF(($C$2:$C$101),C29,($F$2:$F$101)),F29) -> 378
A30: PROD28 | B30: Sports Stopwatch Timer | C30: Sports | D30: Burns-Hansen | E30: 38.76 | F30: 137 | G30: =IF(E30="",AVERAGEIF(($C$2:$C$101),C30,($E$2:$E$101)),E30) -> 38.76 | H30: =IF(F30="",AVERAGEIF(($C$2:$C$101),C30,($F$2:$F$101)),F30) -> 137 | K30: Row Labels | L30: Average of New Cost
A31: PROD29 | B31: Fabric Sofa Throw Blanket | C31: Home | D31: Hoffman Group | E31: 218.48 | F31: 276 | G31: =IF(E31="",AVERAGEIF(($C$2:$C$101),C31,($E$2:$E$101)),E31) -> 218.48 | H31: =IF(F31="",AVERAGEIF(($C$2:$C$101),C31,($F$2:$F$101)),F31) -> 276 | K31: Beauty | L31: 250.41615
A32: PROD30 | B32: Stainless Steel Cutlery Set | C32: Home | D32: Stevens, Fernandez and Martin | E32: 19.52 | F32: 57 | G32: =IF(E32="",AVERAGEIF(($C$2:$C$101),C32,($E$2:$E$101)),E32) -> 19.52 | H32: =IF(F32="",AVERAGEIF(($C$2:$C$101),C32,($F$2:$F$101)),F32) -> 57 | K32: Clothing | L32: 265.73267
A33: PROD31 | B33: Basketball | C33: Sports | D33: Nolan-Snow | E33: 204.39 | F33: 281 | G33: =IF(E33="",AVERAGEIF(($C$2:$C$101),C33,($E$2:$E$101)),E33) -> 204.39 | H33: =IF(F33="",AVERAGEIF(($C$2:$C$101),C33,($F$2:$F$101)),F33) -> 281 | K33: Electronics | L33: 316.55524
A34: PROD32 | B34: Vitamin C Face Serum | C34: Beauty | D34: Griffin Ltd | E34: 283.83 | F34: 244 | G34: =IF(E34="",AVERAGEIF(($C$2:$C$101),C34,($E$2:$E$101)),E34) -> 283.83 | H34: =IF(F34="",AVERAGEIF(($C$2:$C$101),C34,($F$2:$F$101)),F34) -> 244 | K34: Home | L34: 234.806
A35: PROD33 | B35: Modern Wall Clock | C35: Home | D35: Weiss-Watson | E35: 179.77 | F35: 305 | G35: =IF(E35="",AVERAGEIF(($C$2:$C$101),C35,($E$2:$E$101)),E35) -> 179.77 | H35: =IF(F35="",AVERAGEIF(($C$2:$C$101),C35,($F$2:$F$101)),F35) -> 305 | K35: Sports | L35: 211.7968
A36: PROD34 | B36: Gaming Mechanical Keyboard | C36: Electronics | D36: Lucero LLC | E36: 419.28 | F36: 86 | G36: =IF(E36="",AVERAGEIF(($C$2:$C$101),C36,($E$2:$E$101)),E36) -> 419.28 | H36: =IF(F36="",AVERAGEIF(($C$2:$C$101),C36,($F$2:$F$101)),F36) -> 86
A37: PROD35 | B37: Bedroom Table Lamp | C37: Home | D37: Jones LLC | E37: 382.22 | F37: 329 | G37: =IF(E37="",AVERAGEIF(($C$2:$C$101),C37,($E$2:$E$101)),E37) -> 382.22 | H37: =IF(F37="",AVERAGEIF(($C$2:$C$101),C37,($F$2:$F$101)),F37) -> 329
A38: PROD36 | B38: Women's Summer Dress | C38: Clothing | D38: Smith-Mills | E38: 223.43 | F38: 154 | G38: =IF(E38="",AVERAGEIF(($C$2:$C$101),C38,($E$2:$E$101)),E38) -> 223.43 | H38: =IF(F38="",AVERAGEIF(($C$2:$C$101),C38,($F$2:$F$101)),F38) -> 154 | K38: Row Labels | L38: Max of New Stock
A39: PROD37 | B39: Men's Casual Sneakers | C39: Clothing | D39: Hogan-Lee | E39: 353.47 | F39: 214 | G39: =IF(E39="",AVERAGEIF(($C$2:$C$101),C39,($E$2:$E$101)),E39) -> 353.47 | H39: =IF(F39="",AVERAGEIF(($C$2:$C$101),C39,($F$2:$F$101)),F39) -> 214 | K39: Beauty | L39: 460
A40: PROD38 | B40: Sports Water Hydration Pack | C40: Sports | D40: Sims-Smith | E40: 135.61 | F40: 394 | G40: =IF(E40="",AVERAGEIF(($C$2:$C$101),C40,($E$2:$E$101)),E40) -> 135.61 | H40: =IF(F40="",AVERAGEIF(($C$2:$C$101),C40,($F$2:$F$101)),F40) -> 394 | K40: Clothing | L40: 496
A41: PROD39 | B41: Portable Power Bank | C41: Electronics | D41: Cummings and Sons | E41: 326.06 | F41: 301 | G41: =IF(E41="",AVERAGEIF(($C$2:$C$101),C41,($E$2:$E$101)),E41) -> 326.06 | H41: =IF(F41="",AVERAGEIF(($C$2:$C$101),C41,($F$2:$F$101)),F41) -> 301 | K41: Electronics | L41: 485
A42: PROD40 | B42: Noise-Canceling Headphones | C42: Electronics | D42: Taylor-Hart | E42: 38.52 | F42: 378 | G42: =IF(E42="",AVERAGEIF(($C$2:$C$101),C42,($E$2:$E$101)),E42) -> 38.52 | H42: =IF(F42="",AVERAGEIF(($C$2:$C$101),C42,($F$2:$F$101)),F42) -> 378 | K42: Home | L42: 469
A43: PROD41 | B43: Yoga Exercise Mat | C43: Sports | D43: Carroll, Long and Mendoza | E43: 313.26 | F43: 369 | G43: =IF(E43="",AVERAGEIF(($C$2:$C$101),C43,($E$2:$E$101)),E43) -> 313.26 | H43: =IF(F43="",AVERAGEIF(($C$2:$C$101),C43,($F$2:$F$101)),F43) -> 369 | K43: Sports | L43: 471
A44: PROD42 | B44: Smart Home WiFi Camera | C44: Electronics | D44: Holmes LLC | E44: 450.71 | F44: 389 | G44: =IF(E44="",AVERAGEIF(($C$2:$C$101),C44,($E$2:$E$101)),E44) -> 450.71 | H44: =IF(F44="",AVERAGEIF(($C$2:$C$101),C44,($F$2:$F$101)),F44) -> 389
A45: PROD43 | B45: USB External Hard Drive | C45: Electronics | D45: Robinson Inc | E45: 253.33 | F45: 266 | G45: =IF(E45="",AVERAGEIF(($C$2:$C$101),C45,($E$2:$E$101)),E45) -> 253.33 | H45: =IF(F45="",AVERAGEIF(($C$2:$C$101),C45,($F$2:$F$101)),F45) -> 266
A46: PROD44 | B46: Adjustable Jump Rope | C46: Sports | D46: Cox Inc | E46: 167.12 | F46: 316 | G46: =IF(E46="",AVERAGEIF(($C$2:$C$101),C46,($E$2:$E$101)),E46) -> 167.12 | H46: =IF(F46="",AVERAGEIF(($C$2:$C$101),C46,($F$2:$F$101)),F46) -> 316
A47: PROD45 | B47: High-Grip Football | C47: Sports | D47: Bridges, Banks and Cummings | E47: 318.91 | F47: 114 | G47: =IF(E47="",AVERAGEIF(($C$2:$C$101),C47,($E$2:$E$101)),E47) -> 318.91 | H47: =IF(F47="",AVERAGEIF(($C$2:$C$101),C47,($F$2:$F$101)),F47) -> 114
A48: PROD46 | B48: Men's Winter Jacket | C48: Clothing | D48: Kelly, Smith and Perez | E48: 167.34 | F48: 296 | G48: =IF(E48="",AVERAGEIF(($C$2:$C$101),C48,($E$2:$E$101)),E48) -> 167.34 | H48: =IF(F48="",AVERAGEIF(($C$2:$C$101),C48,($F$2:$F$101)),F48) -> 296
A49: PROD47 | B49: Makeup Brush Set | C49: Beauty | D49: Cook Inc | F49: 431 | G49: =IF(E49="",AVERAGEIF(($C$2:$C$101),C49,($E$2:$E$101)),E49) -> 250.41615 | H49: =IF(F49="",AVERAGEIF(($C$2:$C$101),C49,($F$2:$F$101)),F49) -> 431
A50: PROD48 | B50: Car Dashboard Phone Holder | C50: Electronics | D50: Byrd, Stewart and Valdez | E50: 177.98 | F50: 103 | G50: =IF(E50="",AVERAGEIF(($C$2:$C$101),C50,($E$2:$E$101)),E50) -> 177.98 | H50: =IF(F50="",AVERAGEIF(($C$2:$C$101),C50,($F$2:$F$101)),F50) -> 103
A51: PROD49 | B51: Men's Roll-On Perfume | C51: Beauty | D51: Sullivan and Sons | E51: 43.29 | F51: 267 | G51: =IF(E51="",AVERAGEIF(($C$2:$C$101),C51,($E$2:$E$101)),E51) -> 43.29 | H51: =IF(F51="",AVERAGEIF(($C$2:$C$101),C51,($F$2:$F$101)),F51) -> 267
A52: PROD50 | B52: Boxing Hand Wraps | C52: Sports | D52: Smith-King | E52: 190.29 | F52: 260 | G52: =IF(E52="",AVERAGEIF(($C$2:$C$101),C52,($E$2:$E$101)),E52) -> 190.29 | H52: =IF(F52="",AVERAGEIF(($C$2:$C$101),C52,($F$2:$F$101)),F52) -> 260
A53: PROD51 | B53: HDMI Cable – 2m | C53: Electronics | D53: Bautista, Green and Hale | E53: 88.49 | F53: 246 | G53: =IF(E53="",AVERAGEIF(($C$2:$C$101),C53,($E$2:$E$101)),E53) -> 88.49 | H53: =IF(F53="",AVERAGEIF(($C$2:$C$101),C53,($F$2:$F$101)),F53) -> 246
A54: PROD52 | B54: Rugby Ball | C54: Sports | D54: Harris Inc | E54: 212.26 | F54: 82 | G54: =IF(E54="",AVERAGEIF(($C$2:$C$101),C54,($E$2:$E$101)),E54) -> 212.26 | H54: =IF(F54="",AVERAGEIF(($C$2:$C$101),C54,($F$2:$F$101)),F54) -> 82
A55: PROD53 | B55: Men's Track Pants | C55: Clothing | D55: Hamilton, Woods and Walker | E55: 386.56 | F55: 125 | G55: =IF(E55="",AVERAGEIF(($C$2:$C$101),C55,($E$2:$E$101)),E55) -> 386.56 | H55: =IF(F55="",AVERAGEIF(($C$2:$C$101),C55,($F$2:$F$101)),F55) -> 125
A56: PROD54 | B56: Sports Stopwatch Pro | C56: Sports | D56: Thompson-French | E56: 434.84 | F56: 185 | G56: =IF(E56="",AVERAGEIF(($C$2:$C$101),C56,($E$2:$E$101)),E56) -> 434.84 | H56: =IF(F56="",AVERAGEIF(($C$2:$C$101),C56,($F$2:$F$101)),F56) -> 185
A57: PROD55 | B57: Ceramic Plant Pot | C57: Home | D57: Hatfield, Baird and Torres | E57: 81.75 | G57: =IF(E57="",AVERAGEIF(($C$2:$C$101),C57,($E$2:$E$101)),E57) -> 81.75 | H57: =IF(F57="",AVERAGEIF(($C$2:$C$101),C57,($F$2:$F$101)),F57) -> 226.05
A58: PROD56 | B58: Premium Blanket Throw | C58: Home | D58: Hernandez, Kennedy and Porter | E58: 461.47 | F58: 190 | G58: =IF(E58="",AVERAGEIF(($C$2:$C$101),C58,($E$2:$E$101)),E58) -> 461.47 | H58: =IF(F58="",AVERAGEIF(($C$2:$C$101),C58,($F$2:$F$101)),F58) -> 190
A59: PROD57 | B59: Foam Roller | C59: Sports | D59: Atkinson, Camacho and Oliver | E59: 30.62 | F59: 138 | G59: =IF(E59="",AVERAGEIF(($C$2:$C$101),C59,($E$2:$E$101)),E59) -> 30.62 | H59: =IF(F59="",AVERAGEIF(($C$2:$C$101),C59,($F$2:$F$101)),F59) -> 138
A60: PROD58 | B60: Womens Cotton Scarf | C60: Clothing | D60: Shepherd-Gould | E60: 113.83 | F60: 485 | G60: =IF(E60="",AVERAGEIF(($C$2:$C$101),C60,($E$2:$E$101)),E60) -> 113.83 | H60: =IF(F60="",AVERAGEIF(($C$2:$C$101),C60,($F$2:$F$101)),F60) -> 485
A61: PROD59 | B61: Men's Hair Styling Gel | C61: Beauty | D61: Cline-Mccarthy | E61: 17.31 | F61: 399 | G61: =IF(E61="",AVERAGEIF(($C$2:$C$101),C61,($E$2:$E$101)),E61) -> 17.31 | H61: =IF(F61="",AVERAGEIF(($C$2:$C$101),C61,($F$2:$F$101)),F61) -> 399
A62: PROD60 | B62: Luxury Perfume Spray | C62: Beauty | D62: Gibson, Green and Lopez | E62: 482.75 | F62: 444 | G62: =IF(E62="",AVERAGEIF(($C$2:$C$101),C62,($E$2:$E$101)),E62) -> 482.75 | H62: =IF(F62="",AVERAGEIF(($C$2:$C$101),C62,($F$2:$F$101)),F62) -> 444
A63: PROD61 | B63: Tennis Ball 3-Pack | C63: Sports | D63: Lopez LLC | E63: 103.45 | F63: 465 | G63: =IF(E63="",AVERAGEIF(($C$2:$C$101),C63,($E$2:$E$101)),E63) -> 103.45 | H63: =IF(F63="",AVERAGEIF(($C$2:$C$101),C63,($F$2:$F$101)),F63) -> 465
A64: PROD62 | B64: Laptop Cooling Pad | C64: Electronics | D64: Murray, Gould and Ware | E64: 86.42 | F64: 222 | G64: =IF(E64="",AVERAGEIF(($C$2:$C$101),C64,($E$2:$E$101)),E64) -> 86.42 | H64: =IF(F64="",AVERAGEIF(($C$2:$C$101),C64,($F$2:$F$101)),F64) -> 222
A65: PROD63 | B65: Organic Sunscreen Lotion | C65: Beauty | D65: Anderson-Riley | E65: 266.86 | F65: 458 | G65: =IF(E65="",AVERAGEIF(($C$2:$C$101),C65,($E$2:$E$101)),E65) -> 266.86 | H65: =IF(F65="",AVERAGEIF(($C$2:$C$101),C65,($F$2:$F$101)),F65) -> 458
A66: PROD64 | B66: Matte Lipstick Set | C66: Beauty | D66: Zhang Inc | E66: 299.11 | F66: 118 | G66: =IF(E66="",AVERAGEIF(($C$2:$C$101),C66,($E$2:$E$101)),E66) -> 299.11 | H66: =IF(F66="",AVERAGEIF(($C$2:$C$101),C66,($F$2:$F$101)),F66) -> 118
A67: PROD65 | B67: Adjustable Dumbbells 20kg | C67: Sports | D67: Montgomery, Benton and Miller | E67: 240.63 | F67: 423 | G67: =IF(E67="",AVERAGEIF(($C$2:$C$101),C67,($E$2:$E$101)),E67) -> 240.63 | H67: =IF(F67="",AVERAGEIF(($C$2:$C$101),C67,($F$2:$F$101)),F67) -> 423
A68: PROD66 | B68: Women's Hair Dryer Brush | C68: Beauty | D68: Torres, Spencer and Potter | E68: 340.39 | F68: 177 | G68: =IF(E68="",AVERAGEIF(($C$2:$C$101),C68,($E$2:$E$101)),E68) -> 340.39 | H68: =IF(F68="",AVERAGEIF(($C$2:$C$101),C68,($F$2:$F$101)),F68) -> 177
A69: PROD67 | B69: Smart LED Light Strip | C69: Electronics | D69: Flores-Davis | E69: 349.17 | F69: 476 | G69: =IF(E69="",AVERAGEIF(($C$2:$C$101),C69,($E$2:$E$101)),E69) -> 349.17 | H69: =IF(F69="",AVERAGEIF(($C$2:$C$101),C69,($F$2:$F$101)),F69) -> 476
... A84: PROD82 | B84: Fitness Resistance Bands | C84: Sports | D84: Reese-Watson | E84: 152.92 | F84: 281 | G84: =IF(E84="",AVERAGEIF(($C$2:$C$101),C84,($E$2:$E$101)),E84) -> 152.92 | H84: =IF(F84="",AVERAGEIF(($C$2:$C$101),C84,($F$2:$F$101)),F84) -> 281
A85: PROD83 | B85: Hydrating Face Cleanser | C85: Beauty | D85: Butler Group | F85: 159 | G85: =IF(E85="",AVERAGEIF(($C$2:$C$101),C85,($E$2:$E$101)),E85) -> 250.41615 | H85: =IF(F85="",AVERAGEIF(($C$2:$C$101),C85,($F$2:$F$101)),F85) -> 159
A86: PROD84 | B86: Wooden Bookshelf | C86: Home | D86: Collins-Stephenson | E86: 388.46 | F86: 208 | G86: =IF(E86="",AVERAGEIF(($C$2:$C$101),C86,($E$2:$E$101)),E86) -> 388.46 | H86: =IF(F86="",AVERAGEIF(($C$2:$C$101),C86,($F$2:$F$101)),F86) -> 208
A87: PROD85 | B87: Women's Beanie Hat | C87: Clothing | D87: Richardson-Carrillo | E87: 119.57 | F87: 210 | G87: =IF(E87="",AVERAGEIF(($C$2:$C$101),C87,($E$2:$E$101)),E87) -> 119.57 | H87: =IF(F87="",AVERAGEIF(($C$2:$C$101),C87,($F$2:$F$101)),F87) -> 210
A88: PROD86 | B88: Kitchen Cutting Board | C88: Home | D88: Taylor, Dodson and Johnston | E88: 176.07 | F88: 82 | G88: =IF(E88="",AVERAGEIF(($C$2:$C$101),C88,($E$2:$E$101)),E88) -> 176.07 | H88: =IF(F88="",AVERAGEIF(($C$2:$C$101),C88,($F$2:$F$101)),F88) -> 82
A89: PROD87 | B89: LED Bedside Lamp | C89: Home | D89: Aguilar, Horton and Lewis | E89: 371.38 | F89: 220 | G89: =IF(E89="",AVERAGEIF(($C$2:$C$101),C89,($E$2:$E$101)),E89) -> 371.38 | H89: =IF(F89="",AVERAGEIF(($C$2:$C$101),C89,($F$2:$F$101)),F89) -> 220
A90: PROD88 | B90: Sports Wrist Sweatbands | C90: Sports | D90: Olsen-Daniels | E90: 131.24 | F90: 232 | G90: =IF(E90="",AVERAGEIF(($C$2:$C$101),C90,($E$2:$E$101)),E90) -> 131.24 | H90: =IF(F90="",AVERAGEIF(($C$2:$C$101),C90,($F$2:$F$101)),F90) -> 232
A91: PROD89 | B91: Face Foundation Kit | C91: Beauty | D91: Taylor-Elliott | E91: 183.04 | F91: 457 | G91: =IF(E91="",AVERAGEIF(($C$2:$C$101),C91,($E$2:$E$101)),E91) -> 183.04 | H91: =IF(F91="",AVERAGEIF(($C$2:$C$101),C91,($F$2:$F$101)),F91) -> 457
A92: PROD90 | B92: Gaming Mouse Pad XL | C92: Electronics | D92: Sharp, Taylor and Rodriguez | E92: 340.14 | F92: 361 | G92: =IF(E92="",AVERAGEIF(($C$2:$C$101),C92,($E$2:$E$101)),E92) -> 340.14 | H92: =IF(F92="",AVERAGEIF(($C$2:$C$101),C92,($F$2:$F$101)),F92) -> 361
A93: PROD91 | B93: Women's High Heels | C93: Clothing | D93: Smith-Charles | E93: 438.25 | F93: 496 | G93: =IF(E93="",AVERAGEIF(($C$2:$C$101),C93,($E$2:$E$101)),E93) -> 438.25 | H93: =IF(F93="",AVERAGEIF(($C$2:$C$101),C93,($F$2:$F$101)),F93) -> 496
A94: PROD92 | B94: Microwave Oven | C94: Home | D94: Green, Powell and Palmer | E94: 447.43 | F94: 191 | G94: =IF(E94="",AVERAGEIF(($C$2:$C$101),C94,($E$2:$E$101)),E94) -> 447.43 | H94: =IF(F94="",AVERAGEIF(($C$2:$C$101),C94,($F$2:$F$101)),F94) -> 191
A95: PROD93 | B95: USB-C Laptop Charger | C95: Electronics | D95: Martin LLC | E95: 377.52 | F95: 485 | G95: =IF(E95="",AVERAGEIF(($C$2:$C$101),C95,($E$2:$E$101)),E95) -> 377.52 | H95: =IF(F95="",AVERAGEIF(($C$2:$C$101),C95,($F$2:$F$101)),F95) -> 485
A96: PROD94 | B96: Vitamin E Body Lotion | C96: Beauty | D96: Hoffman-Williams | E96: 358.47 | F96: 213 | G96: =IF(E96="",AVERAGEIF(($C$2:$C$101),C96,($E$2:$E$101)),E96) -> 358.47 | H96: =IF(F96="",AVERAGEIF(($C$2:$C$101),C96,($F$2:$F$101)),F96) -> 213
A97: PROD95 | B97: Sports Stopwatch Basic | C97: Sports | D97: Wilson Group | E97: 60.65 | F97: 75 | G97: =IF(E97="",AVERAGEIF(($C$2:$C$101),C97,($E$2:$E$101)),E97) -> 60.65 | H97: =IF(F97="",AVERAGEIF(($C$2:$C$101),C97,($F$2:$F$101)),F97) -> 75
... A101: PROD99 | B101: Stainless Steel Cookware Set | C101: Home | D101: Campbell Ltd | E101: 201.41 | F101: 146 | G101: =IF(E101="",AVERAGEIF(($C$2:$C$101),C101,($E$2:$E$101)),E101) -> 201.41 | H101: =IF(F101="",AVERAGEIF(($C$2:$C$101),C101,($F$2:$F$101)),F101) -> 146
B102: =COUNTA(B2:B101) -> 100 | C102: =COUNTIF(C2:C101,"Electronics") -> 21 | G102: =SUM(G2:G101) -> 25412.936 | H102: =AVERAGE(H2:H101) -> 273.11708
G103: =SUMIF(G2:G101,"> 250") -> 18178.28

Sheet Store_Dim
A1: Store_ID | B1: Store_Name | C1: Region | D1: City | E1: Store_Type
A2: STORE0 | B2: Rivera-Warner | C2: East | D2: Washingtonfurt | E2: Flagship
A3: STORE1 | B3: Martinez, Adkins and Johnson | C3: North | D3: Danielmouth | E3: Flagship
A4: STORE2 | B4: Black-Horn | C4: South | D4: North Nancyview | E4: Outlet
A5: STORE3 | B5: Johnson-Wright | C5: North | D5: Hoodberg | E5: Outlet
A6: STORE4 | B6: Alexander Group | C6: South | D6: Port Sharon | E6: Online
A7: STORE5 | B7: Gray Ltd | C7: North | D7: New Michaelchester | E7: Outlet
A8: STORE6 | B8: Benson-Elliott | C8: East | D8: Port Josephberg | E8: Online
A9: STORE7 | B9: Martinez-Mullins | C9: South | D9: Williamsfurt | E9: Online
A10: STORE8 | B10: Bean, Jones and Park | C10: West | D10: Thompsonborough | E10: Online
A11: STORE9 | B11: Moore, Padilla and Butler | C11: South | D11: East Johnstad | E11: Flagship
A12: STORE10 | B12: Hill, Wagner and Ballard | C12: East | D12: East Davidville | E12: Online
... A21: STORE19 | B21: Mann-Austin | C21: East | D21: Vasquezborough | E21: Online

Sheet Cleaned Store Dim
A1: Store_ID | B1: Store_Name | C1: Region | D1: City | E1: Store_Type | F1: New City (Replace) | H1: Region | I1: East | K1: Region | L1: North
A2: STORE0 | B2: Rivera-Warner | C2: East | D2: Washingtonfurt | E2: Flagship | F2: Washington
A3: STORE1 | B3: Martinez, Adkins and Johnson | C3: North | D3: Danielmouth | E3: Flagship | F3: Daniel | H3: Row Labels | I3: Count of Store_Name | K3: Row Labels | L3: Count of New City (Replace)
A4: STORE2 | B4: Black-Horn | C4: South | D4: North Nancyview | E4: Outlet | F4: North Nancy | H4: Flagship | I4: 3 | K4: Flagship | L4: 3
A5: STORE3 | B5: Johnson-Wright | C5: North | D5: Hoodberg | E5: Outlet | F5: Goldberg | H5: Online | I5: 3 | K5: Online | L5: 1
A6: STORE4 | B6: Alexander Group | C6: South | D6: Port Sharon | E6: Online | F6: Sharon | H6: Grand Total | I6: 6 | K6: Outlet | L6: 2
A7: STORE5 | B7: Gray Ltd | C7: North | D7: New Michaelchester | E7: Outlet | F7: Chester | K7: Grand Total | L7: 6
A8: STORE6 | B8: Benson-Elliott | C8: East | D8: Port Josephberg | E8: Online | F8: Joseph
A9: STORE7 | B9: Martinez-Mullins | C9: South | D9: Williamsfurt | E9: Online | F9: Williamsport
A10: STORE8 | B10: Bean, Jones and Park | C10: West | D10: Thompsonborough | E10: Online | F10: Thompson
A11: STORE9 | B11: Moore, Padilla and Butler | C11: South | D11: East Johnstad | E11: Flagship | F11: Johnstad | H11: Count of City | I11: Column Labels
A12: STORE10 | B12: Hill, Wagner and Ballard | C12: East | D12: East Davidville | E12: Online | F12: David | H12: Row Labels | I12: Flagship | J12: Grand Total
A13: STORE11 | B13: Aguirre-Keller | C13: South | D13: Lake Michael | E13: Online | F13: Lake | H13: East | I13: 3 | J13: 3
A14: STORE12 | B14: Thomas, Bridges and Harris | C14: North | D14: Sabrinatown | E14: Online | F14: Sabrina | H14: North | I14: 3 | J14: 3
A15: STORE13 | B15: Gardner, Humphrey and Contreras | C15: East | D15: Johnsonville | E15: Flagship | F15: Johnsonville | H15: South | I15: 1 | J15: 1
A16: STORE14 | B16: Mcdonald Inc | C16: South | D16: Christopherland | E16: Outlet | F16: Christopher | H16: West | I16: 1 | J16: 1
A17: STORE15 | B17: Shelton PLC | C17: North | D17: East Jenniferstad | E17: Flagship | F17: Jenniferstad | H17: Grand Total | I17: 8 | J17: 8
A18: STORE16 | B18: Frederick-Wright | C18: West | D18: New Jimmymouth | E18: Flagship | F18: New Jimmy
A19: STORE17 | B19: Holloway Ltd | C19: North | D19: Bensonhaven | E19: Flagship | F19: Benson
A20: STORE18 | B20: Guerrero-Schmitt | C20: East | D20: East Stevechester | E20: Flagship | F20: East Stevechester
A21: STORE19 | B21: Mann-Austin | C21: East | D21: Vasquezborough | E21: Online | F21: Vasquez
C22: =COUNTIF(C2:C21,"South") -> 6

Sheet Sales_Fact
A1: Sales_ID | B1: Order_Date | C1: Customer_ID | D1: Product_ID | E1: Store_ID | F1: Quantity | G1: Unit_Price | H1: Discount | I1: Payment_Type | J1: Total_Amount
A2: SALE0 | B2: 45480 | C2: CUST1409 | D2: PROD97 | E2: STORE3 | F2: 1 | G2: 218.04 | H2: 0.09 | I2: Credit Card | J2: 198.4164
A3: SALE1 | B3: 45285 | C3: CUST1467 | D3: PROD74 | E3: STORE17 | F3: 3 | G3: 104.47 | H3: 0.27 | I3: PayPal | J3: 228.7893
A4: SALE2 | B4: 45446 | C4: CUST1056 | D4: PROD49 | E4: STORE8 | F4: 4 | G4: 914.05 | H4: 0.25 | I4: Credit Card | J4: 2742.15
A5: SALE3 | B5: 45259 | C5: CUST1346 | D5: PROD76 | E5: STORE8 | F5: 1 | G5: 921.51 | H5: 0.16 | I5: COD | J5: 774.0684
A6: SALE4 | B6: 45297 | C6: CUST1493 | D6: PROD59 | E6: STORE5 | F6: 3 | G6: 745.3 | H6: 0.18 | I6: Credit Card | J6: 1833.438
A7: SALE5 | B7: 45499 | C7: CUST1116 | D7: PROD15 | E7: STORE7 | F7: 3 | G7: 147.01 | H7: 0.19 | I7: COD | J7: 357.2343
A8: SALE6 | B8: 45850 | C8: CUST1016 | D8: PROD56 | E8: STORE4 | F8: 2 | G8: 785.31 | H8: 0.15 | I8: PayPal | J8: 1335.027
A9: SALE7 | B9: 45248 | C9: CUST1152 | D9: PROD70 | E9: STORE8 | F9: 4 | G9: 342.39 | H9: 0.23 | I9: PayPal | J9: 1054.5612
A10: SALE8 | B10: 45781 | C10: CUST1187 | D10: PROD99 | E10: STORE5 | G10: 448.25 | H10: 0.07 | I10: PayPal | J10: 1250.6175
A11: SALE9 | B11: 45869 | C11: CUST1464 | D11: PROD33 | E11: STORE0 | F11: 2 | G11: 873.17 | H11: 0.23 | I11: PayPal | J11: 1344.6818
A12: SALE10 | B12: 45335 | C12: CUST1065 | D12: PROD24 | E12: STORE14 | F12: 1 | G12: 278.63 | H12: 0.07 | I12: Credit Card | J12: 259.1259
A13: SALE11 | B13: 45801 | C13: CUST1320 | D13: PROD39 | E13: STORE1 | F13: 4 | G13: 286.92 | H13: 0.17 | I13: Credit Card | J13: 952.5744
A14: SALE12 | B14: 45528 | C14: CUST1237 | D14: PROD88 | E14: STORE4 | F14: 4 | G14: 644.58 | H14: 0.01 | I14: Credit Card | J14: 2552.5368
A15: SALE13 | B15: 45875 | C15: CUST1443 | D15: PROD34 | E15: STORE16 | F15: 2 | G15: 316.9 | H15: 0.3 | I15: PayPal | J15: 443.66
A16: SALE14 | B16: 45829 | C16: CUST1348 | D16: PROD24 | E16: STORE15 | F16: 4 | G16: 403.47 | H16: 0.29 | I16: PayPal | J16: 1145.8548
A17: SALE15 | B17: 45636 | C17: CUST1435 | D17: PROD36 | E17: STORE9 | G17: 871.34 | H17: 0.04 | I17: COD | J17: 2509.4592
A18: SALE16 | B18: 45913 | C18: CUST1276 | D18: PROD65 | E18: STORE19 | F18: 2 | G18: 451.98 | H18: 0.25 | I18: Credit Card | J18: 677.97
A19: SALE17 | B19: 45637 | C19: CUST1079 | D19: PROD27 | E19: STORE4 | F19: 2 | G19: 502.69 | H19: 0.23 | I19: Credit Card | J19: 774.1426
A20: SALE18 | B20: 45517 | C20: CUST1094 | D20: PROD39 | E20: STORE4 | F20: 2 | G20: 559.23 | H20: 0.25 | I20: COD | J20: 838.845
A21: SALE19 | B21: 45369 | C21: CUST1239 | D21: PROD60 | E21: STORE13 | F21: 4 | H21: 0.04 | I21: COD | J21: 1782.4512
A22: SALE20 | B22: 45843 | C22: CUST1144 | D22: PROD72 | E22: STORE17 | F22: 3 | G22: 986.04 | H22: 0.27 | I22: COD | J22: 2159.4276
A23: SALE21 | B23: 45447 | C23: CUST1396 | D23: PROD43 | E23: STORE18 | F23: 1 | G23: 589.56 | H23: 0.22 | I23: Credit Card | J23: 459.8568
A24: SALE22 | B24: 45394 | C24: CUST1476 | D24: PROD69 | E24: STORE10 | F24: 3 | G24: 979.42 | H24: 0.03 | I24: PayPal | J24: 2850.1122
A25: SALE23 | B25: 45466 | C25: CUST1368 | D25: PROD12 | E25: STORE8 | F25: 1 | G25: 719.28 | H25: 0.08 | I25: Credit Card | J25: 661.7376
A26: SALE24 | B26: 45908 | C26: CUST1186 | D26: PROD67 | E26: STORE6 | F26: 3 | G26: 77.6 | H26: 0.07 | I26: Credit Card | J26: 216.504
A27: SALE25 | B27: 45552 | C27: CUST1381 | D27: PROD5 | E27: STORE3 | F27: 4 | G27: 852.71 | H27: 0.14 | I27: PayPal | J27: 2933.3224
A28: SALE26 | B28: 45294 | C28: CUST1213 | D28: PROD98 | E28: STORE8 | F28: 4 | G28: 156.16 | I28: Credit Card | J28: 599.6544
A29: SALE27 | B29: 45710 | C29: CUST1200 | D29: PROD77 | E29: STORE8 | F29: 3 | G29: 815.49 | H29: 0.17 | I29: Credit Card | J29: 2030.5701
A30: SALE28 | B30: 45923 | C30: CUST1148 | D30: PROD13 | E30: STORE2 | F30: 2 | G30: 74.21 | H30: 0.11 | I30: PayPal | J30: 132.0938
A31: SALE29 | B31: 45302 | C31: CUST1348 | D31: PROD99 | E31: STORE3 | G31: 451.67 | H31: 0.15 | I31: Credit Card | J31: 1535.678
A32: SALE30 | B32: 45217 | C32: CUST1028 | D32: PROD5 | E32: STORE19 | F32: 1 | G32: 429.38 | H32: 0.13 | I32: PayPal | J32: 373.5606
A33: SALE31 | B33: 45593 | C33: CUST1412 | D33: PROD53 | E33: STORE12 | F33: 2 | G33: 148.96 | H33: 0.03 | I33: COD | J33: 288.9824
A34: SALE32 | B34: 45597 | C34: CUST1398 | D34: PROD75 | E34: STORE8 | F34: 4 | G34: 313.83 | H34: 0.08 | I34: Credit Card | J34: 1154.8944
A35: SALE33 | B35: 45620 | C35: CUST1453 | D35: PROD12 | E35: STORE6 | F35: 2 | G35: 717.31 | H35: 0.15 | I35: Credit Card | J35: 1219.427
A36: SALE34 | B36: 45215 | C36: CUST1344 | D36: PROD79 | E36: STORE1 | G36: 873.22 | H36: 0.18 | I36: Credit Card | J36: 2148.1212
A37: SALE35 | B37: 45878 | C37: CUST1218 | D37: PROD16 | E37: STORE3 | F37: 4 | G37: 109.36 | H37: 0.19 | I37: COD | J37: 354.3264
A38: SALE36 | B38: 45635 | C38: CUST1086 | D38: PROD5 | E38: STORE7 | F38: 3 | G38: 559.52 | H38: 0.16 | I38: PayPal | J38: 1409.9904
A39: SALE37 | B39: 45329 | C39: CUST1492 | D39: PROD10 | E39: STORE17 | F39: 3 | G39: 121.76 | H39: 0.27 | I39: PayPal | J39: 266.6544
A40: SALE38 | B40: 45378 | C40: CUST1189 | D40: PROD33 | E40: STORE13 | F40: 4 | G40: 735.32 | H40: 0.06 | I40: COD | J40: 2764.8032
A41: SALE39 | B41: 45264 | C41: CUST1431 | D41: PROD94 | E41: STORE3 | F41: 2 | G41: 600.73 | H41: 0.08 | I41: Credit Card | J41: 1105.3432
A42: SALE40 | B42: 45486 | C42: CUST1072 | D42: PROD26 | E42: STORE19 | F42: 2 | G42: 873.86 | H42: 0.07 | I42: COD | J42: 1625.3796
A43: SALE41 | B43: 45241 | C43: CUST1302 | D43: PROD23 | E43: STORE8 | F43: 3 | G43: 342.47 | H43: 0.08 | I43: PayPal | J43: 945.2172
A44: SALE42 | B44: 45649 | C44: CUST1335 | D44: PROD29 | E44: STORE9 | F44: 2 | G44: 915.15 | H44: 0.16 | I44: PayPal | J44: 1537.452
A45: SALE43 | B45: 45677 | C45: CUST1084 | D45: PROD33 | E45: STORE17 | G45: 863.11 | H45: 0.28 | I45: PayPal | J45: 1864.3176
A46: SALE44 | B46: 45538 | C46: CUST1203 | D46: PROD43 | E46: STORE12 | F46: 2 | G46: 209.32 | H46: 0.23 | I46: COD | J46: 322.3528
A47: SALE45 | B47: 45606 | C47: CUST1470 | D47: PROD59 | E47: STORE8 | F47: 4 | G47: 288.6 | H47: 0.09 | I47: PayPal | J47: 1050.504
A48: SALE46 | B48: 45570 | C48: CUST1070 | D48: PROD78 | E48: STORE16 | F48: 1 | G48: 418.69 | H48: 0.06 | I48: PayPal | J48: 393.5686
A49: SALE47 | B49: 45466 | C49: CUST1008 | D49: PROD30 | E49: STORE11 | F49: 1 | G49: 135.78 | H49: 0.14 | I49: PayPal | J49: 116.7708
A50: SALE48 | B50: 45218 | C50: CUST1203 | D50: PROD44 | E50: STORE17 | F50: 1 | G50: 517.13 | H50: 0.28 | I50: Credit Card | J50: 372.3336
A51: SALE49 | B51: 45607 | C51: CUST1420 | D51: PROD21 | E51: STORE16 | F51: 2 | G51: 384.66 | H51: 0.08 | I51: COD | J51: 707.7744
A52: SALE50 | B52: 45291 | C52: CUST1070 | D52: PROD52 | E52: STORE9 | F52: 3 | G52: 83.7 | H52: 0.24 | I52: PayPal | J52: 190.836
A53: SALE51 | B53: 45689 | C53: CUST1142 | D53: PROD69 | E53: STORE7 | F53: 3 | G53: 76.57 | H53: 0.26 | I53: Credit Card | J53: 169.9854
A54: SALE52 | B54: 45894 | C54: CUST1148 | D54: PROD89 | E54: STORE6 | F54: 3 | I54: Credit Card | J54: 486.0633
A55: SALE53 | B55: 45677 | C55: CUST1324 | D55: PROD20 | E55: STORE8 | F55: 1 | G55: 900.35 | H55: 0.13 | I55: COD | J55: 783.3045
A56: SALE54 | B56: 45706 | C56: CUST1095 | D56: PROD40 | E56: STORE10 | F56: 4 | G56: 428.09 | H56: 0.07 | I56: Credit Card | J56: 1592.4948
A57: SALE55 | B57: 45589 | C57: CUST1416 | D57: PROD49 | E57: STORE11 | F57: 2 | G57: 559.71 | H57: 0.3 | I57: COD | J57: 783.594
A58: SALE56 | B58: 45282 | C58: CUST1080 | D58: PROD34 | E58: STORE6 | F58: 2 | G58: 833.7 | H58: 0.06 | I58: PayPal | J58: 1567.356
A59: SALE57 | B59: 45462 | C59: CUST1467 | D59: PROD47 | E59: STORE14 | F59: 2 | G59: 680.16 | H59: 0.28 | I59: Credit Card | J59: 979.4304
A60: SALE58 | B60: 45633 | C60: CUST1404 | D60: PROD15 | E60: STORE7 | F60: 4 | G60: 733.42 | I60: PayPal | J60: 2552.3016
A61: SALE59 | B61: 45257 | C61: CUST1367 | D61: PROD89 | E61: STORE11 | F61: 1 | G61: 996.33 | H61: 0.23 | I61: PayPal | J61: 767.1741
A62: SALE60 | B62: 45854 | C62: CUST1408 | D62: PROD31 | E62: STORE10 | F62: 1 | G62: 198.83 | H62: 0.09 | I62: COD | J62: 180.9353
A63: SALE61 | B63: 45716 | C63: CUST1239 | D63: PROD19 | E63: STORE7 | F63: 1 | G63: 374.92 | H63: 0.18 | I63: PayPal | J63: 307.4344
A64: SALE62 | B64: 45515 | C64: CUST1464 | D64: PROD93 | E64: STORE16 | F64: 1 | G64: 468.94 | H64: 0.12 | I64: Credit Card | J64: 412.6672
A65: SALE63 | B65: 45927 | C65: CUST1126 | D65: PROD89 | E65: STORE12 | F65: 2 | G65: 121.37 | H65: 0.05 | I65: Credit Card | J65: 230.603
A66: SALE64 | B66: 45914 | C66: CUST1255 | D66: PROD53 | E66: STORE10 | F66: 3 | G66: 480.06 | H66: 0.01 | I66: Credit Card
A67: SALE65 | B67: 45290 | C67: CUST1162 | D67: PROD99 | E67: STORE17 | F67: 2 | G67: 856.57 | H67: 0.24 | I67: Credit Card | J67: 1301.9864
A68: SALE66 | B68: 45213 | C68: CUST1269 | D68: PROD77 | E68: STORE2 | F68: 4 | G68: 814.25 | H68: 0.18 | I68: Credit Card | J68: 2670.74
A69: SALE67 | B69: 45255 | C69: CUST1483 | D69: PROD12 | E69: STORE2 | F69: 1 | G69: 989.17 | H69: 0.2 | I69: PayPal | J69: 791.336
A70: SALE68 | B70: 45270 | C70: CUST1372 | D70: PROD72 | E70: STORE10 | F70: 4 | G70: 62.48 | H70: 0.18 | I70: Credit Card | J70: 204.9344
A71: SALE69 | B71: 45897 | C71: CUST1423 | D71: PROD13 | E71: STORE16 | F71: 4 | G71: 561.24 | H71: 0.24 | I71: Credit Card | J71: 1706.1696
A72: SALE70 | B72: 45849 | C72: CUST1058 | D72: PROD60 | E72: STORE5 | F72: 3 | G72: 92.24 | H72: 0.28 | I72: COD
A73: SALE71 | B73: 45889 | C73: CUST1168 | D73: PROD72 | E73: STORE1 | F73: 2 | G73: 668.3 | H73: 0.07 | I73: Credit Card | J73: 1243.038
A74: SALE72 | B74: 45533 | C74: CUST1409 | D74: PROD38 | E74: STORE5 | F74: 1 | G74: 553.82 | H74: 0.09 | I74: Credit Card | J74: 503.9762
A75: SALE73 | B75: 45626 | C75: CUST1037 | D75: PROD45 | E75: STORE11 | F75: 2 | G75: 556.43 | H75: 0.13 | I75: Credit Card | J75: 968.1882
A76: SALE74 | B76: 45942 | C76: CUST1273 | D76: PROD20 | E76: STORE8 | F76: 1 | G76: 184.98 | H76: 0.1 | I76: COD | J76: 166.482
A77: SALE75 | B77: 45500 | C77: CUST1035 | D77: PROD97 | E77: STORE12 | F77: 4 | G77: 700.18 | H77: 0.23 | I77: Credit Card | J77: 2156.5544
A78: SALE76 | B78: 45285 | C78: CUST1019 | D78: PROD76 | E78: STORE10 | F78: 2 | G78: 686.31 | H78: 0.25 | I78: Credit Card | J78: 1029.465
A79: SALE77 | B79: 45800 | C79: CUST1007 | D79: PROD67 | E79: STORE15 | F79: 1 | G79: 687.82 | H79: 0.27 | I79: COD | J79: 502.1086
A80: SALE78 | B80: 45609 | C80: CUST1221 | D80: PROD83 | E80: STORE8 | F80: 2 | G80: 900.55 | H80: 0.16 | I80: Credit Card | J80: 1512.924
A81: SALE79 | B81: 45268 | C81: CUST1115 | D81: PROD21 | E81: STORE2 | F81: 1 | G81: 341.17 | H81: 0.15 | I81: Credit Card | J81: 289.9945
A82: SALE80 | B82: 45885 | C82: CUST1176 | D82: PROD52 | E82: STORE8 | F82: 1 | G82: 442.27 | H82: 0.06 | I82: COD | J82: 415.7338
A83: SALE81 | B83: 45616 | C83: CUST1253 | D83: PROD71 | E83: STORE9 | F83: 1 | G83: 363.73 | H83: 0.25 | I83: PayPal | J83: 272.7975
A84: SALE82 | B84: 45518 | C84: CUST1378 | D84: PROD91 | E84: STORE17 | F84: 2 | G84: 601.33 | H84: 0.16 | I84: PayPal | J84: 1010.2344
A85: SALE83 | B85: 45427 | C85: CUST1403 | D85: PROD17 | E85: STORE18 | F85: 4 | G85: 34.39 | H85: 0.03 | I85: PayPal | J85: 133.4332
A86: SALE84 | B86: 45268 | C86: CUST1423 | D86: PROD46 | E86: STORE17 | F86: 1 | G86: 773.57 | H86: 0.05 | I86: COD
A87: SALE85 | B87: 45282 | C87: CUST1054 | D87: PROD88 | E87: STORE7 | F87: 4 | G87: 127.1 | H87: 0.24 | I87: COD | J87: 386.384
A88: SALE86 | B88: 45545 | C88: CUST1303 | D88: PROD20 | E88: STORE3 | F88: 3 | G88: 899.58 | H88: 0.28 | I88: PayPal | J88: 1943.0928
A89: SALE87 | B89: 45755 | C89: CUST1327 | D89: PROD1 | E89: STORE10 | F89: 3 | G89: 964.39 | H89: 0.04 | I89: Credit Card | J89: 2777.4432
A90: SALE88 | B90: 45588 | C90: CUST1183 | D90: PROD38 | E90: STORE0 | F90: 2 | G90: 217.83 | H90: 0.14 | I90: PayPal | J90: 374.6676
A91: SALE89 | B91: 45848 | C91: CUST1143 | D91: PROD17 | E91: STORE1 | F91: 4 | G91: 187.71 | H91: 0.06 | I91: COD | J91: 705.7896
A92: SALE90 | B92: 45577 | C92: CUST1010 | D92: PROD33 | E92: STORE18 | F92: 2 | G92: 350.12 | H92: 0.12 | I92: COD | J92: 616.2112
A93: SALE91 | B93: 45312 | C93: CUST1406 | D93: PROD16 | E93: STORE1 | F93: 4 | G93: 102.19 | H93: 0.17 | I93: PayPal | J93: 339.2708
A94: SALE92 | B94: 45350 | C94: CUST1007 | D94: PROD86 | E94: STORE4 | F94: 1 | G94: 696.53 | H94: 0.17 | I94: Credit Card | J94: 578.1199
A95: SALE93 | B95: 45657 | C95: CUST1065 | D95: PROD19 | E95: STORE4 | F95: 2 | G95: 327.52 | H95: 0.15 | I95: PayPal | J95: 556.784
A96: SALE94 | B96: 45530 | C96: CUST1298 | D96: PROD97 | E96: STORE19 | F96: 2 | G96: 569.36 | H96: 0.01 | I96: PayPal
A97: SALE95 | B97: 45556 | C97: CUST1321 | D97: PROD99 | E97: STORE6 | F97: 2 | G97: 68.29 | H97: 0.14 | I97: COD | J97: 117.4588
A98: SALE96 | B98: 45523 | C98: CUST1244 | D98: PROD50 | E98: STORE10 | F98: 1 | G98: 842.9 | H98: 0.06 | I98: COD | J98: 792.326
A99: SALE97 | B99: 45587 | C99: CUST1287 | D99: PROD3 | E99: STORE3 | F99: 3 | G99: 751.94 | H99: 0.26 | I99: PayPal | J99: 1669.3068
A100: SALE98 | B100: 45580 | C100: CUST1131 | D100: PROD56 | E100: STORE7 | F100: 4 | G100: 476.28 | H100: 0.17 | I100: Credit Card | J100: 1581.2496
...

Sheet Cleaned Sales_Facts
A1: Sales_ID | B1: Order_Date (Delimited) | C1: Customer_ID | D1: Product_ID | E1: Store_ID | F1: Quantity | G1: Unit_Price | H1: Discount | I1: Payment_Type | J1: Total_Amount | K1: New Quantity | L1: New Unit Price | M1: New Discount | N1: New Total Amount | O1: Age | P1: Gender | Q1: New Loyalty | R1: Category | S1: Unit Cost | T1: Stock | U1: Region | V1: Store Type | W1: New City (Replace)
A2: SALE0 | B2: 45480 | C2: CUST1409 | D2: PROD97 | E2: STORE3 | F2: 1 | G2: 218.04 | H2: 0.09 | I2: Credit Card | J2: 198.4164 | K2: =IF(F2="",J2/(G2*(1-H2)),F2) -> 1 | L2: =IF(G2="",J2/(K2*(1-H2)),G2) -> 218.04 | M2: =IF(H2="",1-(J2/(K2*L2)),H2) -> 0.09 | N2: =IF(J2="",F2*G2*(1-H2),J2) -> 198.4164 | O2: =VLOOKUP(C2,'Cleaned Customer Dim'!$A$2:$D$501,4,FALSE) -> 55 | P2: =VLOOKUP(C2,'Cleaned Customer Dim'!$A$2:$E$501,5,FALSE) -> Male | Q2: =VLOOKUP(C2,'Cleaned Customer Dim'!$A$2:$J$501,10,FALSE) -> Gold | R2: =VLOOKUP(D2,'Cleaned Product Dim'!$A$2:$C$101,3,FALSE) -> Sports | S2: =VLOOKUP(D2,'Cleaned Product Dim'!$A$2:$G$101,7,FALSE) -> 245.98 | T2: =VLOOKUP(D2,'Cleaned Product Dim'!$A$2:$H$101,8,FALSE) -> 471 | U2: =VLOOKUP(E2,'Cleaned Store Dim'!$A$2:$C$21,3,FALSE) -> North | V2: =VLOOKUP(E2,'Cleaned Store Dim'!$A$2:$E$21,5,FALSE) -> Outlet | W2: =VLOOKUP(E2,'Cleaned Store Dim'!$A$2:$F$21,6,FALSE) -> Goldberg | Y2: New Quantity | AA2: New Unit Price | AC2: New Discount | AE2: New Total Amount
A3: SALE1 | B3: 45285 | C3: CUST1467 | D3: PROD74 | E3: STORE17 | F3: 3 | G3: 104.47 | H3: 0.27 | I3: PayPal | J3: 228.7893 | K3: =IF(F3="",J3/(G3*(1-H3)),F3) -> 3 | L3: =IF(G3="",J3/(K3*(1-H3)),G3) -> 104.47 | M3: =IF(H3="",1-(J3/(K3*L3)),H3) -> 0.27 | N3: =IF(J3="",F3*G3*(1-H3),J3) -> 228.7893 | O3: =VLOOKUP(C3,'Cleaned Customer Dim'!$A$2:$D$501,4,FALSE) -> 63 | P3: =VLOOKUP(C3,'Cleaned Customer Dim'!$A$2:$E$501,5,FALSE) -> Female | Q3: =VLOOKUP(C3,'Cleaned Customer Dim'!$A$2:$J$501,10,FALSE) -> Gold | R3: =VLOOKUP(D3,'Cleaned Product Dim'!$A$2:$C$101,3,FALSE) -> Electronics | S3: =VLOOKUP(D3,'Cleaned Product Dim'!$A$2:$G$101,7,FALSE) -> 403.71 | T3: =VLOOKUP(D3,'Cleaned Product Dim'!$A$2:$H$101,8,FALSE) -> 159 | U3: =VLOOKUP(E3,'Cleaned Store Dim'!$A$2:$C$21,3,FALSE) -> North | V3: =VLOOKUP(E3,'Cleaned Store Dim'!$A$2:$E$21,5,FALSE) -> Flagship | W3: =VLOOKUP(E3,'Cleaned Store Dim'!$A$2:$F$21,6,FALSE) -> Benson
A4: SALE2 | B4: 45357 | C4: CUST1056 | D4: PROD49 | E4: STORE8 | F4: 4 | G4: 914.05 | H4: 0.25 | I4: Credit Card | J4: 2742.15 | K4: =IF(F4="",J4/(G4*(1-H4)),F4) -> 4 | L4: =IF(G4="",J4/(K4*(1-H4)),G4) -> 914.05 | M4: =IF(H4="",1-(J4/(K4*L4)),H4) -> 0.25 | N4: =IF(J4="",F4*G4*(1-H4),J4) -> 2742.15 | O4: =VLOOKUP(C4,'Cleaned Customer Dim'!$A$2:$D$501,4,FALSE) -> 49 | P4: =VLOOKUP(C4,'Cleaned Customer Dim'!$A$2:$E$501,5,FALSE) -> Female | Q4: =VLOOKUP(C4,'Cleaned Customer Dim'!$A$2:$J$501,10,FALSE) -> Gold | R4: =VLOOKUP(D4,'Cleaned Product Dim'!$A$2:$C$101,3,FALSE) -> Beauty | S4: =VLOOKUP(D4,'Cleaned Product Dim'!$A$2:$G$101,7,FALSE) -> 43.29 | T4: =VLOOKUP(D4,'Cleaned Product Dim'!$A$2:$H$101,8,FALSE) -> 267 | U4: =VLOOKUP(E4,'Cleaned Store Dim'!$A$2:$C$21,3,FALSE) -> West | V4: =VLOOKUP(E4,'Cleaned Store Dim'!$A$2:$E$21,5,FALSE) -> Online | W4: =VLOOKUP(E4,'Cleaned Store Dim'!$A$2:$F$21,6,FALSE) -> Thompson | Y4: Mean | Z4: 2.482 | AA4: Mean | AB4: 513.58279 | AC4: Mean | AD4: 0.14796 | AE4: Mean | AF4: 1087.1973
A5: SALE3 | B5: 45259 | C5: CUST1346 | D5: PROD76 | E5: STORE8 | F5: 1 | G5: 921.51 | H5: 0.16 | I5: COD | J5: 774.0684 | K5: =IF(F5="",J5/(G5*(1-H5)),F5) -> 1 | L5: =IF(G5="",J5/(K5*(1-H5)),G5) -> 921.51 | M5: =IF(H5="",1-(J5/(K5*L5)),H5) -> 0.16 | N5: =IF(J5="",F5*G5*(1-H5),J5) -> 774.0684 | O5: =VLOOKUP(C5,'Cleaned Customer Dim'!$A$2:$D$501,4,FALSE) -> 58 | P5: =VLOOKUP(C5,'Cleaned Customer Dim'!$A$2:$E$501,5,FALSE) -> Female | Q5: =VLOOKUP(C5,'Cleaned Customer Dim'!$A$2:$J$501,10,FALSE) -> Platinum | R5: =VLOOKUP(D5,'Cleaned Product Dim'!$A$2:$C$101,3,FALSE) -> Electronics | S5: =VLOOKUP(D5,'Cleaned Product Dim'!$A$2:$G$101,7,FALSE) -> 392.89 | T5: =VLOOKUP(D5,'Cleaned Product Dim'!$A$2:$H$101,8,FALSE) -> 320 | U5: =VLOOKUP(E5,'Cleaned Store Dim'!$A$2:$C$21,3,FALSE) -> West | V5: =VLOOKUP(E5,'Cleaned Store Dim'!$A$2:$E$21,5,FALSE) -> Online | W5: =VLOOKUP(E5,'Cleaned Store Dim'!$A$2:$F$21,6,FALSE) -> Thompson | Y5: Standard Error | Z5: 0.024852501 | AA5: Standard Error | AB5: 6.3134988 | AC5: Standard Error | AD5: 0.0019598571 | AE5: Standard Error | AF5: 18.327237
A6: SALE4 | B6: 45444 | C6: CUST1493 | D6: PROD59 | E6: STORE5 | F6: 3 | G6: 745.3 | H6: 0.18 | I6: Credit Card | J6: 1833.438 | K6: =IF(F6="",J6/(G6*(1-H6)),F6) -> 3 | L6: =IF(G6="",J6/(K6*(1-H6)),G6) -> 745.3 | M6: =IF(H6="",1-(J6/(K6*L6)),H6) -> 0.18 | N6: =IF(J6="",F6*G6*(1-H6),J6) -> 1833.438 | O6: =VLOOKUP(C6,'Cleaned Customer Dim'!$A$2:$D$501,4,FALSE) -> 28 | P6: =VLOOKUP(C6,'Cleaned Customer Dim'!$A$2:$E$501,5,FALSE) -> Male | Q6: =VLOOKUP(C6,'Cleaned Customer Dim'!$A$2:$J$501,10,FALSE) -> Silver | R6: =VLOOKUP(D6,'Cleaned Product Dim'!$A$2:$C$101,3,FALSE) -> Beauty | S6: =VLOOKUP(D6,'Cleaned Product Dim'!$A$2:$G$101,7,FALSE) -> 17.31 | T6: =VLOOKUP(D6,'Cleaned Product Dim'!$A$2:$H$101,8,FALSE) -> 399 | U6: =VLOOKUP(E6,'Cleaned Store Dim'!$A$2:$C$21,3,FALSE) -> North | V6: =VLOOKUP(E6,'Cleaned Store Dim'!$A$2:$E$21,5,FALSE) -> Outlet | W6: =VLOOKUP(E6,'Cleaned Store Dim'!$A$2:$F$21,6,FALSE) -> Chester | Y6: Median | Z6: 2 | AA6: Median | AB6: 522.43 | AC6: Median | AD6: 0.14 | AE6: Median | AF6: 868.7182
A7: SALE5 | B7: 45499 | C7: CUST1116 | D7: PROD15 | E7: STORE7 | F7: 3 | G7: 147.01 | H7: 0.19 | I7: COD | J7: 357.2343 | K7: =IF(F7="",J7/(G7*(1-H7)),F7) -> 3 | L7: =IF(G7="",J7/(K7*(1-H7)),G7) -> 147.01 | M7: =IF(H7="",1-(J7/(K7*L7)),H7) -> 0.19 | N7: =IF(J7="",F7*G7*(1-H7),J7) -> 357.2343 | O7: =VLOOKUP(C7,'Cleaned Customer Dim'!$A$2:$D$501,4,FALSE) -> 18 | P7: =VLOOKUP(C7,'Cleaned Customer Dim'!$A$2:$E$501,5,FALSE) -> Female | Q7: =VLOOKUP(C7,'Cleaned Customer Dim'!$A$2:$J$501,10,FALSE) -> Platinum | R7: =VLOOKUP(D7,'Cleaned Product Dim'!$A$2:$C$101,3,FALSE) -> Electronics | S7: =VLOOKUP(D7,'Cleaned Product Dim'!$A$2:$G$101,7,FALSE) -> 465.34 | T7: =VLOOKUP(D7,'Cleaned Product Dim'!$A$2:$H$101,8,FALSE) -> 301 | U7: =VLOOKUP(E7,'Cleaned Store Dim'!$A$2:$C$21,3,FALSE) -> South | V7: =VLOOKUP(E7,'Cleaned Store Dim'!$A$2:$E$21,5,FALSE) -> Online | W7: =VLOOKUP(E7,'Cleaned Store Dim'!$A$2:$F$21,6,FALSE) -> Williamsport | Y7: Mode | Z7: 2 | AA7: Mode | AB7: 871.34 | AC7: Mode | AD7: 0.1 | AE7: Mode | AF7: #N/A
A8: SALE6 | B8: 45998 | C8: CUST1016 | D8: PROD56 | E8: STORE4 | F8: 2 | G8: 785.31 | H8: 0.15 | I8: PayPal | J8: 1335.027 | K8: =IF(F8="",J8/(G8*(1-H8)),F8) -> 2 | L8: =IF(G8="",J8/(K8*(1-H8)),G8) -> 785.31 | M8: =IF(H8="",1-(J8/(K8*L8)),H8) -> 0.15 | N8: =IF(J8="",F8*G8*(1-H8),J8) -> 1335.027 | O8: =VLOOKUP(C8,'Cleaned Customer Dim'!$A$2:$D$501,4,FALSE) -> 24 | P8: =VLOOKUP(C8,'Cleaned Customer Dim'!$A$2:$E$501,5,FALSE) -> Female | Q8: =VLOOKUP(C8,'Cleaned Customer Dim'!$A$2:$J$501,10,FALSE) -> Bronze | R8: =VLOOKUP(D8,'Cleaned Product Dim'!$A$2:$C$101,3,FALSE) -> Home | S8: =VLOOKUP(D8,'Cleaned Product Dim'!$A$2:$G$101,7,FALSE) -> 461.47 | T8: =VLOOKUP(D8,'Cleaned Product Dim'!$A$2:$H$101,8,FALSE) -> 190 | U8: =VLOOKUP(E8,'Cleaned Store Dim'!$A$2:$C$21,3,FALSE) -> South | V8: =VLOOKUP(E8,'Cleaned Store Dim'!$A$2:$E$21,5,FALSE) -> Online | W8: =VLOOKUP(E8,'Cleaned Store Dim'!$A$2:$F$21,6,FALSE) -> Sharon | Y8: Standard Deviation | Z8: 1.1114376 | AA8: Standard Deviation | AB8: 282.34825 | AC8: Standard Deviation | AD8: 0.087647473 | AE8: Standard Deviation | AF8: 819.61896
A9: SALE7 | B9: 45248 | C9: CUST1152 | D9: PROD70 | E9: STORE8 | F9: 4 | G9: 342.39 | H9: 0.23 | I9: PayPal | J9: 1054.5612 | K9: =IF(F9="",J9/(G9*(1-H9)),F9) -> 4 | L9: =IF(G9="",J9/(K9*(1-H9)),G9) -> 342.39 | M9: =IF(H9="",1-(J9/(K9*L9)),H9) -> 0.23 | N9: =IF(J9="",F9*G9*(1-H9),J9) -> 1054.5612 | O9: =VLOOKUP(C9,'Cleaned Customer Dim'!$A$2:$D$501,4,FALSE) -> 41 | P9: =VLOOKUP(C9,'Cleaned Customer Dim'!$A$2:$E$501,5,FALSE) -> Female | Q9: =VLOOKUP(C9,'Cleaned Customer Dim'!$A$2:$J$501,10,FALSE) -> Platinum | R9: =VLOOKUP(D9,'Cleaned Product Dim'!$A$2:$C$101,3,FALSE) -> Home | S9: =VLOOKUP(D9,'Cleaned Product Dim'!$A$2:$G$101,7,FALSE) -> 138.05 | T9: =VLOOKUP(D9,'Cleaned Product Dim'!$A$2:$H$101,8,FALSE) -> 89 | U9: =VLOOKUP(E9,'Cleaned Store Dim'!$A$2:$C$21,3,FALSE) -> West | V9: =VLOOKUP(E9,'Cleaned Store Dim'!$A$2:$E$21,5,FALSE) -> Online | W9: =VLOOKUP(E9,'Cleaned Store Dim'!$A$2:$F$21,6,FALSE) -> Thompson | Y9: Sample Variance | Z9: 1.2352936 | AA9: Sample Variance | AB9: 79720.534 | AC9: Sample Variance | AD9: 0.0076820794 | AE9: Sample Variance | AF9: 671775.25
A10: SALE8 | B10: 45752 | C10: CUST1187 | D10: PROD99 | E10: STORE5 | G10: 448.25 | H10: 0.07 | I10: PayPal | J10: 1250.6175 | K10: =IF(F10="",J10/(G10*(1-H10)),F10) -> 3 | L10: =IF(G10="",J10/(K10*(1-H10)),G10) -> 448.25 | M10: =IF(H10="",1-(J10/(K10*L10)),H10) -> 0.07 | N10: =IF(J10="",F10*G10*(1-H10),J10) -> 1250.6175 | O10: =VLOOKUP(C10,'Cleaned Customer Dim'!$A$2:$D$501,4,FALSE) -> 60 | P10: =VLOOKUP(C10,'Cleaned Customer Dim'!$A$2:$E$501,5,FALSE) -> Female | Q10: =VLOOKUP(C10,'Cleaned Customer Dim'!$A$2:$J$501,10,FALSE) -> Platinum | R10: =VLOOKUP(D10,'Cleaned Product Dim'!$A$2:$C$101,3,FALSE) -> Home | S10: =VLOOKUP(D10,'Cleaned Product Dim'!$A$2:$G$101,7,FALSE) -> 201.41 | T10: =VLOOKUP(D10,'Cleaned Product Dim'!$A$2:$H$101,8,FALSE) -> 146 | U10: =VLOOKUP(E10,'Cleaned Store Dim'!$A$2:$C$21,3,FALSE) -> North | V10: =VLOOKUP(E10,'Cleaned Store Dim'!$A$2:$E$21,5,FALSE) -> Outlet | W10: =VLOOKUP(E10,'Cleaned Store Dim'!$A$2:$F$21,6,FALSE) -> Chester | Y10: Kurtosis | Z10: -1.3441226 | AA10: Kurtosis | AB10: -1.1931883 | AC10: Kurtosis | AD10: -1.208024 | AE10: Kurtosis | AF10: 0.045826153
A11: SALE9 | B11: 45869 | C11: CUST1464 | D11: PROD33 | E11: STORE0 | F11: 2 | G11: 873.17 | H11: 0.23 | I11: PayPal | J11: 1344.6818 | K11: =IF(F11="",J11/(G11*(1-H11)),F11) -> 2 | L11: =IF(G11="",J11/(K11*(1-H11)),G11) -> 873.17 | M11: =IF(H11="",1-(J11/(K11*L11)),H11) -> 0.23 | N11: =IF(J11="",F11*G11*(1-H11),J11) -> 1344.6818 | O11: =VLOOKUP(C11,'Cleaned Customer Dim'!$A$2:$D$501,4,FALSE) -> 45 | P11: =VLOOKUP(C11,'Cleaned Customer Dim'!$A$2:$E$501,5,FALSE) -> Female | Q11: =VLOOKUP(C11,'Cleaned Customer Dim'!$A$2:$J$501,10,FALSE) -> Platinum | R11: =VLOOKUP(D11,'Cleaned Product Dim'!$A$2:$C$101,3,FALSE) -> Home | S11: =VLOOKUP(D11,'Cleaned Product Dim'!$A$2:$G$101,7,FALSE) -> 179.77 | T11: =VLOOKUP(D11,'Cleaned Product Dim'!$A$2:$H$101,8,FALSE) -> 305 | U11: =VLOOKUP(E11,'Cleaned Store Dim'!$A$2:$C$21,3,FALSE) -> East | V11: =VLOOKUP(E11,'Cleaned Store Dim'!$A$2:$E$21,5,FALSE) -> Flagship | W11: =VLOOKUP(E11,'Cleaned Store Dim'!$A$2:$F$21,6,FALSE) -> Washington | Y11: Skewness | Z11: 0.022378357 | AA11: Skewness | AB11: -0.034813907 | AC11: Skewness | AD11: 0.062951035 | AE11: Skewness | AF11: 0.87904704
A12: SALE10 | B12: 45335 | C12: CUST1065 | D12: PROD24 | E12: STORE14 | F12: 1 | G12: 278.63 | H12: 0.07 | I12: Credit Card | J12: 259.1259 | K12: =IF(F12="",J12/(G12*(1-H12)),F12) -> 1 | L12: =IF(G12="",J12/(K12*(1-H12)),G12) -> 278.63 | M12: =IF(H12="",1-(J12/(K12*L12)),H12) -> 0.07 | N12: =IF(J12="",F12*G12*(1-H12),J12) -> 259.1259 | O12: =VLOOKUP(C12,'Cleaned Customer Dim'!$A$2:$D$501,4,FALSE) -> 21 | P12: =VLOOKUP(C12,'Cleaned Customer Dim'!$A$2:$E$501,5,FALSE) -> Female | Q12: =VLOOKUP(C12,'Cleaned Customer Dim'!$A$2:$J$501,10,FALSE) -> Silver | R12: =VLOOKUP(D12,'Cleaned Product Dim'!$A$2:$C$101,3,FALSE) -> Sports | S12: =VLOOKUP(D12,'Cleaned Product Dim'!$A$2:$G$101,7,FALSE) -> 166.06 | T12: =VLOOKUP(D12,'Cleaned Product Dim'!$A$2:$H$101,8,FALSE) -> 340 | U12: =VLOOKUP(E12,'Cleaned Store Dim'!$A$2:$C$21,3,FALSE) -> South | V12: =VLOOKUP(E12,'Cleaned Store Dim'!$A$2:$E$21,5,FALSE) -> Outlet | W12: =VLOOKUP(E12,'Cleaned Store Dim'!$A$2:$F$21,6,FALSE) -> Christopher | Y12: Range | Z12: 3 | AA12: Range | AB12: 979.8 | AC12: Range | AD12: 0.3 | AE12: Range | AF12: 3889.7838
A13: SALE11 | B13: 45801 | C13: CUST1320 | D13: PROD39 | E13: STORE1 | F13: 4 | G13: 286.92 | H13: 0.17 | I13: Credit Card | J13: 952.5744 | K13: =IF(F13="",J13/(G13*(1-H13)),F13) -> 4 | L13: =IF(G13="",J13/(K13*(1-H13)),G13) -> 286.92 | M13: =IF(H13="",1-(J13/(K13*L13)),H13) -> 0.17 | N13: =IF(J13="",F13*G13*(1-H13),J13) -> 952.5744 | O13: =VLOOKUP(C13,'Cleaned Customer Dim'!$A$2:$D$501,4,FALSE) -> 34 | P13: =VLOOKUP(C13,'Cleaned Customer Dim'!$A$2:$E$501,5,FALSE) -> Female | Q13: =VLOOKUP(C13,'Cleaned Customer Dim'!$A$2:$J$501,10,FALSE) -> Bronze | R13: =VLOOKUP(D13,'Cleaned Product Dim'!$A$2:$C$101,3,FALSE) -> Electronics | S13: =VLOOKUP(D13,'Cleaned Product Dim'!$A$2:$G$101,7,FALSE) -> 326.06 | T13: =VLOOKUP(D13,'Cleaned Product Dim'!$A$2:$H$101,8,FALSE) -> 301 | U13: =VLOOKUP(E13,'Cleaned Store Dim'!$A$2:$C$21,3,FALSE) -> North | V13: =VLOOKUP(E13,'Cleaned Store Dim'!$A$2:$E$21,5,FALSE) -> Flagship | W13: =VLOOKUP(E13,'Cleaned Store Dim'!$A$2:$F$21,6,FALSE) -> Daniel | Y13: Minimum | Z13: 1 | AA13: Minimum | AB13: 20.09 | AC13: Minimum | AD13: 0 | AE13: Minimum | AF13: 18.459
A14: SALE12 | B14: 45528 | C14: CUST1237 | D14: PROD88 | E14: STORE4 | F14: 4 | G14: 644.58 | H14: 0.01 | I14: Credit Card | J14: 2552.5368 | K14: =IF(F14="",J14/(G14*(1-H14)),F14) -> 4 | L14: =IF(G14="",J14/(K14*(1-H14)),G14) -> 644.58 | M14: =IF(H14="",1-(J14/(K14*L14)),H14) -> 0.01 | N14: =IF(J14="",F14*G14*(1-H14),J14) -> 2552.5368 | O14: =VLOOKUP(C14,'Cleaned Customer Dim'!$A$2:$D$501,4,FALSE) -> 41 | P14: =VLOOKUP(C14,'Cleaned Customer Dim'!$A$2:$E$501,5,FALSE) -> Female | Q14: =VLOOKUP(C14,'Cleaned Customer Dim'!$A$2:$J$501,10,FALSE) -> Gold | R14: =VLOOKUP(D14,'Cleaned Product Dim'!$A$2:$C$101,3,FALSE) -> Sports | S14: =VLOOKUP(D14,'Cleaned Product Dim'!$A$2:$G$101,7,FALSE) -> 131.24 | T14: =VLOOKUP(D14,'Cleaned Product Dim'!$A$2:$H$101,8,FALSE) -> 232 | U14: =VLOOKUP(E14,'Cleaned Store Dim'!$A$2:$C$21,3,FALSE) -> South | V14: =VLOOKUP(E14,'Cleaned Store Dim'!$A$2:$E$21,5,FALSE) -> Online | W14: =VLOOKUP(E14,'Cleaned Store Dim'!$A$2:$F$21,6,FALSE) -> Sharon | Y14: Maximum | Z14: 4 | AA14: Maximum | AB14: 999.89 | AC14: Maximum | AD14: 0.3 | AE14: Maximum | AF14: 3908.2428
A15: SALE13 | B15: 45816 | C15: CUST1443 | D15: PROD34 | E15: STORE16 | F15: 2 | G15: 316.9 | H15: 0.3 | I15: PayPal | J15: 443.66 | K15: =IF(F15="",J15/(G15*(1-H15)),F15) -> 2 | L15: =IF(G15="",J15/(K15*(1-H15)),G15) -> 316.9 | M15: =IF(H15="",1-(J15/(K15*L15)),H15) -> 0.3 | N15: =IF(J15="",F15*G15*(1-H15),J15) -> 443.66 | O15: =VLOOKUP(C15,'Cleaned Customer Dim'!$A$2:$D$501,4,FALSE) -> 51 | P15: =VLOOKUP(C15,'Cleaned Customer Dim'!$A$2:$E$501,5,FALSE) -> Male | Q15: =VLOOKUP(C15,'Cleaned Customer Dim'!$A$2:$J$501,10,FALSE) -> Silver | R15: =VLOOKUP(D15,'Cleaned Product Dim'!$A$2:$C$101,3,FALSE) -> Electronics | S15: =VLOOKUP(D15,'Cleaned Product Dim'!$A$2:$G$101,7,FALSE) -> 419.28 | T15: =VLOOKUP(D15,'Cleaned Product Dim'!$A$2:$H$101,8,FALSE) -> 86 | U15: =VLOOKUP(E15,'Cleaned Store Dim'!$A$2:$C$21,3,FALSE) -> West | V15: =VLOOKUP(E15,'Cleaned Store Dim'!$A$2:$E$21,5,FALSE) -> Flagship | W15: =VLOOKUP(E15,'Cleaned Store Dim'!$A$2:$F$21,6,FALSE) -> New Jimmy | Y15: Sum | Z15: 4964 | AA15: Sum | AB15: 1027165.6 | AC15: Sum | AD15: 295.92 | AE15: Sum | AF15: 2174394.7
A16: SALE14 | B16: 45829 | C16: CUST1348 | D16: PROD24 | E16: STORE15 | F16: 4 | G16: 403.47 | H16: 0.29 | I16: PayPal | J16: 1145.8548 | K16: =IF(F16="",J16/(G16*(1-H16)),F16) -> 4 | L16: =IF(G16="",J16/(K16*(1-H16)),G16) -> 403.47 | M16: =IF(H16="",1-(J16/(K16*L16)),H16) -> 0.29 | N16: =IF(J16="",F16*G16*(1-H16),J16) -> 1145.8548 | O16: =VLOOKUP(C16,'Cleaned Customer Dim'!$A$2:$D$501,4,FALSE) -> 55 | P16: =VLOOKUP(C16,'Cleaned Customer Dim'!$A$2:$E$501,5,FALSE) -> Male | Q16: =VLOOKUP(C16,'Cleaned Customer Dim'!$A$2:$J$501,10,FALSE) -> Silver | R16: =VLOOKUP(D16,'Cleaned Product Dim'!$A$2:$C$101,3,FALSE) -> Sports | S16: =VLOOKUP(D16,'Cleaned Product Dim'!$A$2:$G$101,7,FALSE) -> 166.06 | T16: =VLOOKUP(D16,'Cleaned Product Dim'!$A$2:$H$101,8,FALSE) -> 340 | U16: =VLOOKUP(E16,'Cleaned Store Dim'!$A$2:$C$21,3,FALSE) -> North | V16: =VLOOKUP(E16,'Cleaned Store Dim'!$A$2:$E$21,5,FALSE) -> Flagship | W16: =VLOOKUP(E16,'Cleaned Store Dim'!$A$2:$F$21,6,FALSE) -> Jenniferstad | Y16: Count | Z16: 2000 | AA16: Count | AB16: 2000 | AC16: Count | AD16: 2000 | AE16: Count | AF16: 2000
A17: SALE15 | B17: 45577 | C17: CUST1435 | D17: PROD36 | E17: STORE9 | G17: 871.34 | H17: 0.04 | I17: COD | J17: 2509.4592 | K17: =IF(F17="",J17/(G17*(1-H17)),F17) -> 3 | L17: =IF(G17="",J17/(K17*(1-H17)),G17) -> 871.34 | M17: =IF(H17="",1-(J17/(K17*L17)),H17) -> 0.04 | N17: =IF(J17="",F17*G17*(1-H17),J17) -> 2509.4592 | O17: =VLOOKUP(C17,'Cleaned Customer Dim'!$A$2:$D$501,4,FALSE) -> 37 | P17: =VLOOKUP(C17,'Cleaned Customer Dim'!$A$2:$E$501,5,FALSE) -> Female | Q17: =VLOOKUP(C17,'Cleaned Customer Dim'!$A$2:$J$501,10,FALSE) -> Silver | R17: =VLOOKUP(D17,'Cleaned Product Dim'!$A$2:$C$101,3,FALSE) -> Clothing | S17: =VLOOKUP(D17,'Cleaned Product Dim'!$A$2:$G$101,7,FALSE) -> 223.43 | T17: =VLOOKUP(D17,'Cleaned Product Dim'!$A$2:$H$101,8,FALSE) -> 154 | U17: =VLOOKUP(E17,'Cleaned Store Dim'!$A$2:$C$21,3,FALSE) -> South | V17: =VLOOKUP(E17,'Cleaned Store Dim'!$A$2:$E$21,5,FALSE) -> Flagship | W17: =VLOOKUP(E17,'Cleaned Store Dim'!$A$2:$F$21,6,FALSE) -> Johnstad
A18: SALE16 | B18: 45913 | C18: CUST1276 | D18: PROD65 | E18: STORE19 | F18: 2 | G18: 451.98 | H18: 0.25 | I18: Credit Card | J18: 677.97 | K18: =IF(F18="",J18/(G18*(1-H18)),F18) -> 2 | L18: =IF(G18="",J18/(K18*(1-H18)),G18) -> 451.98 | M18: =IF(H18="",1-(J18/(K18*L18)),H18) -> 0.25 | N18: =IF(J18="",F18*G18*(1-H18),J18) -> 677.97 | O18: =VLOOKUP(C18,'Cleaned Customer Dim'!$A$2:$D$501,4,FALSE) -> 38 | P18: =VLOOKUP(C18,'Cleaned Customer Dim'!$A$2:$E$501,5,FALSE) -> Male | Q18: =VLOOKUP(C18,'Cleaned Customer Dim'!$A$2:$J$501,10,FALSE) -> Gold | R18: =VLOOKUP(D18,'Cleaned Product Dim'!$A$2:$C$101,3,FALSE) -> Sports | S18: =VLOOKUP(D18,'Cleaned Product Dim'!$A$2:$G$101,7,FALSE) -> 240.63 | T18: =VLOOKUP(D18,'Cleaned Product Dim'!$A$2:$H$101,8,FALSE) -> 423 | U18: =VLOOKUP(E18,'Cleaned Store Dim'!$A$2:$C$21,3,FALSE) -> East | V18: =VLOOKUP(E18,'Cleaned Store Dim'!$A$2:$E$21,5,FALSE) -> Online | W18: =VLOOKUP(E18,'Cleaned Store Dim'!$A$2:$F$21,6,FALSE) -> Vasquez
A19: SALE17 | B19: 45608 | C19: CUST1079 | D19: PROD27 | E19: STORE4 | F19: 2 | G19: 502.69 | H19: 0.23 | I19: Credit Card | J19: 774.1426 | K19: =IF(F19="",J19/(G19*(1-H19)),F19) -> 2 | L19: =IF(G19="",J19/(K19*(1-H19)),G19) -> 502.69 | M19: =IF(H19="",1-(J19/(K19*L19)),H19) -> 0.23 | N19: =IF(J19="",F19*G19*(1-H19),J19) -> 774.1426 | O19: =VLOOKUP(C19,'Cleaned Customer Dim'!$A$2:$D$501,4,FALSE) -> 22 | P19: =VLOOKUP(C19,'Cleaned Customer Dim'!$A$2:$E$501,5,FALSE) -> Female | Q19: =VLOOKUP(C19,'Cleaned Customer Dim'!$A$2:$J$501,10,FALSE) -> Platinum | R19: =VLOOKUP(D19,'Cleaned Product Dim'!$A$2:$C$101,3,FALSE) -> Home | S19: =VLOOKUP(D19,'Cleaned Product Dim'!$A$2:$G$101,7,FALSE) -> 234.806 | T19: =VLOOKUP(D19,'Cleaned Product Dim'!$A$2:$H$101,8,FALSE) -> 378 | U19: =VLOOKUP(E19,'Cleaned Store Dim'!$A$2:$C$21,3,FALSE) -> South | V19: =VLOOKUP(E19,'Cleaned Store Dim'!$A$2:$E$21,5,FALSE) -> Online | W19: =VLOOKUP(E19,'Cleaned Store Dim'!$A$2:$F$21,6,FALSE) -> Sharon
A20: SALE18 | B20: 45517 | C20: CUST1094 | D20: PROD39 | E20: STORE4 | F20: 2 | G20: 559.23 | H20: 0.25 | I20: COD | J20: 838.845 | K20: =IF(F20="",J20/(G20*(1-H20)),F20) -> 2 | L20: =IF(G20="",J20/(K20*(1-H20)),G20) -> 559.23 | M20: =IF(H20="",1-(J20/(K20*L20)),H20) -> 0.25 | N20: =IF(J20="",F20*G20*(1-H20),J20) -> 838.845 | O20: =VLOOKUP(C20,'Cleaned Customer Dim'!$A$2:$D$501,4,FALSE) -> 43 | P20: =VLOOKUP(C20,'Cleaned Customer Dim'!$A$2:$E$501,5,FALSE) -> Female | Q20: =VLOOKUP(C20,'Cleaned Customer Dim'!$A$2:$J$501,10,FALSE) -> Gold | R20: =VLOOKUP(D20,'Cleaned Product Dim'!$A$2:$C$101,3,FALSE) -> Electronics | S20: =VLOOKUP(D20,'Cleaned Product Dim'!$A$2:$G$101,7,FALSE) -> 326.06 | T20: =VLOOKUP(D20,'Cleaned Product Dim'!$A$2:$H$101,8,FALSE) -> 301 | U20: =VLOOKUP(E20,'Cleaned Store Dim'!$A$2:$C$21,3,FALSE) -> South | V20: =VLOOKUP(E20,'Cleaned Store Dim'!$A$2:$E$21,5,FALSE) -> Online | W20: =VLOOKUP(E20,'Cleaned Store Dim'!$A$2:$F$21,6,FALSE) -> Sharon
A21: SALE19 | B21: 45369 | C21: CUST1239 | D21: PROD60 | E21: STORE13 | F21: 4 | H21: 0.04 | I21: COD | J21: 1782.4512 | K21: =IF(F21="",J21/(G21*(1-H21)),F21) -> 4 | L21: =IF(G21="",J21/(K21*(1-H21)),G21) -> 464.18 | M21: =IF(H21="",1-(J21/(K21*L21)),H21) -> 0.04 | N21: =IF(J21="",F21*G21*(1-H21),J21) -> 1782.4512 | O21: =VLOOKUP(C21,'Cleaned Customer Dim'!$A$2:$D$501,4,FALSE) -> 58 | P21: =VLOOKUP(C21,'Cleaned Customer Dim'!$A$2:$E$501,5,FALSE) -> Female | Q21: =VLOOKUP(C21,'Cleaned Customer Dim'!$A$2:$J$501,10,FALSE) -> Platinum | R21: =VLOOKUP(D21,'Cleaned Product Dim'!$A$2:$C$101,3,FALSE) -> Beauty | S21: =VLOOKUP(D21,'Cleaned Product Dim'!$A$2:$G$101,7,FALSE) -> 482.75 | T21: =VLOOKUP(D21,'Cleaned Product Dim'!$A$2:$H$101,8,FALSE) -> 444 | U21: =VLOOKUP(E21,'Cleaned Store Dim'!$A$2:$C$21,3,FALSE) -> East | V21: =VLOOKUP(E21,'Cleaned Store Dim'!$A$2:$E$21,5,FALSE) -> Flagship | W21: =VLOOKUP(E21,'Cleaned Store Dim'!$A$2:$F$21,6,FALSE) -> Johnsonville
A22: SALE20 | B22: 45784 | C22: CUST1144 | D22: PROD72 | E22: STORE17 | F22: 3 | G22: 986.04 | H22: 0.27 | I22: COD | J22: 2159.4276 | K22: =IF(F22="",J22/(G22*(1-H22)),F22) -> 3 | L22: =IF(G22="",J22/(K22*(1-H22)),G22) -> 986.04 | M22: =IF(H22="",1-(J22/(K22*L22)),H22) -> 0.27 | N22: =IF(J22="",F22*G22*(1-H22),J22) -> 2159.4276 | O22: =VLOOKUP(C22,'Cleaned Customer Dim'!$A$2:$D$501,4,FALSE) -> 62 | P22: =VLOOKUP(C22,'Cleaned Customer Dim'!$A$2:$E$501,5,FALSE) -> Female | Q22: =VLOOKUP(C22,'Cleaned Customer Dim'!$A$2:$J$501,10,FALSE) -> Bronze | R22: =VLOOKUP(D22,'Cleaned Product Dim'!$A$2:$C$101,3,FALSE) -> Sports | S22: =VLOOKUP(D22,'Cleaned Product Dim'!$A$2:$G$101,7,FALSE) -> 477.61 | T22: =VLOOKUP(D22,'Cleaned Product Dim'!$A$2:$H$101,8,FALSE) -> 300 | U22: =VLOOKUP(E22,'Cleaned Store Dim'!$A$2:$C$21,3,FALSE) -> North | V22: =VLOOKUP(E22,'Cleaned Store Dim'!$A$2:$E$21,5,FALSE) -> Flagship | W22: =VLOOKUP(E22,'Cleaned Store Dim'!$A$2:$F$21,6,FALSE) -> Benson | AI22: Sum of New Quantity | AJ22: Column Labels
A23: SALE21 | B23: 45388 | C23: CUST1396 | D23: PROD43 | E23: STORE18 | F23: 1 | G23: 589.56 | H23: 0.22 | I23: Credit Card | J23: 459.8568 | K23: =IF(F23="",J23/(G23*(1-H23)),F23) -> 1 | L23: =IF(G23="",J23/(K23*(1-H23)),G23) -> 589.56 | M23: =IF(H23="",1-(J23/(K23*L23)),H23) -> 0.22 | N23: =IF(J23="",F23*G23*(1-H23),J23) -> 459.8568 | O23: =VLOOKUP(C23,'Cleaned Customer Dim'!$A$2:$D$501,4,FALSE) -> 25 | P23: =VLOOKUP(C23,'Cleaned Customer Dim'!$A$2:$E$501,5,FALSE) -> Female | Q23: =VLOOKUP(C23,'Cleaned Customer Dim'!$A$2:$J$501,10,FALSE) -> Silver | R23: =VLOOKUP(D23,'Cleaned Product Dim'!$A$2:$C$101,3,FALSE) -> Electronics | S23: =VLOOKUP(D23,'Cleaned Product Dim'!$A$2:$G$101,7,FALSE) -> 253.33 | T23: =VLOOKUP(D23,'Cleaned Product Dim'!$A$2:$H$101,8,FALSE) -> 266 | U23: =VLOOKUP(E23,'Cleaned Store Dim'!$A$2:$C$21,3,FALSE) -> East | V23: =VLOOKUP(E23,'Cleaned Store Dim'!$A$2:$E$21,5,FALSE) -> Flagship | W23: =VLOOKUP(E23,'Cleaned Store Dim'!$A$2:$F$21,6,FALSE) -> East Stevechester | AI23: Row Labels | AJ23: Female | AK23: Male | AL23: Grand Total
A24: SALE22 | B24: 45630 | C24: CUST1476 | D24: PROD69 | E24: STORE10 | F24: 3 | G24: 979.42 | H24: 0.03 | I24: PayPal | J24: 2850.1122 | K24: =IF(F24="",J24/(G24*(1-H24)),F24) -> 3 | L24: =IF(G24="",J24/(K24*(1-H24)),G24) -> 979.42 | M24: =IF(H24="",1-(J24/(K24*L24)),H24) -> 0.03 | N24: =IF(J24="",F24*G24*(1-H24),J24) -> 2850.1122 | O24: =VLOOKUP(C24,'Cleaned Customer Dim'!$A$2:$D$501,4,FALSE) -> 33 | P24: =VLOOKUP(C24,'Cleaned Customer Dim'!$A$2:$E$501,5,FALSE) -> Female | Q24: =VLOOKUP(C24,'Cleaned Customer Dim'!$A$2:$J$501,10,FALSE) -> Gold | R24: =VLOOKUP(D24,'Cleaned Product Dim'!$A$2:$C$101,3,FALSE) -> Clothing | S24: =VLOOKUP(D24,'Cleaned Product Dim'!$A$2:$G$101,7,FALSE) -> 218.22 | T24: =VLOOKUP(D24,'Cleaned Product Dim'!$A$2:$H$101,8,FALSE) -> 224 | U24: =VLOOKUP(E24,'Cleaned Store Dim'!$A$2:$C$21,3,FALSE) -> East | V24: =VLOOKUP(E24,'Cleaned Store Dim'!$A$2:$E$21,5,FALSE) -> Online | W24: =VLOOKUP(E24,'Cleaned Store Dim'!$A$2:$F$21,6,FALSE) -> David | AI24: Beauty | AJ24: 11 | AK24: 5 | AL24: 16
A25: SALE23 | B25: 45466 | C25: CUST1368 | D25: PROD12 | E25: STORE8 | F25: 1 | G25: 719.28 | H25: 0.08 | I25: Credit Card | J25: 661.7376 | K25: =IF(F25="",J25/(G25*(1-H25)),F25) -> 1 | L25: =IF(G25="",J25/(K25*(1-H25)),G25) -> 719.28 | M25: =IF(H25="",1-(J25/(K25*L25)),H25) -> 0.08 | N25: =IF(J25="",F25*G25*(1-H25),J25) -> 661.7376 | O25: =VLOOKUP(C25,'Cleaned Customer Dim'!$A$2:$D$501,4,FALSE) -> 34 | P25: =VLOOKUP(C25,'Cleaned Customer Dim'!$A$2:$E$501,5,FALSE) -> Female | Q25: =VLOOKUP(C25,'Cleaned Customer Dim'!$A$2:$J$501,10,FALSE) -> Platinum | R25: =VLOOKUP(D25,'Cleaned Product Dim'!$A$2:$C$101,3,FALSE) -> Beauty | S25: =VLOOKUP(D25,'Cleaned Product Dim'!$A$2:$G$101,7,FALSE) -> 115.82 | T25: =VLOOKUP(D25,'Cleaned Product Dim'!$A$2:$H$101,8,FALSE) -> 460 | U25: =VLOOKUP(E25,'Cleaned Store Dim'!$A$2:$C$21,3,FALSE) -> West | V25: =VLOOKUP(E25,'Cleaned Store Dim'!$A$2:$E$21,5,FALSE) -> Online | W25: =VLOOKUP(E25,'Cleaned Store Dim'!$A$2:$F$21,6,FALSE) -> Thompson | AI25: Clothing | AJ25: 10 | AK25: 6 | AL25: 16
A26: SALE24 | B26: 45878 | C26: CUST1186 | D26: PROD67 | E26: STORE6 | F26: 3 | G26: 77.6 | H26: 0.07 | I26: Credit Card | J26: 216.504 | K26: =IF(F26="",J26/(G26*(1-H26)),F26) -> 3 | L26: =IF(G26="",J26/(K26*(1-H26)),G26) -> 77.6 | M26: =IF(H26="",1-(J26/(K26*L26)),H26) -> 0.07 | N26: =IF(J26="",F26*G26*(1-H26),J26) -> 216.504 | O26: =VLOOKUP(C26,'Cleaned Customer Dim'!$A$2:$D$501,4,FALSE) -> 53 | P26: =VLOOKUP(C26,'Cleaned Customer Dim'!$A$2:$E$501,5,FALSE) -> Male | Q26: =VLOOKUP(C26,'Cleaned Customer Dim'!$A$2:$J$501,10,FALSE) -> Silver | R26: =VLOOKUP(D26,'Cleaned Product Dim'!$A$2:$C$101,3,FALSE) -> Electronics | S26: =VLOOKUP(D26,'Cleaned Product Dim'!$A$2:$G$101,7,FALSE) -> 349.17 | T26: =VLOOKUP(D26,'Cleaned Product Dim'!$A$2:$H$101,8,FALSE) -> 476 | U26: =VLOOKUP(E26,'Cleaned Store Dim'!$A$2:$C$21,3,FALSE) -> East | V26: =VLOOKUP(E26,'Cleaned Store Dim'!$A$2:$E$21,5,FALSE) -> Online | W26: =VLOOKUP(E26,'Cleaned Store Dim'!$A$2:$F$21,6,FALSE) -> Joseph | AI26: Electronics | AJ26: 18 | AK26: 13 | AL26: 31
A27: SALE25 | B27: 45552 | C27: CUST1381 | D27: PROD5 | E27: STORE3 | F27: 4 | G27: 852.71 | H27: 0.14 | I27: PayPal | J27: 2933.3224 | K27: =IF(F27="",J27/(G27*(1-H27)),F27) -> 4 | L27: =IF(G27="",J27/(K27*(1-H27)),G27) -> 852.71 | M27: =IF(H27="",1-(J27/(K27*L27)),H27) -> 0.14 | N27: =IF(J27="",F27*G27*(1-H27),J27) -> 2933.3224 | O27: =VLOOKUP(C27,'Cleaned Customer Dim'!$A$2:$D$501,4,FALSE) -> 50 | P27: =VLOOKUP(C27,'Cleaned Customer Dim'!$A$2:$E$501,5,FALSE) -> Male | Q27: =VLOOKUP(C27,'Cleaned Customer Dim'!$A$2:$J$501,10,FALSE) -> Silver | R27: =VLOOKUP(D27,'Cleaned Product Dim'!$A$2:$C$101,3,FALSE) -> Clothing | S27: =VLOOKUP(D27,'Cleaned Product Dim'!$A$2:$G$101,7,FALSE) -> 261 | T27: =VLOOKUP(D27,'Cleaned Product Dim'!$A$2:$H$101,8,FALSE) -> 59 | U27: =VLOOKUP(E27,'Cleaned Store Dim'!$A$2:$C$21,3,FALSE) -> North | V27: =VLOOKUP(E27,'Cleaned Store Dim'!$A$2:$E$21,5,FALSE) -> Outlet | W27: =VLOOKUP(E27,'Cleaned Store Dim'!$A$2:$F$21,6,FALSE) -> Goldberg | AI27: Home | AJ27: 14 | AK27: 10 | AL27: 24
A28: SALE26 | B28: 45352 | C28: CUST1213 | D28: PROD98 | E28: STORE8 | F28: 4 | G28: 156.16 | I28: Credit Card | J28: 599.6544 | K28: =IF(F28="",J28/(G28*(1-H28)),F28) -> 4 | L28: =IF(G28="",J28/(K28*(1-H28)),G28) -> 156.16 | M28: =IF(H28="",1-(J28/(K28*L28)),H28) -> 0.04 | N28: =IF(J28="",F28*G28*(1-H28),J28) -> 599.6544 | O28: =VLOOKUP(C28,'Cleaned Customer Dim'!$A$2:$D$501,4,FALSE) -> 42 | P28: =VLOOKUP(C28,'Cleaned Customer Dim'!$A$2:$E$501,5,FALSE) -> Female | Q28: =VLOOKUP(C28,'Cleaned Customer Dim'!$A$2:$J$501,10,FALSE) -> Platinum | R28: =VLOOKUP(D28,'Cleaned Product Dim'!$A$2:$C$101,3,FALSE) -> Electronics | S28: =VLOOKUP(D28,'Cleaned Product Dim'!$A$2:$G$101,7,FALSE) -> 431.67 | T28: =VLOOKUP(D28,'Cleaned Product Dim'!$A$2:$H$101,8,FALSE) -> 73 | U28: =VLOOKUP(E28,'Cleaned Store Dim'!$A$2:$C$21,3,FALSE) -> West | V28: =VLOOKUP(E28,'Cleaned Store Dim'!$A$2:$E$21,5,FALSE) -> Online | W28: =VLOOKUP(E28,'Cleaned Store Dim'!$A$2:$F$21,6,FALSE) -> Thompson | AI28: Sports | AJ28: 11 | AK28: 7 | AL28: 18
A29: SALE27 | B29: 45710 | C29: CUST1200 | D29: PROD77 | E29: STORE8 | F29: 3 | G29: 815.49 | H29: 0.17 | I29: Credit Card | J29: 2030.5701 | K29: =IF(F29="",J29/(G29*(1-H29)),F29) -> 3 | L29: =IF(G29="",J29/(K29*(1-H29)),G29) -> 815.49 | M29: =IF(H29="",1-(J29/(K29*L29)),H29) -> 0.17 | N29: =IF(J29="",F29*G29*(1-H29),J29) -> 2030.5701 | O29: =VLOOKUP(C29,'Cleaned Customer Dim'!$A$2:$D$501,4,FALSE) -> 30 | P29: =VLOOKUP(C29,'Cleaned Customer Dim'!$A$2:$E$501,5,FALSE) -> Male | Q29: =VLOOKUP(C29,'Cleaned Customer Dim'!$A$2:$J$501,10,FALSE) -> Platinum | R29: =VLOOKUP(D29,'Cleaned Product Dim'!$A$2:$C$101,3,FALSE) -> Electronics | S29: =VLOOKUP(D29,'Cleaned Product Dim'!$A$2:$G$101,7,FALSE) -> 480.9 | T29: =VLOOKUP(D29,'Cleaned Product Dim'!$A$2:$H$101,8,FALSE) -> 104 | U29: =VLOOKUP(E29,'Cleaned Store Dim'!$A$2:$C$21,3,FALSE) -> West | V29: =VLOOKUP(E29,'Cleaned Store Dim'!$A$2:$E$21,5,FALSE) -> Online | W29: =VLOOKUP(E29,'Cleaned Store Dim'!$A$2:$F$21,6,FALSE) -> Thompson | AI29: Grand Total | AJ29: 64 | AK29: 41 | AL29: 105
A30: SALE28 | B30: 45923 | C30: CUST1148 | D30: PROD13 | E30: STORE2 | F30: 2 | G30: 74.21 | H30: 0.11 | I30: PayPal | J30: 132.0938 | K30: =IF(F30="",J30/(G30*(1-H30)),F30) -> 2 | L30: =IF(G30="",J30/(K30*(1-H30)),G30) -> 74.21 | M30: =IF(H30="",1-(J30/(K30*L30)),H30) -> 0.11 | N30: =IF(J30="",F30*G30*(1-H30),J30) -> 132.0938 | O30: =VLOOKUP(C30,'Cleaned Customer Dim'!$A$2:$D$501,4,FALSE) -> 42 | P30: =VLOOKUP(C30,'Cleaned Customer Dim'!$A$2:$E$501,5,FALSE) -> Female | Q30: =VLOOKUP(C30,'Cleaned Customer Dim'!$A$2:$J$501,10,FALSE) -> Bronze | R30: =VLOOKUP(D30,'Cleaned Product Dim'!$A$2:$C$101,3,FALSE) -> Electronics | S30: =VLOOKUP(D30,'Cleaned Product Dim'!$A$2:$G$101,7,FALSE) -> 242.23 | T30: =VLOOKUP(D30,'Cleaned Product Dim'!$A$2:$H$101,8,FALSE) -> 453 | U30: =VLOOKUP(E30,'Cleaned Store Dim'!$A$2:$C$21,3,FALSE) -> South | V30: =VLOOKUP(E30,'Cleaned Store Dim'!$A$2:$E$21,5,FALSE) -> Outlet | W30: =VLOOKUP(E30,'Cleaned Store Dim'!$A$2:$F$21,6,FALSE) -> North Nancy
A31: SALE29 | B31: 45597 | C31: CUST1348 | D31: PROD99 | E31: STORE3 | G31: 451.67 | H31: 0.15 | I31: Credit Card | J31: 1535.678 | K31: =IF(F31="",J31/(G31*(1-H31)),F31) -> 4 | L31: =IF(G31="",J31/(K31*(1-H31)),G31) -> 451.67 | M31: =IF(H31="",1-(J31/(K31*L31)),H31) -> 0.15 | N31: =IF(J31="",F31*G31*(1-H31),J31) -> 1535.678 | O31: =VLOOKUP(C31,'Cleaned Customer Dim'!$A$2:$D$501,4,FALSE) -> 55 | P31: =VLOOKUP(C31,'Cleaned Customer Dim'!$A$2:$E$501,5,FALSE) -> Male | Q31: =VLOOKUP(C31,'Cleaned Customer Dim'!$A$2:$J$501,10,FALSE) -> Silver | R31: =VLOOKUP(D31,'Cleaned Product Dim'!$A$2:$C$101,3,FALSE) -> Home | S31: =VLOOKUP(D31,'Cleaned Product Dim'!$A$2:$G$101,7,FALSE) -> 201.41 | T31: =VLOOKUP(D31,'Cleaned Product Dim'!$A$2:$H$101,8,FALSE) -> 146 | U31: =VLOOKUP(E31,'Cleaned Store Dim'!$A$2:$C$21,3,FALSE) -> North | V31: =VLOOKUP(E31,'Cleaned Store Dim'!$A$2:$E$21,5,FALSE) -> Outlet | W31: =VLOOKUP(E31,'Cleaned Store Dim'!$A$2:$F$21,6,FALSE) -> Goldberg
A32: SALE30 | B32: 45217 | C32: CUST1028 | D32: PROD5 | E32: STORE19 | F32: 1 | G32: 429.38 | H32: 0.13 | I32: PayPal | J32: 373.5606 | K32: =IF(F32="",J32/(G32*(1-H32)),F32) -> 1 | L32: =IF(G32="",J32/(K32*(1-H32)),G32) -> 429.38 | M32: =IF(H32="",1-(J32/(K32*L32)),H32) -> 0.13 | N32: =IF(J32="",F32*G32*(1-H32),J32) -> 373.5606 | O32: =VLOOKUP(C32,'Cleaned Customer Dim'!$A$2:$D$501,4,FALSE) -> 27 | P32: =VLOOKUP(C32,'Cleaned Customer Dim'!$A$2:$E$501,5,FALSE) -> Female | Q32: =VLOOKUP(C32,'Cleaned Customer Dim'!$A$2:$J$501,10,FALSE) -> Platinum | R32: =VLOOKUP(D32,'Cleaned Product Dim'!$A$2:$C$101,3,FALSE) -> Clothing | S32: =VLOOKUP(D32,'Cleaned Product Dim'!$A$2:$G$101,7,FALSE) -> 261 | T32: =VLOOKUP(D32,'Cleaned Product Dim'!$A$2:$H$101,8,FALSE) -> 59 | U32: =VLOOKUP(E32,'Cleaned Store Dim'!$A$2:$C$21,3,FALSE) -> East | V32: =VLOOKUP(E32,'Cleaned Store Dim'!$A$2:$E$21,5,FALSE) -> Online | W32: =VLOOKUP(E32,'Cleaned Store Dim'!$A$2:$F$21,6,FALSE) -> Vasquez
A33: SALE31 | B33: 45593 | C33: CUST1412 | D33: PROD53 | E33: STORE12 | F33: 2 | G33: 148.96 | H33: 0.03 | I33: COD | J33: 288.9824 | K33: =IF(F33="",J33/(G33*(1-H33)),F33) -> 2 | L33: =IF(G33="",J33/(K33*(1-H33)),G33) -> 148.96 | M33: =IF(H33="",1-(J33/(K33*L33)),H33) -> 0.03 | N33: =IF(J33="",F33*G33*(1-H33),J33) -> 288.9824 | O33: =VLOOKUP(C33,'Cleaned Customer Dim'!$A$2:$D$501,4,FALSE) -> 23 | P33: =VLOOKUP(C33,'Cleaned Customer Dim'!$A$2:$E$501,5,FALSE) -> Female | Q33: =VLOOKUP(C33,'Cleaned Customer Dim'!$A$2:$J$501,10,FALSE) -> Gold | R33: =VLOOKUP(D33,'Cleaned Product Dim'!$A$2:$C$101,3,FALSE) -> Clothing | S33: =VLOOKUP(D33,'Cleaned Product Dim'!$A$2:$G$101,7,FALSE) -> 386.56 | T33: =VLOOKUP(D33,'Cleaned Product Dim'!$A$2:$H$101,8,FALSE) -> 125 | U33: =VLOOKUP(E33,'Cleaned Store Dim'!$A$2:$C$21,3,FALSE) -> North | V33: =VLOOKUP(E33,'Cleaned Store Dim'!$A$2:$E$21,5,FALSE) -> Online | W33: =VLOOKUP(E33,'Cleaned Store Dim'!$A$2:$F$21,6,FALSE) -> Sabrina
A34: SALE32 | B34: 45302 | C34: CUST1398 | D34: PROD75 | E34: STORE8 | F34: 4 | G34: 313.83 | H34: 0.08 | I34: Credit Card | J34: 1154.8944 | K34: =IF(F34="",J34/(G34*(1-H34)),F34) -> 4 | L34: =IF(G34="",J34/(K34*(1-H34)),G34) -> 313.83 | M34: =IF(H34="",1-(J34/(K34*L34)),H34) -> 0.08 | N34: =IF(J34="",F34*G34*(1-H34),J34) -> 1154.8944 | O34: =VLOOKUP(C34,'Cleaned Customer Dim'!$A$2:$D$501,4,FALSE) -> 54 | P34: =VLOOKUP(C34,'Cleaned Customer Dim'!$A$2:$E$501,5,FALSE) -> Male | Q34: =VLOOKUP(C34,'Cleaned Customer Dim'!$A$2:$J$501,10,FALSE) -> Bronze | R34: =VLOOKUP(D34,'Cleaned Product Dim'!$A$2:$C$101,3,FALSE) -> Clothing | S34: =VLOOKUP(D34,'Cleaned Product Dim'!$A$2:$G$101,7,FALSE) -> 158.14 | T34: =VLOOKUP(D34,'Cleaned Product Dim'!$A$2:$H$101,8,FALSE) -> 82 | U34: =VLOOKUP(E34,'Cleaned Store Dim'!$A$2:$C$21,3,FALSE) -> West | V34: =VLOOKUP(E34,'Cleaned Store Dim'!$A$2:$E$21,5,FALSE) -> Online | W34: =VLOOKUP(E34,'Cleaned Store Dim'!$A$2:$F$21,6,FALSE) -> Thompson
A35: SALE33 | B35: 45620 | C35: CUST1453 | D35: PROD12 | E35: STORE6 | F35: 2 | G35: 717.31 | H35: 0.15 | I35: Credit Card | J35: 1219.427 | K35: =IF(F35="",J35/(G35*(1-H35)),F35) -> 2 | L35: =IF(G35="",J35/(K35*(1-H35)),G35) -> 717.31 | M35: =IF(H35="",1-(J35/(K35*L35)),H35) -> 0.15 | N35: =IF(J35="",F35*G35*(1-H35),J35) -> 1219.427 | O35: =VLOOKUP(C35,'Cleaned Customer Dim'!$A$2:$D$501,4,FALSE) -> 62 | P35: =VLOOKUP(C35,'Cleaned Customer Dim'!$A$2:$E$501,5,FALSE) -> Female | Q35: =VLOOKUP(C35,'Cleaned Customer Dim'!$A$2:$J$501,10,FALSE) -> Platinum | R35: =VLOOKUP(D35,'Cleaned Product Dim'!$A$2:$C$101,3,FALSE) -> Beauty | S35: =VLOOKUP(D35,'Cleaned Product Dim'!$A$2:$G$101,7,FALSE) -> 115.82 | T35: =VLOOKUP(D35,'Cleaned Product Dim'!$A$2:$H$101,8,FALSE) -> 460 | U35: =VLOOKUP(E35,'Cleaned Store Dim'!$A$2:$C$21,3,FALSE) -> East | V35: =VLOOKUP(E35,'Cleaned Store Dim'!$A$2:$E$21,5,FALSE) -> Online | W35: =VLOOKUP(E35,'Cleaned Store Dim'!$A$2:$F$21,6,FALSE) -> Joseph
A36: SALE34 | B36: 45215 | C36: CUST1344 | D36: PROD79 | E36: STORE1 | G36: 873.22 | H36: 0.18 | I36: Credit Card | J36: 2148.1212 | K36: =IF(F36="",J36/(G36*(1-H36)),F36) -> 3 | L36: =IF(G36="",J36/(K36*(1-H36)),G36) -> 873.22 | M36: =IF(H36="",1-(J36/(K36*L36)),H36) -> 0.18 | N36: =IF(J36="",F36*G36*(1-H36),J36) -> 2148.1212 | O36: =VLOOKUP(C36,'Cleaned Customer Dim'!$A$2:$D$501,4,FALSE) -> 39 | P36: =VLOOKUP(C36,'Cleaned Customer Dim'!$A$2:$E$501,5,FALSE) -> Male | Q36: =VLOOKUP(C36,'Cleaned Customer Dim'!$A$2:$J$501,10,FALSE) -> Gold | R36: =VLOOKUP(D36,'Cleaned Product Dim'!$A$2:$C$101,3,FALSE) -> Home | S36: =VLOOKUP(D36,'Cleaned Product Dim'!$A$2:$G$101,7,FALSE) -> 228.53 | T36: =VLOOKUP(D36,'Cleaned Product Dim'!$A$2:$H$101,8,FALSE) -> 469 | U36: =VLOOKUP(E36,'Cleaned Store Dim'!$A$2:$C$21,3,FALSE) -> North | V36: =VLOOKUP(E36,'Cleaned Store Dim'!$A$2:$E$21,5,FALSE) -> Flagship | W36: =VLOOKUP(E36,'Cleaned Store Dim'!$A$2:$F$21,6,FALSE) -> Daniel
A37: SALE35 | B37: 45908 | C37: CUST1218 | D37: PROD16 | E37: STORE3 | F37: 4 | G37: 109.36 | H37: 0.19 | I37: COD | J37: 354.3264 | K37: =IF(F37="",J37/(G37*(1-H37)),F37) -> 4 | L37: =IF(G37="",J37/(K37*(1-H37)),G37) -> 109.36 | M37: =IF(H37="",1-(J37/(K37*L37)),H37) -> 0.19 | N37: =IF(J37="",F37*G37*(1-H37),J37) -> 354.3264 | O37: =VLOOKUP(C37,'Cleaned Customer Dim'!$A$2:$D$501,4,FALSE) -> 46 | P37: =VLOOKUP(C37,'Cleaned Customer Dim'!$A$2:$E$501,5,FALSE) -> Male | Q37: =VLOOKUP(C37,'Cleaned Customer Dim'!$A$2:$J$501,10,FALSE) -> Platinum | R37: =VLOOKUP(D37,'Cleaned Product Dim'!$A$2:$C$101,3,FALSE) -> Beauty | S37: =VLOOKUP(D37,'Cleaned Product Dim'!$A$2:$G$101,7,FALSE) -> 337.42 | T37: =VLOOKUP(D37,'Cleaned Product Dim'!$A$2:$H$101,8,FALSE) -> 256 | U37: =VLOOKUP(E37,'Cleaned Store Dim'!$A$2:$C$21,3,FALSE) -> North | V37: =VLOOKUP(E37,'Cleaned Store Dim'!$A$2:$E$21,5,FALSE) -> Outlet | W37: =VLOOKUP(E37,'Cleaned Store Dim'!$A$2:$F$21,6,FALSE) -> Goldberg
A38: SALE36 | B38: 45547 | C38: CUST1086 | D38: PROD5 | E38: STORE7 | F38: 3 | G38: 559.52 | H38: 0.16 | I38: PayPal | J38: 1409.9904 | K38: =IF(F38="",J38/(G38*(1-H38)),F38) -> 3 | L38: =IF(G38="",J38/(K38*(1-H38)),G38) -> 559.52 | M38: =IF(H38="",1-(J38/(K38*L38)),H38) -> 0.16 | N38: =IF(J38="",F38*G38*(1-H38),J38) -> 1409.9904 | O38: =VLOOKUP(C38,'Cleaned Customer Dim'!$A$2:$D$501,4,FALSE) -> 19 | P38: =VLOOKUP(C38,'Cleaned Customer Dim'!$A$2:$E$501,5,FALSE) -> Female | Q38: =VLOOKUP(C38,'Cleaned Customer Dim'!$A$2:$J$501,10,FALSE) -> Gold | R38: =VLOOKUP(D38,'Cleaned Product Dim'!$A$2:$C$101,3,FALSE) -> Clothing | S38: =VLOOKUP(D38,'Cleaned Product Dim'!$A$2:$G$101,7,FALSE) -> 261 | T38: =VLOOKUP(D38,'Cleaned Product Dim'!$A$2:$H$101,8,FALSE) -> 59 | U38: =VLOOKUP(E38,'Cleaned Store Dim'!$A$2:$C$21,3,FALSE) -> South | V38: =VLOOKUP(E38,'Cleaned Store Dim'!$A$2:$E$21,5,FALSE) -> Online | W38: =VLOOKUP(E38,'Cleaned Store Dim'!$A$2:$F$21,6,FALSE) -> Williamsport
A39: SALE37 | B39: 45475 | C39: CUST1492 | D39: PROD10 | E39: STORE17 | F39: 3 | G39: 121.76 | H39: 0.27 | I39: PayPal | J39: 266.6544 | K39: =IF(F39="",J39/(G39*(1-H39)),F39) -> 3 | L39: =IF(G39="",J39/(K39*(1-H39)),G39) -> 121.76 | M39: =IF(H39="",1-(J39/(K39*L39)),H39) -> 0.27 | N39: =IF(J39="",F39*G39*(1-H39),J39) -> 266.6544 | O39: =VLOOKUP(C39,'Cleaned Customer Dim'!$A$2:$D$501,4,FALSE) -> 59 | P39: =VLOOKUP(C39,'Cleaned Customer Dim'!$A$2:$E$501,5,FALSE) -> Female | Q39: =VLOOKUP(C39,'Cleaned Customer Dim'!$A$2:$J$501,10,FALSE) -> Platinum | R39: =VLOOKUP(D39,'Cleaned Product Dim'!$A$2:$C$101,3,FALSE) -> Home | S39: =VLOOKUP(D39,'Cleaned Product Dim'!$A$2:$G$101,7,FALSE) -> 298.86 | T39: =VLOOKUP(D39,'Cleaned Product Dim'!$A$2:$H$101,8,FALSE) -> 308 | U39: =VLOOKUP(E39,'Cleaned Store Dim'!$A$2:$C$21,3,FALSE) -> North | V39: =VLOOKUP(E39,'Cleaned Store Dim'!$A$2:$E$21,5,FALSE) -> Flagship | W39: =VLOOKUP(E39,'Cleaned Store Dim'!$A$2:$F$21,6,FALSE) -> Benson
A40: SALE38 | B40: 45378 | C40: CUST1189 | D40: PROD33 | E40: STORE13 | F40: 4 | G40: 735.32 | H40: 0.06 | I40: COD | J40: 2764.8032 | K40: =IF(F40="",J40/(G40*(1-H40)),F40) -> 4 | L40: =IF(G40="",J40/(K40*(1-H40)),G40) -> 735.32 | M40: =IF(H40="",1-(J40/(K40*L40)),H40) -> 0.06 | N40: =IF(J40="",F40*G40*(1-H40),J40) -> 2764.8032 | O40: =VLOOKUP(C40,'Cleaned Customer Dim'!$A$2:$D$501,4,FALSE) -> 29 | P40: =VLOOKUP(C40,'Cleaned Customer Dim'!$A$2:$E$501,5,FALSE) -> Male | Q40: =VLOOKUP(C40,'Cleaned Customer Dim'!$A$2:$J$501,10,FALSE) -> Gold | R40: =VLOOKUP(D40,'Cleaned Product Dim'!$A$2:$C$101,3,FALSE) -> Home | S40: =VLOOKUP(D40,'Cleaned Product Dim'!$A$2:$G$101,7,FALSE) -> 179.77 | T40: =VLOOKUP(D40,'Cleaned Product Dim'!$A$2:$H$101,8,FALSE) -> 305 | U40: =VLOOKUP(E40,'Cleaned Store Dim'!$A$2:$C$21,3,FALSE) -> East | V40: =VLOOKUP(E40,'Cleaned Store Dim'!$A$2:$E$21,5,FALSE) -> Flagship | W40: =VLOOKUP(E40,'Cleaned Store Dim'!$A$2:$F$21,6,FALSE) -> Johnsonville
A41: SALE39 | B41: 45028 | C41: CUST1431 | D41: PROD94 | E41: STORE3 | F41: 2 | G41: 600.73 | H41: 0.08 | I41: Credit Card | J41: 1105.3432 | K41: =IF(F41="",J41/(G41*(1-H41)),F41) -> 2 | L41: =IF(G41="",J41/(K41*(1-H41)),G41) -> 600.73 | M41: =IF(H41="",1-(J41/(K41*L41)),H41) -> 0.08 | N41: =IF(J41="",F41*G41*(1-H41),J41) -> 1105.3432 | O41: =VLOOKUP(C41,'Cleaned Customer Dim'!$A$2:$D$501,4,FALSE) -> 27 | P41: =VLOOKUP(C41,'Cleaned Customer Dim'!$A$2:$E$501,5,FALSE) -> Male | Q41: =VLOOKUP(C41,'Cleaned Customer Dim'!$A$2:$J$501,10,FALSE) -> Platinum | R41: =VLOOKUP(D41,'Cleaned Product Dim'!$A$2:$C$101,3,FALSE) -> Beauty | S41: =VLOOKUP(D41,'Cleaned Product Dim'!$A$2:$G$101,7,FALSE) -> 358.47 | T41: =VLOOKUP(D41,'Cleaned Product Dim'!$A$2:$H$101,8,FALSE) -> 213 | U41: =VLOOKUP(E41,'Cleaned Store Dim'!$A$2:$C$21,3,FALSE) -> North | V41: =VLOOKUP(E41,'Cleaned Store Dim'!$A$2:$E$21,5,FALSE) -> Outlet | W41: =VLOOKUP(E41,'Cleaned Store Dim'!$A$2:$F$21,6,FALSE) -> Goldberg
A42: SALE40 | B42: 45486 | C42: CUST1072 | D42: PROD26 | E42: STORE19 | F42: 2 | G42: 873.86 | H42: 0.07 | I42: COD | J42: 1625.3796 | K42: =IF(F42="",J42/(G42*(1-H42)),F42) -> 2 | L42: =IF(G42="",J42/(K42*(1-H42)),G42) -> 873.86 | M42: =IF(H42="",1-(J42/(K42*L42)),H42) -> 0.07 | N42: =IF(J42="",F42*G42*(1-H42),J42) -> 1625.3796 | O42: =VLOOKUP(C42,'Cleaned Customer Dim'!$A$2:$D$501,4,FALSE) -> 39 | P42: =VLOOKUP(C42,'Cleaned Customer Dim'!$A$2:$E$501,5,FALSE) -> Female | Q42: =VLOOKUP(C42,'Cleaned Customer Dim'!$A$2:$J$501,10,FALSE) -> Gold | R42: =VLOOKUP(D42,'Cleaned Product Dim'!$A$2:$C$101,3,FALSE) -> Electronics | S42: =VLOOKUP(D42,'Cleaned Product Dim'!$A$2:$G$101,7,FALSE) -> 322.41 | T42: =VLOOKUP(D42,'Cleaned Product Dim'!$A$2:$H$101,8,FALSE) -> 213 | U42: =VLOOKUP(E42,'Cleaned Store Dim'!$A$2:$C$21,3,FALSE) -> East | V42: =VLOOKUP(E42,'Cleaned Store Dim'!$A$2:$E$21,5,FALSE) -> Online | W42: =VLOOKUP(E42,'Cleaned Store Dim'!$A$2:$F$21,6,FALSE) -> Vasquez
A43: SALE41 | B43: 45241 | C43: CUST1302 | D43: PROD23 | E43: STORE8 | F43: 3 | G43: 342.47 | H43: 0.08 | I43: PayPal | J43: 945.2172 | K43: =IF(F43="",J43/(G43*(1-H43)),F43) -> 3 | L43: =IF(G43="",J43/(K43*(1-H43)),G43) -> 342.47 | M43: =IF(H43="",1-(J43/(K43*L43)),H43) -> 0.08 | N43: =IF(J43="",F43*G43*(1-H43),J43) -> 945.2172 | O43: =VLOOKUP(C43,'Cleaned Customer Dim'!$A$2:$D$501,4,FALSE) -> 36 | P43: =VLOOKUP(C43,'Cleaned Customer Dim'!$A$2:$E$501,5,FALSE) -> Male | Q43: =VLOOKUP(C43,'Cleaned Customer Dim'!$A$2:$J$501,10,FALSE) -> Gold | R43: =VLOOKUP(D43,'Cleaned Product Dim'!$A$2:$C$101,3,FALSE) -> Clothing | S43: =VLOOKUP(D43,'Cleaned Product Dim'!$A$2:$G$101,7,FALSE) -> 265.73267 | T43: =VLOOKUP(D43,'Cleaned Product Dim'!$A$2:$H$101,8,FALSE) -> 360 | U43: =VLOOKUP(E43,'Cleaned Store Dim'!$A$2:$C$21,3,FALSE) -> West | V43: =VLOOKUP(E43,'Cleaned Store Dim'!$A$2:$E$21,5,FALSE) -> Online | W43: =VLOOKUP(E43,'Cleaned Store Dim'!$A$2:$F$21,6,FALSE) -> Thompson
A44: SALE42 | B44: 45649 | C44: CUST1335 | D44: PROD29 | E44: STORE9 | F44: 2 | G44: 915.15 | H44: 0.16 | I44: PayPal | J44: 1537.452 | K44: =IF(F44="",J44/(G44*(1-H44)),F44) -> 2 | L44: =IF(G44="",J44/(K44*(1-H44)),G44) -> 915.15 | M44: =IF(H44="",1-(J44/(K44*L44)),H44) -> 0.16 | N44: =IF(J44="",F44*G44*(1-H44),J44) -> 1537.452 | O44: =VLOOKUP(C44,'Cleaned Customer Dim'!$A$2:$D$501,4,FALSE) -> 37 | P44: =VLOOKUP(C44,'Cleaned Customer Dim'!$A$2:$E$501,5,FALSE) -> Male | Q44: =VLOOKUP(C44,'Cleaned Customer Dim'!$A$2:$J$501,10,FALSE) -> Platinum | R44: =VLOOKUP(D44,'Cleaned Product Dim'!$A$2:$C$101,3,FALSE) -> Home | S44: =VLOOKUP(D44,'Cleaned Product Dim'!$A$2:$G$101,7,FALSE) -> 218.48 | T44: =VLOOKUP(D44,'Cleaned Product Dim'!$A$2:$H$101,8,FALSE) -> 276 | U44: =VLOOKUP(E44,'Cleaned Store Dim'!$A$2:$C$21,3,FALSE) -> South | V44: =VLOOKUP(E44,'Cleaned Store Dim'!$A$2:$E$21,5,FALSE) -> Flagship | W44: =VLOOKUP(E44,'Cleaned Store Dim'!$A$2:$F$21,6,FALSE) -> Johnstad
A45: SALE43 | B45: 45677 | C45: CUST1084 | D45: PROD33 | E45: STORE17 | G45: 863.11 | H45: 0.28 | I45: PayPal | J45: 1864.3176 | K45: =IF(F45="",J45/(G45*(1-H45)),F45) -> 3 | L45: =IF(G45="",J45/(K45*(1-H45)),G45) -> 863.11 | M45: =IF(H45="",1-(J45/(K45*L45)),H45) -> 0.28 | N45: =IF(J45="",F45*G45*(1-H45),J45) -> 1864.3176 | O45: =VLOOKUP(C45,'Cleaned Customer Dim'!$A$2:$D$501,4,FALSE) -> 26 | P45: =VLOOKUP(C45,'Cleaned Customer Dim'!$A$2:$E$501,5,FALSE) -> Female | Q45: =VLOOKUP(C45,'Cleaned Customer Dim'!$A$2:$J$501,10,FALSE) -> Platinum | R45: =VLOOKUP(D45,'Cleaned Product Dim'!$A$2:$C$101,3,FALSE) -> Home | S45: =VLOOKUP(D45,'Cleaned Product Dim'!$A$2:$G$101,7,FALSE) -> 179.77 | T45: =VLOOKUP(D45,'Cleaned Product Dim'!$A$2:$H$101,8,FALSE) -> 305 | U45: =VLOOKUP(E45,'Cleaned Store Dim'!$A$2:$C$21,3,FALSE) -> North | V45: =VLOOKUP(E45,'Cleaned Store Dim'!$A$2:$E$21,5,FALSE) -> Flagship | W45: =VLOOKUP(E45,'Cleaned Store Dim'!$A$2:$F$21,6,FALSE) -> Benson
A46: SALE44 | B46: 45360 | C46: CUST1203 | D46: PROD43 | E46: STORE12 | F46: 2 | G46: 209.32 | H46: 0.23 | I46: COD | J46: 322.3528 | K46: =IF(F46="",J46/(G46*(1-H46)),F46) -> 2 | L46: =IF(G46="",J46/(K46*(1-H46)),G46) -> 209.32 | M46: =IF(H46="",1-(J46/(K46*L46)),H46) -> 0.23 | N46: =IF(J46="",F46*G46*(1-H46),J46) -> 322.3528 | O46: =VLOOKUP(C46,'Cleaned Customer Dim'!$A$2:$D$501,4,FALSE) -> 47 | P46: =VLOOKUP(C46,'Cleaned Customer Dim'!$A$2:$E$501,5,FALSE) -> Male | Q46: =VLOOKUP(C46,'Cleaned Customer Dim'!$A$2:$J$501,10,FALSE) -> Platinum | R46: =VLOOKUP(D46,'Cleaned Product Dim'!$A$2:$C$101,3,FALSE) -> Electronics | S46: =VLOOKUP(D46,'Cleaned Product Dim'!$A$2:$G$101,7,FALSE) -> 253.33 | T46: =VLOOKUP(D46,'Cleaned Product Dim'!$A$2:$H$101,8,FALSE) -> 266 | U46: =VLOOKUP(E46,'Cleaned Store Dim'!$A$2:$C$21,3,FALSE) -> North | V46: =VLOOKUP(E46,'Cleaned Store Dim'!$A$2:$E$21,5,FALSE) -> Online | W46: =VLOOKUP(E46,'Cleaned Store Dim'!$A$2:$F$21,6,FALSE) -> Sabrina
A47: SALE45 | B47: 45576 | C47: CUST1470 | D47: PROD59 | E47: STORE8 | F47: 4 | G47: 288.6 | H47: 0.09 | I47: PayPal | J47: 1050.504 | K47: =IF(F47="",J47/(G47*(1-H47)),F47) -> 4 | L47: =IF(G47="",J47/(K47*(1-H47)),G47) -> 288.6 | M47: =IF(H47="",1-(J47/(K47*L47)),H47) -> 0.09 | N47: =IF(J47="",F47*G47*(1-H47),J47) -> 1050.504 | O47: =VLOOKUP(C47,'Cleaned Customer Dim'!$A$2:$D$501,4,FALSE) -> 21 | P47: =VLOOKUP(C47,'Cleaned Customer Dim'!$A$2:$E$501,5,FALSE) -> Female | Q47: =VLOOKUP(C47,'Cleaned Customer Dim'!$A$2:$J$501,10,FALSE) -> Gold | R47: =VLOOKUP(D47,'Cleaned Product Dim'!$A$2:$C$101,3,FALSE) -> Beauty | S47: =VLOOKUP(D47,'Cleaned Product Dim'!$A$2:$G$101,7,FALSE) -> 17.31 | T47: =VLOOKUP(D47,'Cleaned Product Dim'!$A$2:$H$101,8,FALSE) -> 399 | U47: =VLOOKUP(E47,'Cleaned Store Dim'!$A$2:$C$21,3,FALSE) -> West | V47: =VLOOKUP(E47,'Cleaned Store Dim'!$A$2:$E$21,5,FALSE) -> Online | W47: =VLOOKUP(E47,'Cleaned Store Dim'!$A$2:$F$21,6,FALSE) -> Thompson
A48: SALE46 | B48: 45422 | C48: CUST1070 | D48: PROD78 | E48: STORE16 | F48: 1 | G48: 418.69 | H48: 0.06 | I48: PayPal | J48: 393.5686 | K48: =IF(F48="",J48/(G48*(1-H48)),F48) -> 1 | L48: =IF(G48="",J48/(K48*(1-H48)),G48) -> 418.69 | M48: =IF(H48="",1-(J48/(K48*L48)),H48) -> 0.06 | N48: =IF(J48="",F48*G48*(1-H48),J48) -> 393.5686 | O48: =VLOOKUP(C48,'Cleaned Customer Dim'!$A$2:$D$501,4,FALSE) -> 29 | P48: =VLOOKUP(C48,'Cleaned Customer Dim'!$A$2:$E$501,5,FALSE) -> Female | Q48: =VLOOKUP(C48,'Cleaned Customer Dim'!$A$2:$J$501,10,FALSE) -> Gold | R48: =VLOOKUP(D48,'Cleaned Product Dim'!$A$2:$C$101,3,FALSE) -> Home | S48: =VLOOKUP(D48,'Cleaned Product Dim'!$A$2:$G$101,7,FALSE) -> 325.26 | T48: =VLOOKUP(D48,'Cleaned Product Dim'!$A$2:$H$101,8,FALSE) -> 400 | U48: =VLOOKUP(E48,'Cleaned Store Dim'!$A$2:$C$21,3,FALSE) -> West | V48: =VLOOKUP(E48,'Cleaned Store Dim'!$A$2:$E$21,5,FALSE) -> Flagship | W48: =VLOOKUP(E48,'Cleaned Store Dim'!$A$2:$F$21,6,FALSE) -> New Jimmy
A49: SALE47 | B49: 45466 | C49: CUST1008 | D49: PROD30 | E49: STORE11 | F49: 1 | G49: 135.78 | H49: 0.14 | I49: PayPal | J49: 116.7708 | K49: =IF(F49="",J49/(G49*(1-H49)),F49) -> 1 | L49: =IF(G49="",J49/(K49*(1-H49)),G49) -> 135.78 | M49: =IF(H49="",1-(J49/(K49*L49)),H49) -> 0.14 | N49: =IF(J49="",F49*G49*(1-H49),J49) -> 116.7708 | O49: =VLOOKUP(C49,'Cleaned Customer Dim'!$A$2:$D$501,4,FALSE) -> 53 | P49: =VLOOKUP(C49,'Cleaned Customer Dim'!$A$2:$E$501,5,FALSE) -> Female | Q49: =VLOOKUP(C49,'Cleaned Customer Dim'!$A$2:$J$501,10,FALSE) -> Gold | R49: =VLOOKUP(D49,'Cleaned Product Dim'!$A$2:$C$101,3,FALSE) -> Home | S49: =VLOOKUP(D49,'Cleaned Product Dim'!$A$2:$G$101,7,FALSE) -> 19.52 | T49: =VLOOKUP(D49,'Cleaned Product Dim'!$A$2:$H$101,8,FALSE) -> 57 | U49: =VLOOKUP(E49,'Cleaned Store Dim'!$A$2:$C$21,3,FALSE) -> South | V49: =VLOOKUP(E49,'Cleaned Store Dim'!$A$2:$E$21,5,FALSE) -> Online | W49: =VLOOKUP(E49,'Cleaned Store Dim'!$A$2:$F$21,6,FALSE) -> Lake
A50: SALE48 | B50: 45218 | C50: CUST1203 | D50: PROD44 | E50: STORE17 | F50: 1 | G50: 517.13 | H50: 0.28 | I50: Credit Card | J50: 372.3336 | K50: =IF(F50="",J50/(G50*(1-H50)),F50) -> 1 | L50: =IF(G50="",J50/(K50*(1-H50)),G50) -> 517.13 | M50: =IF(H50="",1-(J50/(K50*L50)),H50) -> 0.28 | N50: =IF(J50="",F50*G50*(1-H50),J50) -> 372.3336 | O50: =VLOOKUP(C50,'Cleaned Customer Dim'!$A$2:$D$501,4,FALSE) -> 47 | P50: =VLOOKUP(C50,'Cleaned Customer Dim'!$A$2:$E$501,5,FALSE) -> Male | Q50: =VLOOKUP(C50,'Cleaned Customer Dim'!$A$2:$J$501,10,FALSE) -> Platinum | R50: =VLOOKUP(D50,'Cleaned Product Dim'!$A$2:$C$101,3,FALSE) -> Sports | S50: =VLOOKUP(D50,'Cleaned Product Dim'!$A$2:$G$101,7,FALSE) -> 167.12 | T50: =VLOOKUP(D50,'Cleaned Product Dim'!$A$2:$H$101,8,FALSE) -> 316 | U50: =VLOOKUP(E50,'Cleaned Store Dim'!$A$2:$C$21,3,FALSE) -> North | V50: =VLOOKUP(E50,'Cleaned Store Dim'!$A$2:$E$21,5,FALSE) -> Flagship | W50: =VLOOKUP(E50,'Cleaned Store Dim'!$A$2:$F$21,6,FALSE) -> Benson
A51: SALE49 | B51: 45607 | C51: CUST1420 | D51: PROD21 | E51: STORE16 | F51: 2 | G51: 384.66 | H51: 0.08 | I51: COD | J51: 707.7744 | K51: =IF(F51="",J51/(G51*(1-H51)),F51) -> 2 | L51: =IF(G51="",J51/(K51*(1-H51)),G51) -> 384.66 | M51: =IF(H51="",1-(J51/(K51*L51)),H51) -> 0.08 | N51: =IF(J51="",F51*G51*(1-H51),J51) -> 707.7744 | O51: =VLOOKUP(C51,'Cleaned Customer Dim'!$A$2:$D$501,4,FALSE) -> 60 | P51: =VLOOKUP(C51,'Cleaned Customer Dim'!$A$2:$E$501,5,FALSE) -> Male | Q51: =VLOOKUP(C51,'Cleaned Customer Dim'!$A$2:$J$501,10,FALSE) -> Bronze | R51: =VLOOKUP(D51,'Cleaned Product Dim'!$A$2:$C$101,3,FALSE) -> Home | S51: =VLOOKUP(D51,'Cleaned Product Dim'!$A$2:$G$101,7,FALSE) -> 123.46 | T51: =VLOOKUP(D51,'Cleaned Product Dim'!$A$2:$H$101,8,FALSE) -> 76 | U51: =VLOOKUP(E51,'Cleaned Store Dim'!$A$2:$C$21,3,FALSE) -> West | V51: =VLOOKUP(E51,'Cleaned Store Dim'!$A$2:$E$21,5,FALSE) -> Flagship | W51: =VLOOKUP(E51,'Cleaned Store Dim'!$A$2:$F$21,6,FALSE) -> New Jimmy
A52: SALE50 | B52: 45291 | C52: CUST1070 | D52: PROD52 | E52: STORE9 | F52: 3 | G52: 83.7 | H52: 0.24 | I52: PayPal | J52: 190.836 | K52: =IF(F52="",J52/(G52*(1-H52)),F52) -> 3 | L52: =IF(G52="",J52/(K52*(1-H52)),G52) -> 83.7 | M52: =IF(H52="",1-(J52/(K52*L52)),H52) -> 0.24 | N52: =IF(J52="",F52*G52*(1-H52),J52) -> 190.836 | O52: =VLOOKUP(C52,'Cleaned Customer Dim'!$A$2:$D$501,4,FALSE) -> 29 | P52: =VLOOKUP(C52,'Cleaned Customer Dim'!$A$2:$E$501,5,FALSE) -> Female | Q52: =VLOOKUP(C52,'Cleaned Customer Dim'!$A$2:$J$501,10,FALSE) -> Gold | R52: =VLOOKUP(D52,'Cleaned Product Dim'!$A$2:$C$101,3,FALSE) -> Sports | S52: =VLOOKUP(D52,'Cleaned Product Dim'!$A$2:$G$101,7,FALSE) -> 212.26 | T52: =VLOOKUP(D52,'Cleaned Product Dim'!$A$2:$H$101,8,FALSE) -> 82 | U52: =VLOOKUP(E52,'Cleaned Store Dim'!$A$2:$C$21,3,FALSE) -> South | V52: =VLOOKUP(E52,'Cleaned Store Dim'!$A$2:$E$21,5,FALSE) -> Flagship | W52: =VLOOKUP(E52,'Cleaned Store Dim'!$A$2:$F$21,6,FALSE) -> Johnstad
A53: SALE51 | B53: 45659 | C53: CUST1142 | D53: PROD69 | E53: STORE7 | F53: 3 | G53: 76.57 | H53: 0.26 | I53: Credit Card | J53: 169.9854 | K53: =IF(F53="",J53/(G53*(1-H53)),F53) -> 3 | L53: =IF(G53="",J53/(K53*(1-H53)),G53) -> 76.57 | M53: =IF(H53="",1-(J53/(K53*L53)),H53) -> 0.26 | N53: =IF(J53="",F53*G53*(1-H53),J53) -> 169.9854 | O53: =VLOOKUP(C53,'Cleaned Customer Dim'!$A$2:$D$501,4,FALSE) -> 37 | P53: =VLOOKUP(C53,'Cleaned Customer Dim'!$A$2:$E$501,5,FALSE) -> Male | Q53: =VLOOKUP(C53,'Cleaned Customer Dim'!$A$2:$J$501,10,FALSE) -> Bronze | R53: =VLOOKUP(D53,'Cleaned Product Dim'!$A$2:$C$101,3,FALSE) -> Clothing | S53: =VLOOKUP(D53,'Cleaned Product Dim'!$A$2:$G$101,7,FALSE) -> 218.22 | T53: =VLOOKUP(D53,'Cleaned Product Dim'!$A$2:$H$101,8,FALSE) -> 224 | U53: =VLOOKUP(E53,'Cleaned Store Dim'!$A$2:$C$21,3,FALSE) -> South | V53: =VLOOKUP(E53,'Cleaned Store Dim'!$A$2:$E$21,5,FALSE) -> Online | W53: =VLOOKUP(E53,'Cleaned Store Dim'!$A$2:$F$21,6,FALSE) -> Williamsport
A54: SALE52 | B54: 45894 | C54: CUST1148 | D54: PROD89 | E54: STORE6 | F54: 3 | I54: Credit Card | J54: 486.0633 | K54: =IF(F54="",J54/(G54*(1-H54)),F54) -> 3 | L54: =IF(G54="",J54/(K54*(1-H54)),G54) -> 162.0211 | M54: =IF(H54="",1-(J54/(K54*L54)),H54) -> 0 | N54: =IF(J54="",F54*G54*(1-H54),J54) -> 486.0633 | O54: =VLOOKUP(C54,'Cleaned Customer Dim'!$A$2:$D$501,4,FALSE) -> 42 | P54: =VLOOKUP(C54,'Cleaned Customer Dim'!$A$2:$E$501,5,FALSE) -> Female | Q54: =VLOOKUP(C54,'Cleaned Customer Dim'!$A$2:$J$501,10,FALSE) -> Bronze | R54: =VLOOKUP(D54,'Cleaned Product Dim'!$A$2:$C$101,3,FALSE) -> Beauty | S54: =VLOOKUP(D54,'Cleaned Product Dim'!$A$2:$G$101,7,FALSE) -> 183.04 | T54: =VLOOKUP(D54,'Cleaned Product Dim'!$A$2:$H$101,8,FALSE) -> 457 | U54: =VLOOKUP(E54,'Cleaned Store Dim'!$A$2:$C$21,3,FALSE) -> East | V54: =VLOOKUP(E54,'Cleaned Store Dim'!$A$2:$E$21,5,FALSE) -> Online | W54: =VLOOKUP(E54,'Cleaned Store Dim'!$A$2:$F$21,6,FALSE) -> Joseph
A55: SALE53 | B55: 45677 | C55: CUST1324 | D55: PROD20 | E55: STORE8 | F55: 1 | G55: 900.35 | H55: 0.13 | I55: COD | J55: 783.3045 | K55: =IF(F55="",J55/(G55*(1-H55)),F55) -> 1 | L55: =IF(G55="",J55/(K55*(1-H55)),G55) -> 900.35 | M55: =IF(H55="",1-(J55/(K55*L55)),H55) -> 0.13 | N55: =IF(J55="",F55*G55*(1-H55),J55) -> 783.3045 | O55: =VLOOKUP(C55,'Cleaned Customer Dim'!$A$2:$D$501,4,FALSE) -> 58 | P55: =VLOOKUP(C55,'Cleaned Customer Dim'!$A$2:$E$501,5,FALSE) -> Male | Q55: =VLOOKUP(C55,'Cleaned Customer Dim'!$A$2:$J$501,10,FALSE) -> Bronze | R55: =VLOOKUP(D55,'Cleaned Product Dim'!$A$2:$C$101,3,FALSE) -> Sports | S55: =VLOOKUP(D55,'Cleaned Product Dim'!$A$2:$G$101,7,FALSE) -> 131.51 | T55: =VLOOKUP(D55,'Cleaned Product Dim'!$A$2:$H$101,8,FALSE) -> 281.95833 | U55: =VLOOKUP(E55,'Cleaned Store Dim'!$A$2:$C$21,3,FALSE) -> West | V55: =VLOOKUP(E55,'Cleaned Store Dim'!$A$2:$E$21,5,FALSE) -> Online | W55: =VLOOKUP(E55,'Cleaned Store Dim'!$A$2:$F$21,6,FALSE) -> Thompson
A56: SALE54 | B56: 45706 | C56: CUST1095 | D56: PROD40 | E56: STORE10 | F56: 4 | G56: 428.09 | H56: 0.07 | I56: Credit Card | J56: 1592.4948 | K56: =IF(F56="",J56/(G56*(1-H56)),F56) -> 4 | L56: =IF(G56="",J56/(K56*(1-H56)),G56) -> 428.09 | M56: =IF(H56="",1-(J56/(K56*L56)),H56) -> 0.07 | N56: =IF(J56="",F56*G56*(1-H56),J56) -> 1592.4948 | O56: =VLOOKUP(C56,'Cleaned Customer Dim'!$A$2:$D$501,4,FALSE) -> 62 | P56: =VLOOKUP(C56,'Cleaned Customer Dim'!$A$2:$E$501,5,FALSE) -> Female | Q56: =VLOOKUP(C56,'Cleaned Customer Dim'!$A$2:$J$501,10,FALSE) -> Platinum | R56: =VLOOKUP(D56,'Cleaned Product Dim'!$A$2:$C$101,3,FALSE) -> Electronics | S56: =VLOOKUP(D56,'Cleaned Product Dim'!$A$2:$G$101,7,FALSE) -> 38.52 | T56: =VLOOKUP(D56,'Cleaned Product Dim'!$A$2:$H$101,8,FALSE) -> 378 | U56: =VLOOKUP(E56,'Cleaned Store Dim'!$A$2:$C$21,3,FALSE) -> East | V56: =VLOOKUP(E56,'Cleaned Store Dim'!$A$2:$E$21,5,FALSE) -> Online | W56: =VLOOKUP(E56,'Cleaned Store Dim'!$A$2:$F$21,6,FALSE) -> David
A57: SALE55 | B57: 45589 | C57: CUST1416 | D57: PROD49 | E57: STORE11 | F57: 2 | G57: 559.71 | H57: 0.3 | I57: COD | J57: 783.594 | K57: =IF(F57="",J57/(G57*(1-H57)),F57) -> 2 | L57: =IF(G57="",J57/(K57*(1-H57)),G57) -> 559.71 | M57: =IF(H57="",1-(J57/(K57*L57)),H57) -> 0.3 | N57: =IF(J57="",F57*G57*(1-H57),J57) -> 783.594 | O57: =VLOOKUP(C57,'Cleaned Customer Dim'!$A$2:$D$501,4,FALSE) -> 46 | P57: =VLOOKUP(C57,'Cleaned Customer Dim'!$A$2:$E$501,5,FALSE) -> Male | Q57: =VLOOKUP(C57,'Cleaned Customer Dim'!$A$2:$J$501,10,FALSE) -> Platinum | R57: =VLOOKUP(D57,'Cleaned Product Dim'!$A$2:$C$101,3,FALSE) -> Beauty | S57: =VLOOKUP(D57,'Cleaned Product Dim'!$A$2:$G$101,7,FALSE) -> 43.29 | T57: =VLOOKUP(D57,'Cleaned Product Dim'!$A$2:$H$101,8,FALSE) -> 267 | U57: =VLOOKUP(E57,'Cleaned Store Dim'!$A$2:$C$21,3,FALSE) -> South | V57: =VLOOKUP(E57,'Cleaned Store Dim'!$A$2:$E$21,5,FALSE) -> Online | W57: =VLOOKUP(E57,'Cleaned Store Dim'!$A$2:$F$21,6,FALSE) -> Lake
A58: SALE56 | B58: 45282 | C58: CUST1080 | D58: PROD34 | E58: STORE6 | F58: 2 | G58: 833.7 | H58: 0.06 | I58: PayPal | J58: 1567.356 | K58: =IF(F58="",J58/(G58*(1-H58)),F58) -> 2 | L58: =IF(G58="",J58/(K58*(1-H58)),G58) -> 833.7 | M58: =IF(H58="",1-(J58/(K58*L58)),H58) -> 0.06 | N58: =IF(J58="",F58*G58*(1-H58),J58) -> 1567.356 | O58: =VLOOKUP(C58,'Cleaned Customer Dim'!$A$2:$D$501,4,FALSE) -> 61 | P58: =VLOOKUP(C58,'Cleaned Customer Dim'!$A$2:$E$501,5,FALSE) -> Female | Q58: =VLOOKUP(C58,'Cleaned Customer Dim'!$A$2:$J$501,10,FALSE) -> Bronze | R58: =VLOOKUP(D58,'Cleaned Product Dim'!$A$2:$C$101,3,FALSE) -> Electronics | S58: =VLOOKUP(D58,'Cleaned Product Dim'!$A$2:$G$101,7,FALSE) -> 419.28 | T58: =VLOOKUP(D58,'Cleaned Product Dim'!$A$2:$H$101,8,FALSE) -> 86 | U58: =VLOOKUP(E58,'Cleaned Store Dim'!$A$2:$C$21,3,FALSE) -> East | V58: =VLOOKUP(E58,'Cleaned Store Dim'!$A$2:$E$21,5,FALSE) -> Online | W58: =VLOOKUP(E58,'Cleaned Store Dim'!$A$2:$F$21,6,FALSE) -> Joseph
A59: SALE57 | B59: 45462 | C59: CUST1467 | D59: PROD47 | E59: STORE14 | F59: 2 | G59: 680.16 | H59: 0.28 | I59: Credit Card | J59: 979.4304 | K59: =IF(F59="",J59/(G59*(1-H59)),F59) -> 2 | L59: =IF(G59="",J59/(K59*(1-H59)),G59) -> 680.16 | M59: =IF(H59="",1-(J59/(K59*L59)),H59) -> 0.28 | N59: =IF(J59="",F59*G59*(1-H59),J59) -> 979.4304 | O59: =VLOOKUP(C59,'Cleaned Customer Dim'!$A$2:$D$501,4,FALSE) -> 63 | P59: =VLOOKUP(C59,'Cleaned Customer Dim'!$A$2:$E$501,5,FALSE) -> Female | Q59: =VLOOKUP(C59,'Cleaned Customer Dim'!$A$2:$J$501,10,FALSE) -> Gold | R59: =VLOOKUP(D59,'Cleaned Product Dim'!$A$2:$C$101,3,FALSE) -> Beauty | S59: =VLOOKUP(D59,'Cleaned Product Dim'!$A$2:$G$101,7,FALSE) -> 250.41615 | T59: =VLOOKUP(D59,'Cleaned Product Dim'!$A$2:$H$101,8,FALSE) -> 431 | U59: =VLOOKUP(E59,'Cleaned Store Dim'!$A$2:$C$21,3,FALSE) -> South | V59: =VLOOKUP(E59,'Cleaned Store Dim'!$A$2:$E$21,5,FALSE) -> Outlet | W59: =VLOOKUP(E59,'Cleaned Store Dim'!$A$2:$F$21,6,FALSE) -> Christopher
A60: SALE58 | B60: 45485 | C60: CUST1404 | D60: PROD15 | E60: STORE7 | F60: 4 | G60: 733.42 | I60: PayPal | J60: 2552.3016 | K60: =IF(F60="",J60/(G60*(1-H60)),F60) -> 4 | L60: =IF(G60="",J60/(K60*(1-H60)),G60) -> 733.42 | M60: =IF(H60="",1-(J60/(K60*L60)),H60) -> 0.13 | N60: =IF(J60="",F60*G60*(1-H60),J60) -> 2552.3016 | O60: =VLOOKUP(C60,'Cleaned Customer Dim'!$A$2:$D$501,4,FALSE) -> 22 | P60: =VLOOKUP(C60,'Cleaned Customer Dim'!$A$2:$E$501,5,FALSE) -> Female | Q60: =VLOOKUP(C60,'Cleaned Customer Dim'!$A$2:$J$501,10,FALSE) -> Silver | R60: =VLOOKUP(D60,'Cleaned Product Dim'!$A$2:$C$101,3,FALSE) -> Electronics | S60: =VLOOKUP(D60,'Cleaned Product Dim'!$A$2:$G$101,7,FALSE) -> 465.34 | T60: =VLOOKUP(D60,'Cleaned Product Dim'!$A$2:$H$101,8,FALSE) -> 301 | U60: =VLOOKUP(E60,'Cleaned Store Dim'!$A$2:$C$21,3,FALSE) -> South | V60: =VLOOKUP(E60,'Cleaned Store Dim'!$A$2:$E$21,5,FALSE) -> Online | W60: =VLOOKUP(E60,'Cleaned Store Dim'!$A$2:$F$21,6,FALSE) -> Williamsport
A61: SALE59 | B61: 45257 | C61: CUST1367 | D61: PROD89 | E61: STORE11 | F61: 1 | G61: 996.33 | H61: 0.23 | I61: PayPal | J61: 767.1741 | K61: =IF(F61="",J61/(G61*(1-H61)),F61) -> 1 | L61: =IF(G61="",J61/(K61*(1-H61)),G61) -> 996.33 | M61: =IF(H61="",1-(J61/(K61*L61)),H61) -> 0.23 | N61: =IF(J61="",F61*G61*(1-H61),J61) -> 767.1741 | O61: =VLOOKUP(C61,'Cleaned Customer Dim'!$A$2:$D$501,4,FALSE) -> 51 | P61: =VLOOKUP(C61,'Cleaned Customer Dim'!$A$2:$E$501,5,FALSE) -> Male | Q61: =VLOOKUP(C61,'Cleaned Customer Dim'!$A$2:$J$501,10,FALSE) -> Bronze | R61: =VLOOKUP(D61,'Cleaned Product Dim'!$A$2:$C$101,3,FALSE) -> Beauty | S61: =VLOOKUP(D61,'Cleaned Product Dim'!$A$2:$G$101,7,FALSE) -> 183.04 | T61: =VLOOKUP(D61,'Cleaned Product Dim'!$A$2:$H$101,8,FALSE) -> 457 | U61: =VLOOKUP(E61,'Cleaned Store Dim'!$A$2:$C$21,3,FALSE) -> South | V61: =VLOOKUP(E61,'Cleaned Store Dim'!$A$2:$E$21,5,FALSE) -> Online | W61: =VLOOKUP(E61,'Cleaned Store Dim'!$A$2:$F$21,6,FALSE) -> Lake
A62: SALE60 | B62: 45854 | C62: CUST1408 | D62: PROD31 | E62: STORE10 | F62: 1 | G62: 198.83 | H62: 0.09 | I62: COD | J62: 180.9353 | K62: =IF(F62="",J62/(G62*(1-H62)),F62) -> 1 | L62: =IF(G62="",J62/(K62*(1-H62)),G62) -> 198.83 | M62: =IF(H62="",1-(J62/(K62*L62)),H62) -> 0.09 | N62: =IF(J62="",F62*G62*(1-H62),J62) -> 180.9353 | O62: =VLOOKUP(C62,'Cleaned Customer Dim'!$A$2:$D$501,4,FALSE) -> 36 | P62: =VLOOKUP(C62,'Cleaned Customer Dim'!$A$2:$E$501,5,FALSE) -> Male | Q62: =VLOOKUP(C62,'Cleaned Customer Dim'!$A$2:$J$501,10,FALSE) -> Gold | R62: =VLOOKUP(D62,'Cleaned Product Dim'!$A$2:$C$101,3,FALSE) -> Sports | S62: =VLOOKUP(D62,'Cleaned Product Dim'!$A$2:$G$101,7,FALSE) -> 204.39 | T62: =VLOOKUP(D62,'Cleaned Product Dim'!$A$2:$H$101,8,FALSE) -> 281 | U62: =VLOOKUP(E62,'Cleaned Store Dim'!$A$2:$C$21,3,FALSE) -> East | V62: =VLOOKUP(E62,'Cleaned Store Dim'!$A$2:$E$21,5,FALSE) -> Online | W62: =VLOOKUP(E62,'Cleaned Store Dim'!$A$2:$F$21,6,FALSE) -> David
A63: SALE61 | B63: 45716 | C63: CUST1239 | D63: PROD19 | E63: STORE7 | F63: 1 | G63: 374.92 | H63: 0.18 | I63: PayPal | J63: 307.4344 | K63: =IF(F63="",J63/(G63*(1-H63)),F63) -> 1 | L63: =IF(G63="",J63/(K63*(1-H63)),G63) -> 374.92 | M63: =IF(H63="",1-(J63/(K63*L63)),H63) -> 0.18 | N63: =IF(J63="",F63*G63*(1-H63),J63) -> 307.4344 | O63: =VLOOKUP(C63,'Cleaned Customer Dim'!$A$2:$D$501,4,FALSE) -> 58 | P63: =VLOOKUP(C63,'Cleaned Customer Dim'!$A$2:$E$501,5,FALSE) -> Female | Q63: =VLOOKUP(C63,'Cleaned Customer Dim'!$A$2:$J$501,10,FALSE) -> Platinum | R63: =VLOOKUP(D63,'Cleaned Product Dim'!$A$2:$C$101,3,FALSE) -> Sports | S63: =VLOOKUP(D63,'Cleaned Product Dim'!$A$2:$G$101,7,FALSE) -> 21.34 | T63: =VLOOKUP(D63,'Cleaned Product Dim'!$A$2:$H$101,8,FALSE) -> 65 | U63: =VLOOKUP(E63,'Cleaned Store Dim'!$A$2:$C$21,3,FALSE) -> South | V63: =VLOOKUP(E63,'Cleaned Store Dim'!$A$2:$E$21,5,FALSE) -> Online | W63: =VLOOKUP(E63,'Cleaned Store Dim'!$A$2:$F$21,6,FALSE) -> Williamsport
A64: SALE62 | B64: 45604 | C64: CUST1464 | D64: PROD93 | E64: STORE16 | F64: 1 | G64: 468.94 | H64: 0.12 | I64: Credit Card | J64: 412.6672 | K64: =IF(F64="",J64/(G64*(1-H64)),F64) -> 1 | L64: =IF(G64="",J64/(K64*(1-H64)),G64) -> 468.94 | M64: =IF(H64="",1-(J64/(K64*L64)),H64) -> 0.12 | N64: =IF(J64="",F64*G64*(1-H64),J64) -> 412.6672 | O64: =VLOOKUP(C64,'Cleaned Customer Dim'!$A$2:$D$501,4,FALSE) -> 45 | P64: =VLOOKUP(C64,'Cleaned Customer Dim'!$A$2:$E$501,5,FALSE) -> Female | Q64: =VLOOKUP(C64,'Cleaned Customer Dim'!$A$2:$J$501,10,FALSE) -> Platinum | R64: =VLOOKUP(D64,'Cleaned Product Dim'!$A$2:$C$101,3,FALSE) -> Electronics | S64: =VLOOKUP(D64,'Cleaned Product Dim'!$A$2:$G$101,7,FALSE) -> 377.52 | T64: =VLOOKUP(D64,'Cleaned Product Dim'!$A$2:$H$101,8,FALSE) -> 485 | U64: =VLOOKUP(E64,'Cleaned Store Dim'!$A$2:$C$21,3,FALSE) -> West | V64: =VLOOKUP(E64,'Cleaned Store Dim'!$A$2:$E$21,5,FALSE) -> Flagship | W64: =VLOOKUP(E64,'Cleaned Store Dim'!$A$2:$F$21,6,FALSE) -> New Jimmy
A65: SALE63 | B65: 45927 | C65: CUST1126 | D65: PROD89 | E65: STORE12 | F65: 2 | G65: 121.37 | H65: 0.05 | I65: Credit Card | J65: 230.603 | K65: =IF(F65="",J65/(G65*(1-H65)),F65) -> 2 | L65: =IF(G65="",J65/(K65*(1-H65)),G65) -> 121.37 | M65: =IF(H65="",1-(J65/(K65*L65)),H65) -> 0.05 | N65: =IF(J65="",F65*G65*(1-H65),J65) -> 230.603 | O65: =VLOOKUP(C65,'Cleaned Customer Dim'!$A$2:$D$501,4,FALSE) -> 62 | P65: =VLOOKUP(C65,'Cleaned Customer Dim'!$A$2:$E$501,5,FALSE) -> Female | Q65: =VLOOKUP(C65,'Cleaned Customer Dim'!$A$2:$J$501,10,FALSE) -> Gold | R65: =VLOOKUP(D65,'Cleaned Product Dim'!$A$2:$C$101,3,FALSE) -> Beauty | S65: =VLOOKUP(D65,'Cleaned Product Dim'!$A$2:$G$101,7,FALSE) -> 183.04 | T65: =VLOOKUP(D65,'Cleaned Product Dim'!$A$2:$H$101,8,FALSE) -> 457 | U65: =VLOOKUP(E65,'Cleaned Store Dim'!$A$2:$C$21,3,FALSE) -> North | V65: =VLOOKUP(E65,'Cleaned Store Dim'!$A$2:$E$21,5,FALSE) -> Online | W65: =VLOOKUP(E65,'Cleaned Store Dim'!$A$2:$F$21,6,FALSE) -> Sabrina
A66: SALE64 | B66: 45914 | C66: CUST1255 | D66: PROD53 | E66: STORE10 | F66: 3 | G66: 480.06 | H66: 0.01 | I66: Credit Card | K66: =IF(F66="",J66/(G66*(1-H66)),F66) -> 3 | L66: =IF(G66="",J66/(K66*(1-H66)),G66) -> 480.06 | M66: =IF(H66="",1-(J66/(K66*L66)),H66) -> 0.01 | N66: =IF(J66="",F66*G66*(1-H66),J66) -> 1425.7782 | O66: =VLOOKUP(C66,'Cleaned Customer Dim'!$A$2:$D$501,4,FALSE) -> 21 | P66: =VLOOKUP(C66,'Cleaned Customer Dim'!$A$2:$E$501,5,FALSE) -> Male | Q66: =VLOOKUP(C66,'Cleaned Customer Dim'!$A$2:$J$501,10,FALSE) -> Gold | R66: =VLOOKUP(D66,'Cleaned Product Dim'!$A$2:$C$101,3,FALSE) -> Clothing | S66: =VLOOKUP(D66,'Cleaned Product Dim'!$A$2:$G$101,7,FALSE) -> 386.56 | T66: =VLOOKUP(D66,'Cleaned Product Dim'!$A$2:$H$101,8,FALSE) -> 125 | U66: =VLOOKUP(E66,'Cleaned Store Dim'!$A$2:$C$21,3,FALSE) -> East | V66: =VLOOKUP(E66,'Cleaned Store Dim'!$A$2:$E$21,5,FALSE) -> Online | W66: =VLOOKUP(E66,'Cleaned Store Dim'!$A$2:$F$21,6,FALSE) -> David
A67: SALE65 | B67: 45290 | C67: CUST1162 | D67: PROD99 | E67: STORE17 | F67: 2 | G67: 856.57 | H67: 0.24 | I67: Credit Card | J67: 1301.9864 | K67: =IF(F67="",J67/(G67*(1-H67)),F67) -> 2 | L67: =IF(G67="",J67/(K67*(1-H67)),G67) -> 856.57 | M67: =IF(H67="",1-(J67/(K67*L67)),H67) -> 0.24 | N67: =IF(J67="",F67*G67*(1-H67),J67) -> 1301.9864 | O67: =VLOOKUP(C67,'Cleaned Customer Dim'!$A$2:$D$501,4,FALSE) -> 37 | P67: =VLOOKUP(C67,'Cleaned Customer Dim'!$A$2:$E$501,5,FALSE) -> Male | Q67: =VLOOKUP(C67,'Cleaned Customer Dim'!$A$2:$J$501,10,FALSE) -> Silver | R67: =VLOOKUP(D67,'Cleaned Product Dim'!$A$2:$C$101,3,FALSE) -> Home | S67: =VLOOKUP(D67,'Cleaned Product Dim'!$A$2:$G$101,7,FALSE) -> 201.41 | T67: =VLOOKUP(D67,'Cleaned Product Dim'!$A$2:$H$101,8,FALSE) -> 146 | U67: =VLOOKUP(E67,'Cleaned Store Dim'!$A$2:$C$21,3,FALSE) -> North | V67: =VLOOKUP(E67,'Cleaned Store Dim'!$A$2:$E$21,5,FALSE) -> Flagship | W67: =VLOOKUP(E67,'Cleaned Store Dim'!$A$2:$F$21,6,FALSE) -> Benson
A68: SALE66 | B68: 45213 | C68: CUST1269 | D68: PROD77 | E68: STORE2 | F68: 4 | G68: 814.25 | H68: 0.18 | I68: Credit Card | J68: 2670.74 | K68: =IF(F68="",J68/(G68*(1-H68)),F68) -> 4 | L68: =IF(G68="",J68/(K68*(1-H68)),G68) -> 814.25 | M68: =IF(H68="",1-(J68/(K68*L68)),H68) -> 0.18 | N68: =IF(J68="",F68*G68*(1-H68),J68) -> 2670.74 | O68: =VLOOKUP(C68,'Cleaned Customer Dim'!$A$2:$D$501,4,FALSE) -> 45 | P68: =VLOOKUP(C68,'Cleaned Customer Dim'!$A$2:$E$501,5,FALSE) -> Female | Q68: =VLOOKUP(C68,'Cleaned Customer Dim'!$A$2:$J$501,10,FALSE) -> Silver | R68: =VLOOKUP(D68,'Cleaned Product Dim'!$A$2:$C$101,3,FALSE) -> Electronics | S68: =VLOOKUP(D68,'Cleaned Product Dim'!$A$2:$G$101,7,FALSE) -> 480.9 | T68: =VLOOKUP(D68,'Cleaned Product Dim'!$A$2:$H$101,8,FALSE) -> 104 | U68: =VLOOKUP(E68,'Cleaned Store Dim'!$A$2:$C$21,3,FALSE) -> South | V68: =VLOOKUP(E68,'Cleaned Store Dim'!$A$2:$E$21,5,FALSE) -> Outlet | W68: =VLOOKUP(E68,'Cleaned Store Dim'!$A$2:$F$21,6,FALSE) -> North Nancy
A69: SALE67 | B69: 45255 | C69: CUST1483 | D69: PROD12 | E69: STORE2 | F69: 1 | G69: 989.17 | H69: 0.2 | I69: PayPal | J69: 791.336 | K69: =IF(F69="",J69/(G69*(1-H69)),F69) -> 1 | L69: =IF(G69="",J69/(K69*(1-H69)),G69) -> 989.17 | M69: =IF(H69="",1-(J69/(K69*L69)),H69) -> 0.2 | N69: =IF(J69="",F69*G69*(1-H69),J69) -> 791.336 | O69: =VLOOKUP(C69,'Cleaned Customer Dim'!$A$2:$D$501,4,FALSE) -> 48 | P69: =VLOOKUP(C69,'Cleaned Customer Dim'!$A$2:$E$501,5,FALSE) -> Male | Q69: =VLOOKUP(C69,'Cleaned Customer Dim'!$A$2:$J$501,10,FALSE) -> Gold | R69: =VLOOKUP(D69,'Cleaned Product Dim'!$A$2:$C$101,3,FALSE) -> Beauty | S69: =VLOOKUP(D69,'Cleaned Product Dim'!$A$2:$G$101,7,FALSE) -> 115.82 | T69: =VLOOKUP(D69,'Cleaned Product Dim'!$A$2:$H$101,8,FALSE) -> 460 | U69: =VLOOKUP(E69,'Cleaned Store Dim'!$A$2:$C$21,3,FALSE) -> South | V69: =VLOOKUP(E69,'Cleaned Store Dim'!$A$2:$E$21,5,FALSE) -> Outlet | W69: =VLOOKUP(E69,'Cleaned Store Dim'!$A$2:$F$21,6,FALSE) -> North Nancy
A70: SALE68 | B70: 45211 | C70: CUST1372 | D70: PROD72 | E70: STORE10 | F70: 4 | G70: 62.48 | H70: 0.18 | I70: Credit Card | J70: 204.9344 | K70: =IF(F70="",J70/(G70*(1-H70)),F70) -> 4 | L70: =IF(G70="",J70/(K70*(1-H70)),G70) -> 62.48 | M70: =IF(H70="",1-(J70/(K70*L70)),H70) -> 0.18 | N70: =IF(J70="",F70*G70*(1-H70),J70) -> 204.9344 | O70: =VLOOKUP(C70,'Cleaned Customer Dim'!$A$2:$D$501,4,FALSE) -> 28 | P70: =VLOOKUP(C70,'Cleaned Customer Dim'!$A$2:$E$501,5,FALSE) -> Male | Q70: =VLOOKUP(C70,'Cleaned Customer Dim'!$A$2:$J$501,10,FALSE) -> Bronze | R70: =VLOOKUP(D70,'Cleaned Product Dim'!$A$2:$C$101,3,FALSE) -> Sports | S70: =VLOOKUP(D70,'Cleaned Product Dim'!$A$2:$G$101,7,FALSE) -> 477.61 | T70: =VLOOKUP(D70,'Cleaned Product Dim'!$A$2:$H$101,8,FALSE) -> 300 | U70: =VLOOKUP(E70,'Cleaned Store Dim'!$A$2:$C$21,3,FALSE) -> East | V70: =VLOOKUP(E70,'Cleaned Store Dim'!$A$2:$E$21,5,FALSE) -> Online | W70: =VLOOKUP(E70,'Cleaned Store Dim'!$A$2:$F$21,6,FALSE) -> David
A71: SALE69 | B71: 45897 | C71: CUST1423 | D71: PROD13 | E71: STORE16 | F71: 4 | G71: 561.24 | H71: 0.24 | I71: Credit Card | J71: 1706.1696 | K71: =IF(F71="",J71/(G71*(1-H71)),F71) -> 4 | L71: =IF(G71="",J71/(K71*(1-H71)),G71) -> 561.24 | M71: =IF(H71="",1-(J71/(K71*L71)),H71) -> 0.24 | N71: =IF(J71="",F71*G71*(1-H71),J71) -> 1706.1696 | O71: =VLOOKUP(C71,'Cleaned Customer Dim'!$A$2:$D$501,4,FALSE) -> 35 | P71: =VLOOKUP(C71,'Cleaned Customer Dim'!$A$2:$E$501,5,FALSE) -> Male | Q71: =VLOOKUP(C71,'Cleaned Customer Dim'!$A$2:$J$501,10,FALSE) -> Silver | R71: =VLOOKUP(D71,'Cleaned Product Dim'!$A$2:$C$101,3,FALSE) -> Electronics | S71: =VLOOKUP(D71,'Cleaned Product Dim'!$A$2:$G$101,7,FALSE) -> 242.23 | T71: =VLOOKUP(D71,'Cleaned Product Dim'!$A$2:$H$101,8,FALSE) -> 453 | U71: =VLOOKUP(E71,'Cleaned Store Dim'!$A$2:$C$21,3,FALSE) -> West | V71: =VLOOKUP(E71,'Cleaned Store Dim'!$A$2:$E$21,5,FALSE) -> Flagship | W71: =VLOOKUP(E71,'Cleaned Store Dim'!$A$2:$F$21,6,FALSE) -> New Jimmy
A72: SALE70 | B72: 45968 | C72: CUST1058 | D72: PROD60 | E72: STORE5 | F72: 3 | G72: 92.24 | H72: 0.28 | I72: COD | K72: =IF(F72="",J72/(G72*(1-H72)),F72) -> 3 | L72: =IF(G72="",J72/(K72*(1-H72)),G72) -> 92.24 | M72: =IF(H72="",1-(J72/(K72*L72)),H72) -> 0.28 | N72: =IF(J72="",F72*G72*(1-H72),J72) -> 199.2384 | O72: =VLOOKUP(C72,'Cleaned Customer Dim'!$A$2:$D$501,4,FALSE) -> 51 | P72: =VLOOKUP(C72,'Cleaned Customer Dim'!$A$2:$E$501,5,FALSE) -> Male | Q72: =VLOOKUP(C72,'Cleaned Customer Dim'!$A$2:$J$501,10,FALSE) -> Platinum | R72: =VLOOKUP(D72,'Cleaned Product Dim'!$A$2:$C$101,3,FALSE) -> Beauty | S72: =VLOOKUP(D72,'Cleaned Product Dim'!$A$2:$G$101,7,FALSE) -> 482.75 | T72: =VLOOKUP(D72,'Cleaned Product Dim'!$A$2:$H$101,8,FALSE) -> 444 | U72: =VLOOKUP(E72,'Cleaned Store Dim'!$A$2:$C$21,3,FALSE) -> North | V72: =VLOOKUP(E72,'Cleaned Store Dim'!$A$2:$E$21,5,FALSE) -> Outlet | W72: =VLOOKUP(E72,'Cleaned Store Dim'!$A$2:$F$21,6,FALSE) -> Chester
A73: SALE71 | B73: 45889 | C73: CUST1168 | D73: PROD72 | E73: STORE1 | F73: 2 | G73: 668.3 | H73: 0.07 | I73: Credit Card | J73: 1243.038 | K73: =IF(F73="",J73/(G73*(1-H73)),F73) -> 2 | L73: =IF(G73="",J73/(K73*(1-H73)),G73) -> 668.3 | M73: =IF(H73="",1-(J73/(K73*L73)),H73) -> 0.07 | N73: =IF(J73="",F73*G73*(1-H73),J73) -> 1243.038 | O73: =VLOOKUP(C73,'Cleaned Customer Dim'!$A$2:$D$501,4,FALSE) -> 36 | P73: =VLOOKUP(C73,'Cleaned Customer Dim'!$A$2:$E$501,5,FALSE) -> Female | Q73: =VLOOKUP(C73,'Cleaned Customer Dim'!$A$2:$J$501,10,FALSE) -> Platinum | R73: =VLOOKUP(D73,'Cleaned Product Dim'!$A$2:$C$101,3,FALSE) -> Sports | S73: =VLOOKUP(D73,'Cleaned Product Dim'!$A$2:$G$101,7,FALSE) -> 477.61 | T73: =VLOOKUP(D73,'Cleaned Product Dim'!$A$2:$H$101,8,FALSE) -> 300 | U73: =VLOOKUP(E73,'Cleaned Store Dim'!$A$2:$C$21,3,FALSE) -> North | V73: =VLOOKUP(E73,'Cleaned Store Dim'!$A$2:$E$21,5,FALSE) -> Flagship | W73: =VLOOKUP(E73,'Cleaned Store Dim'!$A$2:$F$21,6,FALSE) -> Daniel
A74: SALE72 | B74: 45533 | C74: CUST1409 | D74: PROD38 | E74: STORE5 | F74: 1 | G74: 553.82 | H74: 0.09 | I74: Credit Card | J74: 503.9762 | K74: =IF(F74="",J74/(G74*(1-H74)),F74) -> 1 | L74: =IF(G74="",J74/(K74*(1-H74)),G74) -> 553.82 | M74: =IF(H74="",1-(J74/(K74*L74)),H74) -> 0.09 | N74: =IF(J74="",F74*G74*(1-H74),J74) -> 503.9762 | O74: =VLOOKUP(C74,'Cleaned Customer Dim'!$A$2:$D$501,4,FALSE) -> 55 | P74: =VLOOKUP(C74,'Cleaned Customer Dim'!$A$2:$E$501,5,FALSE) -> Male | Q74: =VLOOKUP(C74,'Cleaned Customer Dim'!$A$2:$J$501,10,FALSE) -> Gold | R74: =VLOOKUP(D74,'Cleaned Product Dim'!$A$2:$C$101,3,FALSE) -> Sports | S74: =VLOOKUP(D74,'Cleaned Product Dim'!$A$2:$G$101,7,FALSE) -> 135.61 | T74: =VLOOKUP(D74,'Cleaned Product Dim'!$A$2:$H$101,8,FALSE) -> 394 | U74: =VLOOKUP(E74,'Cleaned Store Dim'!$A$2:$C$21,3,FALSE) -> North | V74: =VLOOKUP(E74,'Cleaned Store Dim'!$A$2:$E$21,5,FALSE) -> Outlet | W74: =VLOOKUP(E74,'Cleaned Store Dim'!$A$2:$F$21,6,FALSE) -> Chester
A75: SALE73 | B75: 45626 | C75: CUST1037 | D75: PROD45 | E75: STORE11 | F75: 2 | G75: 556.43 | H75: 0.13 | I75: Credit Card | J75: 968.1882 | K75: =IF(F75="",J75/(G75*(1-H75)),F75) -> 2 | L75: =IF(G75="",J75/(K75*(1-H75)),G75) -> 556.43 | M75: =IF(H75="",1-(J75/(K75*L75)),H75) -> 0.13 | N75: =IF(J75="",F75*G75*(1-H75),J75) -> 968.1882 | O75: =VLOOKUP(C75,'Cleaned Customer Dim'!$A$2:$D$501,4,FALSE) -> 27 | P75: =VLOOKUP(C75,'Cleaned Customer Dim'!$A$2:$E$501,5,FALSE) -> Female | Q75: =VLOOKUP(C75,'Cleaned Customer Dim'!$A$2:$J$501,10,FALSE) -> Platinum | R75: =VLOOKUP(D75,'Cleaned Product Dim'!$A$2:$C$101,3,FALSE) -> Sports | S75: =VLOOKUP(D75,'Cleaned Product Dim'!$A$2:$G$101,7,FALSE) -> 318.91 | T75: =VLOOKUP(D75,'Cleaned Product Dim'!$A$2:$H$101,8,FALSE) -> 114 | U75: =VLOOKUP(E75,'Cleaned Store Dim'!$A$2:$C$21,3,FALSE) -> South | V75: =VLOOKUP(E75,'Cleaned Store Dim'!$A$2:$E$21,5,FALSE) -> Online | W75: =VLOOKUP(E75,'Cleaned Store Dim'!$A$2:$F$21,6,FALSE) -> Lake
A76: SALE74 | B76: 46001 | C76: CUST1273 | D76: PROD20 | E76: STORE8 | F76: 1 | G76: 184.98 | H76: 0.1 | I76: COD | J76: 166.482 | K76: =IF(F76="",J76/(G76*(1-H76)),F76) -> 1 | L76: =IF(G76="",J76/(K76*(1-H76)),G76) -> 184.98 | M76: =IF(H76="",1-(J76/(K76*L76)),H76) -> 0.1 | N76: =IF(J76="",F76*G76*(1-H76),J76) -> 166.482 | O76: =VLOOKUP(C76,'Cleaned Customer Dim'!$A$2:$D$501,4,FALSE) -> 23 | P76: =VLOOKUP(C76,'Cleaned Customer Dim'!$A$2:$E$501,5,FALSE) -> Male | Q76: =VLOOKUP(C76,'Cleaned Customer Dim'!$A$2:$J$501,10,FALSE) -> Bronze | R76: =VLOOKUP(D76,'Cleaned Product Dim'!$A$2:$C$101,3,FALSE) -> Sports | S76: =VLOOKUP(D76,'Cleaned Product Dim'!$A$2:$G$101,7,FALSE) -> 131.51 | T76: =VLOOKUP(D76,'Cleaned Product Dim'!$A$2:$H$101,8,FALSE) -> 281.95833 | U76: =VLOOKUP(E76,'Cleaned Store Dim'!$A$2:$C$21,3,FALSE) -> West | V76: =VLOOKUP(E76,'Cleaned Store Dim'!$A$2:$E$21,5,FALSE) -> Online | W76: =VLOOKUP(E76,'Cleaned Store Dim'!$A$2:$F$21,6,FALSE) -> Thompson
A77: SALE75 | B77: 45500 | C77: CUST1035 | D77: PROD97 | E77: STORE12 | F77: 4 | G77: 700.18 | H77: 0.23 | I77: Credit Card | J77: 2156.5544 | K77: =IF(F77="",J77/(G77*(1-H77)),F77) -> 4 | L77: =IF(G77="",J77/(K77*(1-H77)),G77) -> 700.18 | M77: =IF(H77="",1-(J77/(K77*L77)),H77) -> 0.23 | N77: =IF(J77="",F77*G77*(1-H77),J77) -> 2156.5544 | O77: =VLOOKUP(C77,'Cleaned Customer Dim'!$A$2:$D$501,4,FALSE) -> 52 | P77: =VLOOKUP(C77,'Cleaned Customer Dim'!$A$2:$E$501,5,FALSE) -> Male | Q77: =VLOOKUP(C77,'Cleaned Customer Dim'!$A$2:$J$501,10,FALSE) -> Silver | R77: =VLOOKUP(D77,'Cleaned Product Dim'!$A$2:$C$101,3,FALSE) -> Sports | S77: =VLOOKUP(D77,'Cleaned Product Dim'!$A$2:$G$101,7,FALSE) -> 245.98 | T77: =VLOOKUP(D77,'Cleaned Product Dim'!$A$2:$H$101,8,FALSE) -> 471 | U77: =VLOOKUP(E77,'Cleaned Store Dim'!$A$2:$C$21,3,FALSE) -> North | V77: =VLOOKUP(E77,'Cleaned Store Dim'!$A$2:$E$21,5,FALSE) -> Online | W77: =VLOOKUP(E77,'Cleaned Store Dim'!$A$2:$F$21,6,FALSE) -> Sabrina
A78: SALE76 | B78: 45285 | C78: CUST1019 | D78: PROD76 | E78: STORE10 | F78: 2 | G78: 686.31 | H78: 0.25 | I78: Credit Card | J78: 1029.465 | K78: =IF(F78="",J78/(G78*(1-H78)),F78) -> 2 | L78: =IF(G78="",J78/(K78*(1-H78)),G78) -> 686.31 | M78: =IF(H78="",1-(J78/(K78*L78)),H78) -> 0.25 | N78: =IF(J78="",F78*G78*(1-H78),J78) -> 1029.465 | O78: =VLOOKUP(C78,'Cleaned Customer Dim'!$A$2:$D$501,4,FALSE) -> 46 | P78: =VLOOKUP(C78,'Cleaned Customer Dim'!$A$2:$E$501,5,FALSE) -> Female | Q78: =VLOOKUP(C78,'Cleaned Customer Dim'!$A$2:$J$501,10,FALSE) -> Platinum | R78: =VLOOKUP(D78,'Cleaned Product Dim'!$A$2:$C$101,3,FALSE) -> Electronics | S78: =VLOOKUP(D78,'Cleaned Product Dim'!$A$2:$G$101,7,FALSE) -> 392.89 | T78: =VLOOKUP(D78,'Cleaned Product Dim'!$A$2:$H$101,8,FALSE) -> 320 | U78: =VLOOKUP(E78,'Cleaned Store Dim'!$A$2:$C$21,3,FALSE) -> East | V78: =VLOOKUP(E78,'Cleaned Store Dim'!$A$2:$E$21,5,FALSE) -> Online | W78: =VLOOKUP(E78,'Cleaned Store Dim'!$A$2:$F$21,6,FALSE) -> David
A79: SALE77 | B79: 45800 | C79: CUST1007 | D79: PROD67 | E79: STORE15 | F79: 1 | G79: 687.82 | H79: 0.27 | I79: COD | J79: 502.1086 | K79: =IF(F79="",J79/(G79*(1-H79)),F79) -> 1 | L79: =IF(G79="",J79/(K79*(1-H79)),G79) -> 687.82 | M79: =IF(H79="",1-(J79/(K79*L79)),H79) -> 0.27 | N79: =IF(J79="",F79*G79*(1-H79),J79) -> 502.1086 | O79: =VLOOKUP(C79,'Cleaned Customer Dim'!$A$2:$D$501,4,FALSE) -> 29 | P79: =VLOOKUP(C79,'Cleaned Customer Dim'!$A$2:$E$501,5,FALSE) -> Female | Q79: =VLOOKUP(C79,'Cleaned Customer Dim'!$A$2:$J$501,10,FALSE) -> Bronze | R79: =VLOOKUP(D79,'Cleaned Product Dim'!$A$2:$C$101,3,FALSE) -> Electronics | S79: =VLOOKUP(D79,'Cleaned Product Dim'!$A$2:$G$101,7,FALSE) -> 349.17 | T79: =VLOOKUP(D79,'Cleaned Product Dim'!$A$2:$H$101,8,FALSE) -> 476 | U79: =VLOOKUP(E79,'Cleaned Store Dim'!$A$2:$C$21,3,FALSE) -> North | V79: =VLOOKUP(E79,'Cleaned Store Dim'!$A$2:$E$21,5,FALSE) -> Flagship | W79: =VLOOKUP(E79,'Cleaned Store Dim'!$A$2:$F$21,6,FALSE) -> Jenniferstad
A80: SALE78 | B80: 45609 | C80: CUST1221 | D80: PROD83 | E80: STORE8 | F80: 2 | G80: 900.55 | H80: 0.16 | I80: Credit Card | J80: 1512.924 | K80: =IF(F80="",J80/(G80*(1-H80)),F80) -> 2 | L80: =IF(G80="",J80/(K80*(1-H80)),G80) -> 900.55 | M80: =IF(H80="",1-(J80/(K80*L80)),H80) -> 0.16 | N80: =IF(J80="",F80*G80*(1-H80),J80) -> 1512.924 | O80: =VLOOKUP(C80,'Cleaned Customer Dim'!$A$2:$D$501,4,FALSE) -> 38 | P80: =VLOOKUP(C80,'Cleaned Customer Dim'!$A$2:$E$501,5,FALSE) -> Male | Q80: =VLOOKUP(C80,'Cleaned Customer Dim'!$A$2:$J$501,10,FALSE) -> Platinum | R80: =VLOOKUP(D80,'Cleaned Product Dim'!$A$2:$C$101,3,FALSE) -> Beauty | S80: =VLOOKUP(D80,'Cleaned Product Dim'!$A$2:$G$101,7,FALSE) -> 250.41615 | T80: =VLOOKUP(D80,'Cleaned Product Dim'!$A$2:$H$101,8,FALSE) -> 159 | U80: =VLOOKUP(E80,'Cleaned Store Dim'!$A$2:$C$21,3,FALSE) -> West | V80: =VLOOKUP(E80,'Cleaned Store Dim'!$A$2:$E$21,5,FALSE) -> Online | W80: =VLOOKUP(E80,'Cleaned Store Dim'!$A$2:$F$21,6,FALSE) -> Thompson
A81: SALE79 | B81: 45150 | C81: CUST1115 | D81: PROD21 | E81: STORE2 | F81: 1 | G81: 341.17 | H81: 0.15 | I81: Credit Card | J81: 289.9945 | K81: =IF(F81="",J81/(G81*(1-H81)),F81) -> 1 | L81: =IF(G81="",J81/(K81*(1-H81)),G81) -> 341.17 | M81: =IF(H81="",1-(J81/(K81*L81)),H81) -> 0.15 | N81: =IF(J81="",F81*G81*(1-H81),J81) -> 289.9945 | O81: =VLOOKUP(C81,'Cleaned Customer Dim'!$A$2:$D$501,4,FALSE) -> 53 | P81: =VLOOKUP(C81,'Cleaned Customer Dim'!$A$2:$E$501,5,FALSE) -> Female | Q81: =VLOOKUP(C81,'Cleaned Customer Dim'!$A$2:$J$501,10,FALSE) -> Platinum | R81: =VLOOKUP(D81,'Cleaned Product Dim'!$A$2:$C$101,3,FALSE) -> Home | S81: =VLOOKUP(D81,'Cleaned Product Dim'!$A$2:$G$101,7,FALSE) -> 123.46 | T81: =VLOOKUP(D81,'Cleaned Product Dim'!$A$2:$H$101,8,FALSE) -> 76 | U81: =VLOOKUP(E81,'Cleaned Store Dim'!$A$2:$C$21,3,FALSE) -> South | V81: =VLOOKUP(E81,'Cleaned Store Dim'!$A$2:$E$21,5,FALSE) -> Outlet | W81: =VLOOKUP(E81,'Cleaned Store Dim'!$A$2:$F$21,6,FALSE) -> North Nancy
A82: SALE80 | B82: 45885 | C82: CUST1176 | D82: PROD52 | E82: STORE8 | F82: 1 | G82: 442.27 | H82: 0.06 | I82: COD | J82: 415.7338 | K82: =IF(F82="",J82/(G82*(1-H82)),F82) -> 1 | L82: =IF(G82="",J82/(K82*(1-H82)),G82) -> 442.27 | M82: =IF(H82="",1-(J82/(K82*L82)),H82) -> 0.06 | N82: =IF(J82="",F82*G82*(1-H82),J82) -> 415.7338 | O82: =VLOOKUP(C82,'Cleaned Customer Dim'!$A$2:$D$501,4,FALSE) -> 48 | P82: =VLOOKUP(C82,'Cleaned Customer Dim'!$A$2:$E$501,5,FALSE) -> Male | Q82: =VLOOKUP(C82,'Cleaned Customer Dim'!$A$2:$J$501,10,FALSE) -> Silver | R82: =VLOOKUP(D82,'Cleaned Product Dim'!$A$2:$C$101,3,FALSE) -> Sports | S82: =VLOOKUP(D82,'Cleaned Product Dim'!$A$2:$G$101,7,FALSE) -> 212.26 | T82: =VLOOKUP(D82,'Cleaned Product Dim'!$A$2:$H$101,8,FALSE) -> 82 | U82: =VLOOKUP(E82,'Cleaned Store Dim'!$A$2:$C$21,3,FALSE) -> West | V82: =VLOOKUP(E82,'Cleaned Store Dim'!$A$2:$E$21,5,FALSE) -> Online | W82: =VLOOKUP(E82,'Cleaned Store Dim'!$A$2:$F$21,6,FALSE) -> Thompson
A83: SALE81 | B83: 45616 | C83: CUST1253 | D83: PROD71 | E83: STORE9 | F83: 1 | G83: 363.73 | H83: 0.25 | I83: PayPal | J83: 272.7975 | K83: =IF(F83="",J83/(G83*(1-H83)),F83) -> 1 | L83: =IF(G83="",J83/(K83*(1-H83)),G83) -> 363.73 | M83: =IF(H83="",1-(J83/(K83*L83)),H83) -> 0.25 | N83: =IF(J83="",F83*G83*(1-H83),J83) -> 272.7975 | O83: =VLOOKUP(C83,'Cleaned Customer Dim'!$A$2:$D$501,4,FALSE) -> 32 | P83: =VLOOKUP(C83,'Cleaned Customer Dim'!$A$2:$E$501,5,FALSE) -> Male | Q83: =VLOOKUP(C83,'Cleaned Customer Dim'!$A$2:$J$501,10,FALSE) -> Bronze | R83: =VLOOKUP(D83,'Cleaned Product Dim'!$A$2:$C$101,3,FALSE) -> Beauty | S83: =VLOOKUP(D83,'Cleaned Product Dim'!$A$2:$G$101,7,FALSE) -> 214.32 | T83: =VLOOKUP(D83,'Cleaned Product Dim'!$A$2:$H$101,8,FALSE) -> 383 | U83: =VLOOKUP(E83,'Cleaned Store Dim'!$A$2:$C$21,3,FALSE) -> South | V83: =VLOOKUP(E83,'Cleaned Store Dim'!$A$2:$E$21,5,FALSE) -> Flagship | W83: =VLOOKUP(E83,'Cleaned Store Dim'!$A$2:$F$21,6,FALSE) -> Johnstad
A84: SALE82 | B84: 45518 | C84: CUST1378 | D84: PROD91 | E84: STORE17 | F84: 2 | G84: 601.33 | H84: 0.16 | I84: PayPal | J84: 1010.2344 | K84: =IF(F84="",J84/(G84*(1-H84)),F84) -> 2 | L84: =IF(G84="",J84/(K84*(1-H84)),G84) -> 601.33 | M84: =IF(H84="",1-(J84/(K84*L84)),H84) -> 0.16 | N84: =IF(J84="",F84*G84*(1-H84),J84) -> 1010.2344 | O84: =VLOOKUP(C84,'Cleaned Customer Dim'!$A$2:$D$501,4,FALSE) -> 44 | P84: =VLOOKUP(C84,'Cleaned Customer Dim'!$A$2:$E$501,5,FALSE) -> Female | Q84: =VLOOKUP(C84,'Cleaned Customer Dim'!$A$2:$J$501,10,FALSE) -> Bronze | R84: =VLOOKUP(D84,'Cleaned Product Dim'!$A$2:$C$101,3,FALSE) -> Clothing | S84: =VLOOKUP(D84,'Cleaned Product Dim'!$A$2:$G$101,7,FALSE) -> 438.25 | T84: =VLOOKUP(D84,'Cleaned Product Dim'!$A$2:$H$101,8,FALSE) -> 496 | U84: =VLOOKUP(E84,'Cleaned Store Dim'!$A$2:$C$21,3,FALSE) -> North | V84: =VLOOKUP(E84,'Cleaned Store Dim'!$A$2:$E$21,5,FALSE) -> Flagship | W84: =VLOOKUP(E84,'Cleaned Store Dim'!$A$2:$F$21,6,FALSE) -> Benson
A85: SALE83 | B85: 45427 | C85: CUST1403 | D85: PROD17 | E85: STORE18 | F85: 4 | G85: 34.39 | H85: 0.03 | I85: PayPal | J85: 133.4332 | K85: =IF(F85="",J85/(G85*(1-H85)),F85) -> 4 | L85: =IF(G85="",J85/(K85*(1-H85)),G85) -> 34.39 | M85: =IF(H85="",1-(J85/(K85*L85)),H85) -> 0.03 | N85: =IF(J85="",F85*G85*(1-H85),J85) -> 133.4332 | O85: =VLOOKUP(C85,'Cleaned Customer Dim'!$A$2:$D$501,4,FALSE) -> 34 | P85: =VLOOKUP(C85,'Cleaned Customer Dim'!$A$2:$E$501,5,FALSE) -> Male | Q85: =VLOOKUP(C85,'Cleaned Customer Dim'!$A$2:$J$501,10,FALSE) -> Bronze | R85: =VLOOKUP(D85,'Cleaned Product Dim'!$A$2:$C$101,3,FALSE) -> Sports | S85: =VLOOKUP(D85,'Cleaned Product Dim'!$A$2:$G$101,7,FALSE) -> 144.53 | T85: =VLOOKUP(D85,'Cleaned Product Dim'!$A$2:$H$101,8,FALSE) -> 367 | U85: =VLOOKUP(E85,'Cleaned Store Dim'!$A$2:$C$21,3,FALSE) -> East | V85: =VLOOKUP(E85,'Cleaned Store Dim'!$A$2:$E$21,5,FALSE) -> Flagship | W85: =VLOOKUP(E85,'Cleaned Store Dim'!$A$2:$F$21,6,FALSE) -> East Stevechester
A86: SALE84 | B86: 45150 | C86: CUST1423 | D86: PROD46 | E86: STORE17 | F86: 1 | G86: 773.57 | H86: 0.05 | I86: COD | K86: =IF(F86="",J86/(G86*(1-H86)),F86) -> 1 | L86: =IF(G86="",J86/(K86*(1-H86)),G86) -> 773.57 | M86: =IF(H86="",1-(J86/(K86*L86)),H86) -> 0.05 | N86: =IF(J86="",F86*G86*(1-H86),J86) -> 734.8915 | O86: =VLOOKUP(C86,'Cleaned Customer Dim'!$A$2:$D$501,4,FALSE) -> 35 | P86: =VLOOKUP(C86,'Cleaned Customer Dim'!$A$2:$E$501,5,FALSE) -> Male | Q86: =VLOOKUP(C86,'Cleaned Customer Dim'!$A$2:$J$501,10,FALSE) -> Silver | R86: =VLOOKUP(D86,'Cleaned Product Dim'!$A$2:$C$101,3,FALSE) -> Clothing | S86: =VLOOKUP(D86,'Cleaned Product Dim'!$A$2:$G$101,7,FALSE) -> 167.34 | T86: =VLOOKUP(D86,'Cleaned Product Dim'!$A$2:$H$101,8,FALSE) -> 296 | U86: =VLOOKUP(E86,'Cleaned Store Dim'!$A$2:$C$21,3,FALSE) -> North | V86: =VLOOKUP(E86,'Cleaned Store Dim'!$A$2:$E$21,5,FALSE) -> Flagship | W86: =VLOOKUP(E86,'Cleaned Store Dim'!$A$2:$F$21,6,FALSE) -> Benson
A87: SALE85 | B87: 45282 | C87: CUST1054 | D87: PROD88 | E87: STORE7 | F87: 4 | G87: 127.1 | H87: 0.24 | I87: COD | J87: 386.384 | K87: =IF(F87="",J87/(G87*(1-H87)),F87) -> 4 | L87: =IF(G87="",J87/(K87*(1-H87)),G87) -> 127.1 | M87: =IF(H87="",1-(J87/(K87*L87)),H87) -> 0.24 | N87: =IF(J87="",F87*G87*(1-H87),J87) -> 386.384 | O87: =VLOOKUP(C87,'Cleaned Customer Dim'!$A$2:$D$501,4,FALSE) -> 24 | P87: =VLOOKUP(C87,'Cleaned Customer Dim'!$A$2:$E$501,5,FALSE) -> Male | Q87: =VLOOKUP(C87,'Cleaned Customer Dim'!$A$2:$J$501,10,FALSE) -> Platinum | R87: =VLOOKUP(D87,'Cleaned Product Dim'!$A$2:$C$101,3,FALSE) -> Sports | S87: =VLOOKUP(D87,'Cleaned Product Dim'!$A$2:$G$101,7,FALSE) -> 131.24 | T87: =VLOOKUP(D87,'Cleaned Product Dim'!$A$2:$H$101,8,FALSE) -> 232 | U87: =VLOOKUP(E87,'Cleaned Store Dim'!$A$2:$C$21,3,FALSE) -> South | V87: =VLOOKUP(E87,'Cleaned Store Dim'!$A$2:$E$21,5,FALSE) -> Online | W87: =VLOOKUP(E87,'Cleaned Store Dim'!$A$2:$F$21,6,FALSE) -> Williamsport
A88: SALE86 | B88: 45574 | C88: CUST1303 | D88: PROD20 | E88: STORE3 | F88: 3 | G88: 899.58 | H88: 0.28 | I88: PayPal | J88: 1943.0928 | K88: =IF(F88="",J88/(G88*(1-H88)),F88) -> 3 | L88: =IF(G88="",J88/(K88*(1-H88)),G88) -> 899.58 | M88: =IF(H88="",1-(J88/(K88*L88)),H88) -> 0.28 | N88: =IF(J88="",F88*G88*(1-H88),J88) -> 1943.0928 | O88: =VLOOKUP(C88,'Cleaned Customer Dim'!$A$2:$D$501,4,FALSE) -> 23 | P88: =VLOOKUP(C88,'Cleaned Customer Dim'!$A$2:$E$501,5,FALSE) -> Female | Q88: =VLOOKUP(C88,'Cleaned Customer Dim'!$A$2:$J$501,10,FALSE) -> Platinum | R88: =VLOOKUP(D88,'Cleaned Product Dim'!$A$2:$C$101,3,FALSE) -> Sports | S88: =VLOOKUP(D88,'Cleaned Product Dim'!$A$2:$G$101,7,FALSE) -> 131.51 | T88: =VLOOKUP(D88,'Cleaned Product Dim'!$A$2:$H$101,8,FALSE) -> 281.95833 | U88: =VLOOKUP(E88,'Cleaned Store Dim'!$A$2:$C$21,3,FALSE) -> North | V88: =VLOOKUP(E88,'Cleaned Store Dim'!$A$2:$E$21,5,FALSE) -> Outlet | W88: =VLOOKUP(E88,'Cleaned Store Dim'!$A$2:$F$21,6,FALSE) -> Goldberg
A89: SALE87 | B89: 45873 | C89: CUST1327 | D89: PROD1 | E89: STORE10 | F89: 3 | G89: 964.39 | H89: 0.04 | I89: Credit Card | J89: 2777.4432 | K89: =IF(F89="",J89/(G89*(1-H89)),F89) -> 3 | L89: =IF(G89="",J89/(K89*(1-H89)),G89) -> 964.39 | M89: =IF(H89="",1-(J89/(K89*L89)),H89) -> 0.04 | N89: =IF(J89="",F89*G89*(1-H89),J89) -> 2777.4432 | O89: =VLOOKUP(C89,'Cleaned Customer Dim'!$A$2:$D$501,4,FALSE) -> 62 | P89: =VLOOKUP(C89,'Cleaned Customer Dim'!$A$2:$E$501,5,FALSE) -> Female | Q89: =VLOOKUP(C89,'Cleaned Customer Dim'!$A$2:$J$501,10,FALSE) -> Bronze | R89: =VLOOKUP(D89,'Cleaned Product Dim'!$A$2:$C$101,3,FALSE) -> Clothing | S89: =VLOOKUP(D89,'Cleaned Product Dim'!$A$2:$G$101,7,FALSE) -> 342.56 | T89: =VLOOKUP(D89,'Cleaned Product Dim'!$A$2:$H$101,8,FALSE) -> 181 | U89: =VLOOKUP(E89,'Cleaned Store Dim'!$A$2:$C$21,3,FALSE) -> East | V89: =VLOOKUP(E89,'Cleaned Store Dim'!$A$2:$E$21,5,FALSE) -> Online | W89: =VLOOKUP(E89,'Cleaned Store Dim'!$A$2:$F$21,6,FALSE) -> David
A90: SALE88 | B90: 45588 | C90: CUST1183 | D90: PROD38 | E90: STORE0 | F90: 2 | G90: 217.83 | H90: 0.14 | I90: PayPal | J90: 374.6676 | K90: =IF(F90="",J90/(G90*(1-H90)),F90) -> 2 | L90: =IF(G90="",J90/(K90*(1-H90)),G90) -> 217.83 | M90: =IF(H90="",1-(J90/(K90*L90)),H90) -> 0.14 | N90: =IF(J90="",F90*G90*(1-H90),J90) -> 374.6676 | O90: =VLOOKUP(C90,'Cleaned Customer Dim'!$A$2:$D$501,4,FALSE) -> 18 | P90: =VLOOKUP(C90,'Cleaned Customer Dim'!$A$2:$E$501,5,FALSE) -> Male | Q90: =VLOOKUP(C90,'Cleaned Customer Dim'!$A$2:$J$501,10,FALSE) -> Platinum | R90: =VLOOKUP(D90,'Cleaned Product Dim'!$A$2:$C$101,3,FALSE) -> Sports | S90: =VLOOKUP(D90,'Cleaned Product Dim'!$A$2:$G$101,7,FALSE) -> 135.61 | T90: =VLOOKUP(D90,'Cleaned Product Dim'!$A$2:$H$101,8,FALSE) -> 394 | U90: =VLOOKUP(E90,'Cleaned Store Dim'!$A$2:$C$21,3,FALSE) -> East | V90: =VLOOKUP(E90,'Cleaned Store Dim'!$A$2:$E$21,5,FALSE) -> Flagship | W90: =VLOOKUP(E90,'Cleaned Store Dim'!$A$2:$F$21,6,FALSE) -> Washington
A91: SALE89 | B91: 45937 | C91: CUST1143 | D91: PROD17 | E91: STORE1 | F91: 4 | G91: 187.71 | H91: 0.06 | I91: COD | J91: 705.7896 | K91: =IF(F91="",J91/(G91*(1-H91)),F91) -> 4 | L91: =IF(G91="",J91/(K91*(1-H91)),G91) -> 187.71 | M91: =IF(H91="",1-(J91/(K91*L91)),H91) -> 0.06 | N91: =IF(J91="",F91*G91*(1-H91),J91) -> 705.7896 | O91: =VLOOKUP(C91,'Cleaned Customer Dim'!$A$2:$D$501,4,FALSE) -> 46 | P91: =VLOOKUP(C91,'Cleaned Customer Dim'!$A$2:$E$501,5,FALSE) -> Male | Q91: =VLOOKUP(C91,'Cleaned Customer Dim'!$A$2:$J$501,10,FALSE) -> Bronze | R91: =VLOOKUP(D91,'Cleaned Product Dim'!$A$2:$C$101,3,FALSE) -> Sports | S91: =VLOOKUP(D91,'Cleaned Product Dim'!$A$2:$G$101,7,FALSE) -> 144.53 | T91: =VLOOKUP(D91,'Cleaned Product Dim'!$A$2:$H$101,8,FALSE) -> 367 | U91: =VLOOKUP(E91,'Cleaned Store Dim'!$A$2:$C$21,3,FALSE) -> North | V91: =VLOOKUP(E91,'Cleaned Store Dim'!$A$2:$E$21,5,FALSE) -> Flagship | W91: =VLOOKUP(E91,'Cleaned Store Dim'!$A$2:$F$21,6,FALSE) -> Daniel
A92: SALE90 | B92: 45636 | C92: CUST1010 | D92: PROD33 | E92: STORE18 | F92: 2 | G92: 350.12 | H92: 0.12 | I92: COD | J92: 616.2112 | K92: =IF(F92="",J92/(G92*(1-H92)),F92) -> 2 | L92: =IF(G92="",J92/(K92*(1-H92)),G92) -> 350.12 | M92: =IF(H92="",1-(J92/(K92*L92)),H92) -> 0.12 | N92: =IF(J92="",F92*G92*(1-H92),J92) -> 616.2112 | O92: =VLOOKUP(C92,'Cleaned Customer Dim'!$A$2:$D$501,4,FALSE) -> 53 | P92: =VLOOKUP(C92,'Cleaned Customer Dim'!$A$2:$E$501,5,FALSE) -> Male | Q92: =VLOOKUP(C92,'Cleaned Customer Dim'!$A$2:$J$501,10,FALSE) -> Bronze | R92: =VLOOKUP(D92,'Cleaned Product Dim'!$A$2:$C$101,3,FALSE) -> Home | S92: =VLOOKUP(D92,'Cleaned Product Dim'!$A$2:$G$101,7,FALSE) -> 179.77 | T92: =VLOOKUP(D92,'Cleaned Product Dim'!$A$2:$H$101,8,FALSE) -> 305 | U92: =VLOOKUP(E92,'Cleaned Store Dim'!$A$2:$C$21,3,FALSE) -> East | V92: =VLOOKUP(E92,'Cleaned Store Dim'!$A$2:$E$21,5,FALSE) -> Flagship | W92: =VLOOKUP(E92,'Cleaned Store Dim'!$A$2:$F$21,6,FALSE) -> East Stevechester
A93: SALE91 | B93: 45312 | C93: CUST1406 | D93: PROD16 | E93: STORE1 | F93: 4 | G93: 102.19 | H93: 0.17 | I93: PayPal | J93: 339.2708 | K93: =IF(F93="",J93/(G93*(1-H93)),F93) -> 4 | L93: =IF(G93="",J93/(K93*(1-H93)),G93) -> 102.19 | M93: =IF(H93="",1-(J93/(K93*L93)),H93) -> 0.17 | N93: =IF(J93="",F93*G93*(1-H93),J93) -> 339.2708 | O93: =VLOOKUP(C93,'Cleaned Customer Dim'!$A$2:$D$501,4,FALSE) -> 23 | P93: =VLOOKUP(C93,'Cleaned Customer Dim'!$A$2:$E$501,5,FALSE) -> Female | Q93: =VLOOKUP(C93,'Cleaned Customer Dim'!$A$2:$J$501,10,FALSE) -> Gold | R93: =VLOOKUP(D93,'Cleaned Product Dim'!$A$2:$C$101,3,FALSE) -> Beauty | S93: =VLOOKUP(D93,'Cleaned Product Dim'!$A$2:$G$101,7,FALSE) -> 337.42 | T93: =VLOOKUP(D93,'Cleaned Product Dim'!$A$2:$H$101,8,FALSE) -> 256 | U93: =VLOOKUP(E93,'Cleaned Store Dim'!$A$2:$C$21,3,FALSE) -> North | V93: =VLOOKUP(E93,'Cleaned Store Dim'!$A$2:$E$21,5,FALSE) -> Flagship | W93: =VLOOKUP(E93,'Cleaned Store Dim'!$A$2:$F$21,6,FALSE) -> Daniel
A94: SALE92 | B94: 45350 | C94: CUST1007 | D94: PROD86 | E94: STORE4 | F94: 1 | G94: 696.53 | H94: 0.17 | I94: Credit Card | J94: 578.1199 | K94: =IF(F94="",J94/(G94*(1-H94)),F94) -> 1 | L94: =IF(G94="",J94/(K94*(1-H94)),G94) -> 696.53 | M94: =IF(H94="",1-(J94/(K94*L94)),H94) -> 0.17 | N94: =IF(J94="",F94*G94*(1-H94),J94) -> 578.1199 | O94: =VLOOKUP(C94,'Cleaned Customer Dim'!$A$2:$D$501,4,FALSE) -> 29 | P94: =VLOOKUP(C94,'Cleaned Customer Dim'!$A$2:$E$501,5,FALSE) -> Female | Q94: =VLOOKUP(C94,'Cleaned Customer Dim'!$A$2:$J$501,10,FALSE) -> Bronze | R94: =VLOOKUP(D94,'Cleaned Product Dim'!$A$2:$C$101,3,FALSE) -> Home | S94: =VLOOKUP(D94,'Cleaned Product Dim'!$A$2:$G$101,7,FALSE) -> 176.07 | T94: =VLOOKUP(D94,'Cleaned Product Dim'!$A$2:$H$101,8,FALSE) -> 82 | U94: =VLOOKUP(E94,'Cleaned Store Dim'!$A$2:$C$21,3,FALSE) -> South | V94: =VLOOKUP(E94,'Cleaned Store Dim'!$A$2:$E$21,5,FALSE) -> Online | W94: =VLOOKUP(E94,'Cleaned Store Dim'!$A$2:$F$21,6,FALSE) -> Sharon
A95: SALE93 | B95: 45657 | C95: CUST1065 | D95: PROD19 | E95: STORE4 | F95: 2 | G95: 327.52 | H95: 0.15 | I95: PayPal | J95: 556.784 | K95: =IF(F95="",J95/(G95*(1-H95)),F95) -> 2 | L95: =IF(G95="",J95/(K95*(1-H95)),G95) -> 327.52 | M95: =IF(H95="",1-(J95/(K95*L95)),H95) -> 0.15 | N95: =IF(J95="",F95*G95*(1-H95),J95) -> 556.784 | O95: =VLOOKUP(C95,'Cleaned Customer Dim'!$A$2:$D$501,4,FALSE) -> 21 | P95: =VLOOKUP(C95,'Cleaned Customer Dim'!$A$2:$E$501,5,FALSE) -> Female | Q95: =VLOOKUP(C95,'Cleaned Customer Dim'!$A$2:$J$501,10,FALSE) -> Silver | R95: =VLOOKUP(D95,'Cleaned Product Dim'!$A$2:$C$101,3,FALSE) -> Sports | S95: =VLOOKUP(D95,'Cleaned Product Dim'!$A$2:$G$101,7,FALSE) -> 21.34 | T95: =VLOOKUP(D95,'Cleaned Product Dim'!$A$2:$H$101,8,FALSE) -> 65 | U95: =VLOOKUP(E95,'Cleaned Store Dim'!$A$2:$C$21,3,FALSE) -> South | V95: =VLOOKUP(E95,'Cleaned Store Dim'!$A$2:$E$21,5,FALSE) -> Online | W95: =VLOOKUP(E95,'Cleaned Store Dim'!$A$2:$F$21,6,FALSE) -> Sharon
A96: SALE94 | B96: 45530 | C96: CUST1298 | D96: PROD97 | E96: STORE19 | F96: 2 | G96: 569.36 | H96: 0.01 | I96: PayPal | K96: =IF(F96="",J96/(G96*(1-H96)),F96) -> 2 | L96: =IF(G96="",J96/(K96*(1-H96)),G96) -> 569.36 | M96: =IF(H96="",1-(J96/(K96*L96)),H96) -> 0.01 | N96: =IF(J96="",F96*G96*(1-H96),J96) -> 1127.3328 | O96: =VLOOKUP(C96,'Cleaned Customer Dim'!$A$2:$D$501,4,FALSE) -> 64 | P96: =VLOOKUP(C96,'Cleaned Customer Dim'!$A$2:$E$501,5,FALSE) -> Male | Q96: =VLOOKUP(C96,'Cleaned Customer Dim'!$A$2:$J$501,10,FALSE) -> Platinum | R96: =VLOOKUP(D96,'Cleaned Product Dim'!$A$2:$C$101,3,FALSE) -> Sports | S96: =VLOOKUP(D96,'Cleaned Product Dim'!$A$2:$G$101,7,FALSE) -> 245.98 | T96: =VLOOKUP(D96,'Cleaned Product Dim'!$A$2:$H$101,8,FALSE) -> 471 | U96: =VLOOKUP(E96,'Cleaned Store Dim'!$A$2:$C$21,3,FALSE) -> East | V96: =VLOOKUP(E96,'Cleaned Store Dim'!$A$2:$E$21,5,FALSE) -> Online | W96: =VLOOKUP(E96,'Cleaned Store Dim'!$A$2:$F$21,6,FALSE) -> Vasquez
A97: SALE95 | B97: 45556 | C97: CUST1321 | D97: PROD99 | E97: STORE6 | F97: 2 | G97: 68.29 | H97: 0.14 | I97: COD | J97: 117.4588 | K97: =IF(F97="",J97/(G97*(1-H97)),F97) -> 2 | L97: =IF(G97="",J97/(K97*(1-H97)),G97) -> 68.29 | M97: =IF(H97="",1-(J97/(K97*L97)),H97) -> 0.14 | N97: =IF(J97="",F97*G97*(1-H97),J97) -> 117.4588 | O97: =VLOOKUP(C97,'Cleaned Customer Dim'!$A$2:$D$501,4,FALSE) -> 21 | P97: =VLOOKUP(C97,'Cleaned Customer Dim'!$A$2:$E$501,5,FALSE) -> Female | Q97: =VLOOKUP(C97,'Cleaned Customer Dim'!$A$2:$J$501,10,FALSE) -> Bronze | R97: =VLOOKUP(D97,'Cleaned Product Dim'!$A$2:$C$101,3,FALSE) -> Home | S97: =VLOOKUP(D97,'Cleaned Product Dim'!$A$2:$G$101,7,FALSE) -> 201.41 | T97: =VLOOKUP(D97,'Cleaned Product Dim'!$A$2:$H$101,8,FALSE) -> 146 | U97: =VLOOKUP(E97,'Cleaned Store Dim'!$A$2:$C$21,3,FALSE) -> East | V97: =VLOOKUP(E97,'Cleaned Store Dim'!$A$2:$E$21,5,FALSE) -> Online | W97: =VLOOKUP(E97,'Cleaned Store Dim'!$A$2:$F$21,6,FALSE) -> Joseph
A98: SALE96 | B98: 45523 | C98: CUST1244 | D98: PROD50 | E98: STORE10 | F98: 1 | G98: 842.9 | H98: 0.06 | I98: COD | J98: 792.326 | K98: =IF(F98="",J98/(G98*(1-H98)),F98) -> 1 | L98: =IF(G98="",J98/(K98*(1-H98)),G98) -> 842.9 | M98: =IF(H98="",1-(J98/(K98*L98)),H98) -> 0.06 | N98: =IF(J98="",F98*G98*(1-H98),J98) -> 792.326 | O98: =VLOOKUP(C98,'Cleaned Customer Dim'!$A$2:$D$501,4,FALSE) -> 19 | P98: =VLOOKUP(C98,'Cleaned Customer Dim'!$A$2:$E$501,5,FALSE) -> Male | Q98: =VLOOKUP(C98,'Cleaned Customer Dim'!$A$2:$J$501,10,FALSE) -> Bronze | R98: =VLOOKUP(D98,'Cleaned Product Dim'!$A$2:$C$101,3,FALSE) -> Sports | S98: =VLOOKUP(D98,'Cleaned Product Dim'!$A$2:$G$101,7,FALSE) -> 190.29 | T98: =VLOOKUP(D98,'Cleaned Product Dim'!$A$2:$H$101,8,FALSE) -> 260 | U98: =VLOOKUP(E98,'Cleaned Store Dim'!$A$2:$C$21,3,FALSE) -> East | V98: =VLOOKUP(E98,'Cleaned Store Dim'!$A$2:$E$21,5,FALSE) -> Online | W98: =VLOOKUP(E98,'Cleaned Store Dim'!$A$2:$F$21,6,FALSE) -> David
A99: SALE97 | B99: 45587 | C99: CUST1287 | D99: PROD3 | E99: STORE3 | F99: 3 | G99: 751.94 | H99: 0.26 | I99: PayPal | J99: 1669.3068 | K99: =IF(F99="",J99/(G99*(1-H99)),F99) -> 3 | L99: =IF(G99="",J99/(K99*(1-H99)),G99) -> 751.94 | M99: =IF(H99="",1-(J99/(K99*L99)),H99) -> 0.26 | N99: =IF(J99="",F99*G99*(1-H99),J99) -> 1669.3068 | O99: =VLOOKUP(C99,'Cleaned Customer Dim'!$A$2:$D$501,4,FALSE) -> 22 | P99: =VLOOKUP(C99,'Cleaned Customer Dim'!$A$2:$E$501,5,FALSE) -> Female | Q99: =VLOOKUP(C99,'Cleaned Customer Dim'!$A$2:$J$501,10,FALSE) -> Gold | R99: =VLOOKUP(D99,'Cleaned Product Dim'!$A$2:$C$101,3,FALSE) -> Clothing | S99: =VLOOKUP(D99,'Cleaned Product Dim'!$A$2:$G$101,7,FALSE) -> 364.67 | T99: =VLOOKUP(D99,'Cleaned Product Dim'!$A$2:$H$101,8,FALSE) -> 452 | U99: =VLOOKUP(E99,'Cleaned Store Dim'!$A$2:$C$21,3,FALSE) -> North | V99: =VLOOKUP(E99,'Cleaned Store Dim'!$A$2:$E$21,5,FALSE) -> Outlet | W99: =VLOOKUP(E99,'Cleaned Store Dim'!$A$2:$F$21,6,FALSE) -> Goldberg
A100: SALE98 | B100: 45580 | C100: CUST1131 | D100: PROD56 | E100: STORE7 | F100: 4 | G100: 476.28 | H100: 0.17 | I100: Credit Card | J100: 1581.2496 | K100: =IF(F100="",J100/(G100*(1-H100)),F100) -> 4 | L100: =IF(G100="",J100/(K100*(1-H100)),G100) -> 476.28 | M100: =IF(H100="",1-(J100/(K100*L100)),H100) -> 0.17 | N100: =IF(J100="",F100*G100*(1-H100),J100) -> 1581.2496 | O100: =VLOOKUP(C100,'Cleaned Customer Dim'!$A$2:$D$501,4,FALSE) -> 34 | P100: =VLOOKUP(C100,'Cleaned Customer Dim'!$A$2:$E$501,5,FALSE) -> Female | Q100: =VLOOKUP(C100,'Cleaned Customer Dim'!$A$2:$J$501,10,FALSE) -> Bronze | R100: =VLOOKUP(D100,'Cleaned Product Dim'!$A$2:$C$101,3,FALSE) -> Home | S100: =VLOOKUP(D100,'Cleaned Product Dim'!$A$2:$G$101,7,FALSE) -> 461.47 | T100: =VLOOKUP(D100,'Cleaned Product Dim'!$A$2:$H$101,8,FALSE) -> 190 | U100: =VLOOKUP(E100,'Cleaned Store Dim'!$A$2:$C$21,3,FALSE) -> South | V100: =VLOOKUP(E100,'Cleaned Store Dim'!$A$2:$E$21,5,FALSE) -> Online | W100: =VLOOKUP(E100,'Cleaned Store Dim'!$A$2:$F$21,6,FALSE) -> Williamsport
...

Sheet Sales Pivot Table & Chart
A1: Customer_ID | B1: All | G1: Product_ID | H1: All | K1: Store_ID | L1: All
A3: Count of Age | B3: Column Labels | G3: Average of Age | H3: Column Labels | K3: Count of New City (Replace) | L3: Column Labels
A4: Row Labels | B4: Female | C4: Male | G4: Row Labels | H4: Female | I4: Male | K4: Row Labels | L4: Outlet
A5: Bronze | B5: 7 | C5: 6 | G5: Beauty | H5: 37 | I5: 43.666667 | K5: North | L5: 23
A6: Gold | B6: 3 | C6: 5 | G6: Clothing | H6: 41.8 | I6: 46.666667 | K6: South | L6: 22
A7: Platinum | B7: 10 | C7: 6 | G7: Electronics | H7: 40.857143 | I7: 43.4
A8: Silver | B8: 6 | C8: 2 | G8: Home | H8: 48.666667 | I8: 44.4
G9: Sports | H9: 42 | I9: 37
A24: Customer_ID | B24: All
A26: Distinct Count of Age | B26: Column Labels | K26: Sales_ID | L26: All
A27: Row Labels | B27: COD | C27: Credit Card | D27: PayPal | Q27: Sales_ID | R27: All
A28: North | B28: 7 | C28: 10 | D28: 4 | K28: Count of New City (Replace) | L28: Column Labels
A29: South | B29: 6 | C29: 7 | D29: 7 | K29: Row Labels | L29: COD | M29: Credit Card | N29: PayPal | Q29: Row Labels | R29: Count of New Unit Price | S29: Count of New Discount | T29: Count of New Total Amount
K30: 1 | L30: 4 | M30: 6 | N30: 4 | Q30: 1 | R30: 14 | S30: 14 | T30: 14
K31: 2 | L31: 3 | M31: 4 | N31: 5 | Q31: 2 | R31: 12 | S31: 12 | T31: 12
K32: 3 | L32: 4 | M32: 4 | N32: 1 | Q32: 3 | R32: 9 | S32: 9 | T32: 9
K33: 4 | L33: 3 | M33: 5 | N33: 2 | Q33: 4 | R33: 10 | S33: 10 | T33: 10
G39: Row Labels | H39: Sum of Unit Cost | I39: Sum of Stock
G40: Beauty | H40: 1818.7662 | I40: 2147
G41: Clothing | H41: 2039.9527 | I41: 1953
G42: Electronics | H42: 4127.06 | I42: 3409
G43: Home | H43: 2531.78 | I43: 2293
G44: Sports | H44: 1286.47 | I44: 2049

Sheet Sales Dashboard
A1: SALES DASHBOARD

Sheet Summary
A1: Summary of capstone Project
A2: Replace:
A23: Finding missing value | C23: and filling it
A48: Removing duplicate:
A74: Data Analysis using analysis toolpak
A99: Vlookup Merging table
A126: Pivot table and chart
